package com.ireadercity.b2.ui;

final class j
  implements Runnable
{
  j(AIReaderActivity paramAIReaderActivity) {}
  
  /* Error */
  public final void run()
  {
    // Byte code:
    //   0: aconst_null
    //   1: astore_1
    //   2: getstatic 26	com/ireadercity/b2/h/r:a	Ljava/util/Map;
    //   5: ifnull +73 -> 78
    //   8: new 28	java/io/File
    //   11: dup
    //   12: new 30	java/lang/StringBuilder
    //   15: dup
    //   16: invokespecial 31	java/lang/StringBuilder:<init>	()V
    //   19: getstatic 37	com/ireadercity/b2/a:n	Ljava/lang/String;
    //   22: invokevirtual 41	java/lang/StringBuilder:append	(Ljava/lang/String;)Ljava/lang/StringBuilder;
    //   25: ldc 43
    //   27: invokevirtual 41	java/lang/StringBuilder:append	(Ljava/lang/String;)Ljava/lang/StringBuilder;
    //   30: invokevirtual 47	java/lang/StringBuilder:toString	()Ljava/lang/String;
    //   33: invokespecial 50	java/io/File:<init>	(Ljava/lang/String;)V
    //   36: astore_2
    //   37: aload_2
    //   38: invokevirtual 54	java/io/File:exists	()Z
    //   41: ifne +8 -> 49
    //   44: aload_2
    //   45: invokevirtual 57	java/io/File:createNewFile	()Z
    //   48: pop
    //   49: new 59	java/io/ObjectOutputStream
    //   52: dup
    //   53: new 61	java/io/FileOutputStream
    //   56: dup
    //   57: aload_2
    //   58: invokespecial 64	java/io/FileOutputStream:<init>	(Ljava/io/File;)V
    //   61: invokespecial 67	java/io/ObjectOutputStream:<init>	(Ljava/io/OutputStream;)V
    //   64: astore_2
    //   65: aload_2
    //   66: astore_1
    //   67: aload_2
    //   68: getstatic 26	com/ireadercity/b2/h/r:a	Ljava/util/Map;
    //   71: invokevirtual 71	java/io/ObjectOutputStream:writeObject	(Ljava/lang/Object;)V
    //   74: aload_2
    //   75: invokevirtual 74	java/io/ObjectOutputStream:close	()V
    //   78: aconst_null
    //   79: putstatic 26	com/ireadercity/b2/h/r:a	Ljava/util/Map;
    //   82: aload_0
    //   83: getfield 12	com/ireadercity/b2/ui/j:a	Lcom/ireadercity/b2/ui/AIReaderActivity;
    //   86: invokevirtual 80	com/ireadercity/b2/ui/AIReaderActivity:getApplicationContext	()Landroid/content/Context;
    //   89: invokestatic 85	com/ireadercity/b2/e/a:a	(Landroid/content/Context;)Lcom/ireadercity/b2/e/a;
    //   92: invokevirtual 87	com/ireadercity/b2/e/a:a	()Z
    //   95: pop
    //   96: aload_0
    //   97: getfield 12	com/ireadercity/b2/ui/j:a	Lcom/ireadercity/b2/ui/AIReaderActivity;
    //   100: invokevirtual 80	com/ireadercity/b2/ui/AIReaderActivity:getApplicationContext	()Landroid/content/Context;
    //   103: invokestatic 85	com/ireadercity/b2/e/a:a	(Landroid/content/Context;)Lcom/ireadercity/b2/e/a;
    //   106: invokevirtual 90	com/ireadercity/b2/e/a:c	()V
    //   109: aload_0
    //   110: getfield 12	com/ireadercity/b2/ui/j:a	Lcom/ireadercity/b2/ui/AIReaderActivity;
    //   113: astore_1
    //   114: invokestatic 93	com/ireadercity/b2/ui/AIReaderActivity:g	()V
    //   117: invokestatic 99	android/os/Process:myPid	()I
    //   120: invokestatic 103	android/os/Process:killProcess	(I)V
    //   123: return
    //   124: astore_1
    //   125: aload_1
    //   126: invokevirtual 106	java/io/IOException:printStackTrace	()V
    //   129: goto -51 -> 78
    //   132: astore_3
    //   133: aconst_null
    //   134: astore_2
    //   135: aload_2
    //   136: astore_1
    //   137: aload_3
    //   138: invokevirtual 107	java/io/FileNotFoundException:printStackTrace	()V
    //   141: aload_2
    //   142: ifnull -64 -> 78
    //   145: aload_2
    //   146: invokevirtual 74	java/io/ObjectOutputStream:close	()V
    //   149: goto -71 -> 78
    //   152: astore_1
    //   153: aload_1
    //   154: invokevirtual 106	java/io/IOException:printStackTrace	()V
    //   157: goto -79 -> 78
    //   160: astore_3
    //   161: aconst_null
    //   162: astore_2
    //   163: aload_2
    //   164: astore_1
    //   165: aload_3
    //   166: invokevirtual 106	java/io/IOException:printStackTrace	()V
    //   169: aload_2
    //   170: ifnull -92 -> 78
    //   173: aload_2
    //   174: invokevirtual 74	java/io/ObjectOutputStream:close	()V
    //   177: goto -99 -> 78
    //   180: astore_1
    //   181: aload_1
    //   182: invokevirtual 106	java/io/IOException:printStackTrace	()V
    //   185: goto -107 -> 78
    //   188: astore_3
    //   189: aload_1
    //   190: astore_2
    //   191: aload_3
    //   192: astore_1
    //   193: aload_2
    //   194: ifnull +7 -> 201
    //   197: aload_2
    //   198: invokevirtual 74	java/io/ObjectOutputStream:close	()V
    //   201: aload_1
    //   202: athrow
    //   203: astore_2
    //   204: aload_2
    //   205: invokevirtual 106	java/io/IOException:printStackTrace	()V
    //   208: goto -7 -> 201
    //   211: astore_3
    //   212: aload_1
    //   213: astore_2
    //   214: aload_3
    //   215: astore_1
    //   216: goto -23 -> 193
    //   219: astore_3
    //   220: goto -57 -> 163
    //   223: astore_3
    //   224: goto -89 -> 135
    // Local variable table:
    //   start	length	slot	name	signature
    //   0	227	0	this	j
    //   1	113	1	localObject1	Object
    //   124	2	1	localIOException1	java.io.IOException
    //   136	1	1	localObject2	Object
    //   152	2	1	localIOException2	java.io.IOException
    //   164	1	1	localObject3	Object
    //   180	10	1	localIOException3	java.io.IOException
    //   192	24	1	localObject4	Object
    //   36	162	2	localObject5	Object
    //   203	2	2	localIOException4	java.io.IOException
    //   213	1	2	localObject6	Object
    //   132	6	3	localFileNotFoundException1	java.io.FileNotFoundException
    //   160	6	3	localIOException5	java.io.IOException
    //   188	4	3	localObject7	Object
    //   211	4	3	localObject8	Object
    //   219	1	3	localIOException6	java.io.IOException
    //   223	1	3	localFileNotFoundException2	java.io.FileNotFoundException
    // Exception table:
    //   from	to	target	type
    //   74	78	124	java/io/IOException
    //   8	49	132	java/io/FileNotFoundException
    //   49	65	132	java/io/FileNotFoundException
    //   145	149	152	java/io/IOException
    //   8	49	160	java/io/IOException
    //   49	65	160	java/io/IOException
    //   173	177	180	java/io/IOException
    //   8	49	188	finally
    //   49	65	188	finally
    //   197	201	203	java/io/IOException
    //   67	74	211	finally
    //   137	141	211	finally
    //   165	169	211	finally
    //   67	74	219	java/io/IOException
    //   67	74	223	java/io/FileNotFoundException
  }
}


/* Location:              E:\project\angent\dex2jar-2.0\classes-dex2jar.jar!\com\ireadercity\b2\ui\j.class
 * Java compiler version: 6 (50.0)
 * JD-Core Version:       0.7.1
 */