package com.ireadercity.b2.h;

final class h
  extends Thread
{
  h(d paramd, String paramString) {}
  
  /* Error */
  public final void run()
  {
    // Byte code:
    //   0: new 27	org/apache/http/impl/client/DefaultHttpClient
    //   3: dup
    //   4: invokespecial 28	org/apache/http/impl/client/DefaultHttpClient:<init>	()V
    //   7: astore 5
    //   9: new 30	org/apache/http/client/methods/HttpGet
    //   12: dup
    //   13: aload_0
    //   14: getfield 14	com/ireadercity/b2/h/h:a	Ljava/lang/String;
    //   17: invokespecial 33	org/apache/http/client/methods/HttpGet:<init>	(Ljava/lang/String;)V
    //   20: astore 6
    //   22: aconst_null
    //   23: astore 4
    //   25: aconst_null
    //   26: astore_3
    //   27: aload 4
    //   29: astore_2
    //   30: aload 5
    //   32: aload 6
    //   34: invokeinterface 39 2 0
    //   39: invokeinterface 45 1 0
    //   44: astore 5
    //   46: aload 4
    //   48: astore_2
    //   49: aload 5
    //   51: invokeinterface 51 1 0
    //   56: pop2
    //   57: aload 4
    //   59: astore_2
    //   60: aload 5
    //   62: invokeinterface 55 1 0
    //   67: astore 7
    //   69: aload 7
    //   71: ifnull +130 -> 201
    //   74: aload 4
    //   76: astore_2
    //   77: aload_0
    //   78: getfield 12	com/ireadercity/b2/h/h:b	Lcom/ireadercity/b2/h/d;
    //   81: invokestatic 61	com/ireadercity/b2/a:c	()Ljava/lang/String;
    //   84: invokestatic 66	com/ireadercity/b2/h/d:b	(Lcom/ireadercity/b2/h/d;Ljava/lang/String;)Ljava/lang/String;
    //   87: pop
    //   88: aload 4
    //   90: astore_2
    //   91: new 68	java/io/FileOutputStream
    //   94: dup
    //   95: new 70	java/io/File
    //   98: dup
    //   99: aload_0
    //   100: getfield 12	com/ireadercity/b2/h/h:b	Lcom/ireadercity/b2/h/d;
    //   103: invokestatic 74	com/ireadercity/b2/h/d:d	(Lcom/ireadercity/b2/h/d;)Ljava/lang/String;
    //   106: invokespecial 75	java/io/File:<init>	(Ljava/lang/String;)V
    //   109: invokespecial 78	java/io/FileOutputStream:<init>	(Ljava/io/File;)V
    //   112: astore 4
    //   114: aload 4
    //   116: astore 5
    //   118: aload 4
    //   120: astore_3
    //   121: aload 4
    //   123: astore 6
    //   125: sipush 1024
    //   128: newarray <illegal type>
    //   130: astore 8
    //   132: aload 4
    //   134: astore 5
    //   136: aload 4
    //   138: astore_3
    //   139: aload 4
    //   141: astore 6
    //   143: aload 7
    //   145: aload 8
    //   147: invokevirtual 84	java/io/InputStream:read	([B)I
    //   150: istore_1
    //   151: aload 4
    //   153: astore_2
    //   154: iload_1
    //   155: iconst_m1
    //   156: if_icmpeq +47 -> 203
    //   159: aload 4
    //   161: astore 5
    //   163: aload 4
    //   165: astore_3
    //   166: aload 4
    //   168: astore 6
    //   170: aload 4
    //   172: aload 8
    //   174: iconst_0
    //   175: iload_1
    //   176: invokevirtual 88	java/io/FileOutputStream:write	([BII)V
    //   179: goto -47 -> 132
    //   182: astore_2
    //   183: aload 5
    //   185: astore_3
    //   186: aload_2
    //   187: invokevirtual 91	org/apache/http/client/ClientProtocolException:printStackTrace	()V
    //   190: aload 5
    //   192: ifnull +8 -> 200
    //   195: aload 5
    //   197: invokevirtual 94	java/io/FileOutputStream:close	()V
    //   200: return
    //   201: aconst_null
    //   202: astore_2
    //   203: aload_2
    //   204: astore 5
    //   206: aload_2
    //   207: astore_3
    //   208: aload_2
    //   209: astore 6
    //   211: aload_2
    //   212: invokevirtual 97	java/io/FileOutputStream:flush	()V
    //   215: aload_2
    //   216: astore 5
    //   218: aload_2
    //   219: astore_3
    //   220: aload_2
    //   221: astore 6
    //   223: aload_0
    //   224: getfield 12	com/ireadercity/b2/h/h:b	Lcom/ireadercity/b2/h/d;
    //   227: invokevirtual 99	com/ireadercity/b2/h/d:a	()V
    //   230: aload_2
    //   231: ifnull -31 -> 200
    //   234: aload_2
    //   235: invokevirtual 94	java/io/FileOutputStream:close	()V
    //   238: return
    //   239: astore_2
    //   240: return
    //   241: astore 4
    //   243: aload_3
    //   244: astore_2
    //   245: aload 4
    //   247: invokevirtual 100	java/io/IOException:printStackTrace	()V
    //   250: aload_3
    //   251: ifnull -51 -> 200
    //   254: aload_3
    //   255: invokevirtual 94	java/io/FileOutputStream:close	()V
    //   258: return
    //   259: astore_2
    //   260: return
    //   261: astore 4
    //   263: aload_2
    //   264: astore_3
    //   265: aload 4
    //   267: astore_2
    //   268: aload_3
    //   269: ifnull +7 -> 276
    //   272: aload_3
    //   273: invokevirtual 94	java/io/FileOutputStream:close	()V
    //   276: aload_2
    //   277: athrow
    //   278: astore_2
    //   279: return
    //   280: astore_3
    //   281: goto -5 -> 276
    //   284: astore_2
    //   285: goto -17 -> 268
    //   288: astore 4
    //   290: aload 6
    //   292: astore_3
    //   293: goto -50 -> 243
    //   296: astore_2
    //   297: aconst_null
    //   298: astore 5
    //   300: goto -117 -> 183
    // Local variable table:
    //   start	length	slot	name	signature
    //   0	303	0	this	h
    //   150	26	1	i	int
    //   29	125	2	localFileOutputStream1	java.io.FileOutputStream
    //   182	5	2	localClientProtocolException1	org.apache.http.client.ClientProtocolException
    //   202	33	2	localObject1	Object
    //   239	1	2	localException1	Exception
    //   244	1	2	localObject2	Object
    //   259	5	2	localException2	Exception
    //   267	10	2	localObject3	Object
    //   278	1	2	localException3	Exception
    //   284	1	2	localObject4	Object
    //   296	1	2	localClientProtocolException2	org.apache.http.client.ClientProtocolException
    //   26	247	3	localObject5	Object
    //   280	1	3	localException4	Exception
    //   292	1	3	localObject6	Object
    //   23	148	4	localFileOutputStream2	java.io.FileOutputStream
    //   241	5	4	localIOException1	java.io.IOException
    //   261	5	4	localObject7	Object
    //   288	1	4	localIOException2	java.io.IOException
    //   7	292	5	localObject8	Object
    //   20	271	6	localObject9	Object
    //   67	77	7	localInputStream	java.io.InputStream
    //   130	43	8	arrayOfByte	byte[]
    // Exception table:
    //   from	to	target	type
    //   125	132	182	org/apache/http/client/ClientProtocolException
    //   143	151	182	org/apache/http/client/ClientProtocolException
    //   170	179	182	org/apache/http/client/ClientProtocolException
    //   211	215	182	org/apache/http/client/ClientProtocolException
    //   223	230	182	org/apache/http/client/ClientProtocolException
    //   234	238	239	java/lang/Exception
    //   30	46	241	java/io/IOException
    //   49	57	241	java/io/IOException
    //   60	69	241	java/io/IOException
    //   77	88	241	java/io/IOException
    //   91	114	241	java/io/IOException
    //   254	258	259	java/lang/Exception
    //   30	46	261	finally
    //   49	57	261	finally
    //   60	69	261	finally
    //   77	88	261	finally
    //   91	114	261	finally
    //   245	250	261	finally
    //   195	200	278	java/lang/Exception
    //   272	276	280	java/lang/Exception
    //   125	132	284	finally
    //   143	151	284	finally
    //   170	179	284	finally
    //   186	190	284	finally
    //   211	215	284	finally
    //   223	230	284	finally
    //   125	132	288	java/io/IOException
    //   143	151	288	java/io/IOException
    //   170	179	288	java/io/IOException
    //   211	215	288	java/io/IOException
    //   223	230	288	java/io/IOException
    //   30	46	296	org/apache/http/client/ClientProtocolException
    //   49	57	296	org/apache/http/client/ClientProtocolException
    //   60	69	296	org/apache/http/client/ClientProtocolException
    //   77	88	296	org/apache/http/client/ClientProtocolException
    //   91	114	296	org/apache/http/client/ClientProtocolException
  }
}


/* Location:              E:\project\angent\dex2jar-2.0\classes-dex2jar.jar!\com\ireadercity\b2\h\h.class
 * Java compiler version: 6 (50.0)
 * JD-Core Version:       0.7.1
 */