package com.taobao.munion.net;

import android.net.Proxy;
import com.taobao.munion.common.MunionConfigManager;
import com.umeng.newxp.common.persistence.PersistentCookieStore;
import org.apache.http.HttpHost;
import org.apache.http.HttpVersion;
import org.apache.http.client.HttpClient;
import org.apache.http.impl.client.DefaultHttpClient;
import org.apache.http.params.BasicHttpParams;
import org.apache.http.params.HttpProtocolParams;

public class b
{
  static b.f a;
  static b.f b;
  static b.b c;
  public static final String d = "response-code";
  public static final String e = "last-modified";
  public static final String f = "content-type";
  public static final String g = "location";
  public static final String h = "accept-encoding";
  public static final String i = "expires";
  public static final String j = "cache-control";
  public static final String k = "if-modified-since";
  public static final String l = "content-length";
  public static final String m = "content-range";
  public static final String n = "set-cookie";
  private static final int o = 5;
  private static c u;
  private e p;
  private String q;
  private boolean r;
  private int s = 0;
  private long t = 0L;
  private i v = null;
  
  public b(String paramString, e parame)
  {
    if (a == null) {
      a = new b.f(this);
    }
    if (b == null) {
      b = new b.f(this);
    }
    if (c == null) {
      c = new b.b(this);
    }
    this.q = paramString;
    if (parame != null) {}
    for (this.p = parame;; this.p = new e())
    {
      System.setProperty("http.keepAlive", "false");
      return;
    }
  }
  
  static void a(c paramc)
  {
    u = paramc;
  }
  
  private DefaultHttpClient d()
  {
    BasicHttpParams localBasicHttpParams = new BasicHttpParams();
    localBasicHttpParams.setIntParameter("http.socket.timeout", 10000);
    localBasicHttpParams.setIntParameter("http.connection.timeout", 10000);
    localBasicHttpParams.setIntParameter("http.socket.buffer-size", 32768);
    HttpProtocolParams.setVersion(localBasicHttpParams, HttpVersion.HTTP_1_1);
    HttpProtocolParams.setContentCharset(localBasicHttpParams, "UTF-8");
    DefaultHttpClient localDefaultHttpClient = new DefaultHttpClient(localBasicHttpParams);
    localDefaultHttpClient.setRedirectHandler(new b.1(this));
    String str = Proxy.getDefaultHost();
    int i1 = Proxy.getDefaultPort();
    if (str != null) {
      localBasicHttpParams.setParameter("http.route.default-proxy", new HttpHost(str, i1));
    }
    return localDefaultHttpClient;
  }
  
  /* Error */
  private h e()
  {
    // Byte code:
    //   0: aload_0
    //   1: getfield 85	com/taobao/munion/net/b:q	Ljava/lang/String;
    //   4: astore 16
    //   6: aload_0
    //   7: invokestatic 183	java/lang/System:currentTimeMillis	()J
    //   10: putfield 67	com/taobao/munion/net/b:t	J
    //   13: ldc -71
    //   15: aload 16
    //   17: iconst_0
    //   18: iconst_5
    //   19: invokevirtual 191	java/lang/String:substring	(II)Ljava/lang/String;
    //   22: invokevirtual 195	java/lang/String:compareToIgnoreCase	(Ljava/lang/String;)I
    //   25: ifne +683 -> 708
    //   28: iconst_1
    //   29: istore_3
    //   30: aconst_null
    //   31: astore 22
    //   33: aconst_null
    //   34: astore 54
    //   36: aconst_null
    //   37: astore 23
    //   39: aconst_null
    //   40: astore 51
    //   42: aconst_null
    //   43: astore 21
    //   45: aconst_null
    //   46: astore 60
    //   48: aconst_null
    //   49: astore 50
    //   51: aconst_null
    //   52: astore 32
    //   54: aconst_null
    //   55: astore 57
    //   57: aconst_null
    //   58: astore 30
    //   60: aconst_null
    //   61: astore 58
    //   63: aconst_null
    //   64: astore 55
    //   66: aconst_null
    //   67: astore 56
    //   69: aconst_null
    //   70: astore 25
    //   72: aconst_null
    //   73: astore 33
    //   75: aconst_null
    //   76: astore 62
    //   78: aconst_null
    //   79: astore 31
    //   81: aconst_null
    //   82: astore 61
    //   84: aconst_null
    //   85: astore 63
    //   87: aconst_null
    //   88: astore 24
    //   90: aconst_null
    //   91: astore 42
    //   93: aconst_null
    //   94: astore 48
    //   96: aconst_null
    //   97: astore 40
    //   99: aconst_null
    //   100: astore 46
    //   102: aconst_null
    //   103: astore 49
    //   105: aconst_null
    //   106: astore 47
    //   108: aconst_null
    //   109: astore 44
    //   111: aconst_null
    //   112: astore 43
    //   114: aconst_null
    //   115: astore 59
    //   117: aconst_null
    //   118: astore 41
    //   120: aconst_null
    //   121: astore 53
    //   123: aconst_null
    //   124: astore 52
    //   126: aconst_null
    //   127: astore 45
    //   129: iconst_m1
    //   130: istore_1
    //   131: aconst_null
    //   132: astore 26
    //   134: invokestatic 200	com/taobao/munion/net/f:a	()Lcom/taobao/munion/net/f;
    //   137: invokevirtual 202	com/taobao/munion/net/f:d	()I
    //   140: istore 10
    //   142: aload 16
    //   144: astore 18
    //   146: aload 16
    //   148: astore 19
    //   150: aload 16
    //   152: astore 20
    //   154: aload 16
    //   156: astore 17
    //   158: aload_0
    //   159: getfield 87	com/taobao/munion/net/b:p	Lcom/taobao/munion/net/e;
    //   162: getfield 204	com/taobao/munion/net/e:i	Z
    //   165: ifeq +655 -> 820
    //   168: aload 16
    //   170: astore 18
    //   172: aload 16
    //   174: astore 19
    //   176: aload 16
    //   178: astore 20
    //   180: aload 16
    //   182: astore 17
    //   184: aload_0
    //   185: getfield 87	com/taobao/munion/net/b:p	Lcom/taobao/munion/net/e;
    //   188: getfield 207	com/taobao/munion/net/e:h	[B
    //   191: ifnull +522 -> 713
    //   194: aload 16
    //   196: astore 18
    //   198: aload 16
    //   200: astore 19
    //   202: aload 16
    //   204: astore 20
    //   206: aload 16
    //   208: astore 17
    //   210: aload_0
    //   211: getfield 87	com/taobao/munion/net/b:p	Lcom/taobao/munion/net/e;
    //   214: getfield 207	com/taobao/munion/net/e:h	[B
    //   217: astore 26
    //   219: aload 26
    //   221: astore 17
    //   223: iload_1
    //   224: istore_2
    //   225: aload 16
    //   227: astore 29
    //   229: aload 53
    //   231: astore 28
    //   233: aload 46
    //   235: astore 27
    //   237: aload 61
    //   239: astore 26
    //   241: aload 58
    //   243: astore 25
    //   245: aload 51
    //   247: astore 24
    //   249: new 209	java/net/URL
    //   252: dup
    //   253: aload 16
    //   255: invokespecial 212	java/net/URL:<init>	(Ljava/lang/String;)V
    //   258: astore 18
    //   260: iload_1
    //   261: istore_2
    //   262: aload 16
    //   264: astore 29
    //   266: aload 53
    //   268: astore 28
    //   270: aload 46
    //   272: astore 27
    //   274: aload 61
    //   276: astore 26
    //   278: aload 58
    //   280: astore 25
    //   282: aload 51
    //   284: astore 24
    //   286: aload 18
    //   288: invokevirtual 215	java/net/URL:getHost	()Ljava/lang/String;
    //   291: astore 19
    //   293: iload_1
    //   294: istore_2
    //   295: aload 16
    //   297: astore 29
    //   299: aload 53
    //   301: astore 28
    //   303: aload 46
    //   305: astore 27
    //   307: aload 61
    //   309: astore 26
    //   311: aload 58
    //   313: astore 25
    //   315: aload 51
    //   317: astore 24
    //   319: getstatic 219	com/taobao/munion/utils/m:g	Z
    //   322: ifne +7 -> 329
    //   325: iload_3
    //   326: ifeq +543 -> 869
    //   329: iload_1
    //   330: istore_2
    //   331: aload 16
    //   333: astore 29
    //   335: aload 53
    //   337: astore 28
    //   339: aload 46
    //   341: astore 27
    //   343: aload 61
    //   345: astore 26
    //   347: aload 58
    //   349: astore 25
    //   351: aload 51
    //   353: astore 24
    //   355: aload_0
    //   356: invokespecial 221	com/taobao/munion/net/b:d	()Lorg/apache/http/impl/client/DefaultHttpClient;
    //   359: astore 64
    //   361: iload_1
    //   362: istore_2
    //   363: aload 16
    //   365: astore 29
    //   367: aload 53
    //   369: astore 28
    //   371: aload 46
    //   373: astore 27
    //   375: aload 61
    //   377: astore 26
    //   379: aload 58
    //   381: astore 25
    //   383: aload 51
    //   385: astore 24
    //   387: aload_0
    //   388: getfield 87	com/taobao/munion/net/b:p	Lcom/taobao/munion/net/e;
    //   391: invokevirtual 223	com/taobao/munion/net/e:f	()I
    //   394: iconst_1
    //   395: if_icmpeq +1345 -> 1740
    //   398: iconst_1
    //   399: istore_2
    //   400: iload_2
    //   401: ifne +1344 -> 1745
    //   404: iload_1
    //   405: istore_2
    //   406: aload 16
    //   408: astore 29
    //   410: aload 53
    //   412: astore 28
    //   414: aload 46
    //   416: astore 27
    //   418: aload 61
    //   420: astore 26
    //   422: aload 58
    //   424: astore 25
    //   426: aload 51
    //   428: astore 24
    //   430: getstatic 78	com/taobao/munion/net/b:b	Lcom/taobao/munion/net/b$f;
    //   433: astore 18
    //   435: iload_1
    //   436: istore 4
    //   438: aload 59
    //   440: astore 33
    //   442: aload 48
    //   444: astore 35
    //   446: aload 62
    //   448: astore 37
    //   450: aload 57
    //   452: astore 38
    //   454: aload 54
    //   456: astore 39
    //   458: iload_1
    //   459: istore_2
    //   460: aload 16
    //   462: astore 29
    //   464: aload 53
    //   466: astore 28
    //   468: aload 46
    //   470: astore 27
    //   472: aload 61
    //   474: astore 26
    //   476: aload 58
    //   478: astore 25
    //   480: aload 51
    //   482: astore 24
    //   484: iload_1
    //   485: istore 5
    //   487: iload_1
    //   488: istore_3
    //   489: aload 52
    //   491: astore 36
    //   493: aload 47
    //   495: astore 34
    //   497: aload 63
    //   499: astore 32
    //   501: aload 56
    //   503: astore 31
    //   505: aload 60
    //   507: astore 30
    //   509: aload_0
    //   510: getfield 225	com/taobao/munion/net/b:r	Z
    //   513: ifeq +1266 -> 1779
    //   516: iload_1
    //   517: istore 4
    //   519: aload 59
    //   521: astore 33
    //   523: aload 48
    //   525: astore 35
    //   527: aload 62
    //   529: astore 37
    //   531: aload 57
    //   533: astore 38
    //   535: aload 54
    //   537: astore 39
    //   539: iload_1
    //   540: istore_2
    //   541: aload 16
    //   543: astore 29
    //   545: aload 53
    //   547: astore 28
    //   549: aload 46
    //   551: astore 27
    //   553: aload 61
    //   555: astore 26
    //   557: aload 58
    //   559: astore 25
    //   561: aload 51
    //   563: astore 24
    //   565: iload_1
    //   566: istore 5
    //   568: iload_1
    //   569: istore_3
    //   570: aload 52
    //   572: astore 36
    //   574: aload 47
    //   576: astore 34
    //   578: aload 63
    //   580: astore 32
    //   582: aload 56
    //   584: astore 31
    //   586: aload 60
    //   588: astore 30
    //   590: getstatic 230	com/taobao/munion/net/h:h	Lcom/taobao/munion/net/h;
    //   593: astore 17
    //   595: getstatic 104	com/taobao/munion/net/b:u	Lcom/taobao/munion/net/c;
    //   598: ifnull +47 -> 645
    //   601: iconst_0
    //   602: ifeq +11 -> 613
    //   605: new 232	java/lang/NullPointerException
    //   608: dup
    //   609: invokespecial 233	java/lang/NullPointerException:<init>	()V
    //   612: athrow
    //   613: iconst_0
    //   614: ifeq +11 -> 625
    //   617: new 232	java/lang/NullPointerException
    //   620: dup
    //   621: invokespecial 233	java/lang/NullPointerException:<init>	()V
    //   624: athrow
    //   625: getstatic 104	com/taobao/munion/net/b:u	Lcom/taobao/munion/net/c;
    //   628: iconst_m1
    //   629: iconst_0
    //   630: invokestatic 183	java/lang/System:currentTimeMillis	()J
    //   633: aload_0
    //   634: getfield 67	com/taobao/munion/net/b:t	J
    //   637: lsub
    //   638: aload 16
    //   640: invokeinterface 238 6 0
    //   645: iconst_0
    //   646: ifeq +11 -> 657
    //   649: new 232	java/lang/NullPointerException
    //   652: dup
    //   653: invokespecial 233	java/lang/NullPointerException:<init>	()V
    //   656: athrow
    //   657: iconst_0
    //   658: ifeq +11 -> 669
    //   661: new 232	java/lang/NullPointerException
    //   664: dup
    //   665: invokespecial 233	java/lang/NullPointerException:<init>	()V
    //   668: athrow
    //   669: iconst_0
    //   670: ifeq +11 -> 681
    //   673: new 232	java/lang/NullPointerException
    //   676: dup
    //   677: invokespecial 233	java/lang/NullPointerException:<init>	()V
    //   680: athrow
    //   681: iconst_0
    //   682: ifeq +11 -> 693
    //   685: new 232	java/lang/NullPointerException
    //   688: dup
    //   689: invokespecial 233	java/lang/NullPointerException:<init>	()V
    //   692: athrow
    //   693: iconst_0
    //   694: ifeq +11 -> 705
    //   697: new 232	java/lang/NullPointerException
    //   700: dup
    //   701: invokespecial 233	java/lang/NullPointerException:<init>	()V
    //   704: athrow
    //   705: aload 17
    //   707: areturn
    //   708: iconst_0
    //   709: istore_3
    //   710: goto -680 -> 30
    //   713: aload 16
    //   715: astore 18
    //   717: aload 16
    //   719: astore 19
    //   721: aload 16
    //   723: astore 20
    //   725: aload 16
    //   727: astore 17
    //   729: aload 16
    //   731: bipush 63
    //   733: invokevirtual 242	java/lang/String:indexOf	(I)I
    //   736: istore_2
    //   737: aload 26
    //   739: astore 18
    //   741: aload 16
    //   743: astore 17
    //   745: iload_2
    //   746: iflt +10962 -> 11708
    //   749: aload 16
    //   751: astore 18
    //   753: aload 16
    //   755: astore 19
    //   757: aload 16
    //   759: astore 20
    //   761: aload 16
    //   763: astore 17
    //   765: aload_0
    //   766: getfield 85	com/taobao/munion/net/b:q	Ljava/lang/String;
    //   769: iconst_0
    //   770: iload_2
    //   771: iconst_1
    //   772: iadd
    //   773: invokevirtual 191	java/lang/String:substring	(II)Ljava/lang/String;
    //   776: astore 16
    //   778: aload 16
    //   780: astore 18
    //   782: aload 16
    //   784: astore 19
    //   786: aload 16
    //   788: astore 20
    //   790: aload 16
    //   792: astore 17
    //   794: aload_0
    //   795: getfield 85	com/taobao/munion/net/b:q	Ljava/lang/String;
    //   798: iload_2
    //   799: iconst_1
    //   800: iadd
    //   801: invokevirtual 245	java/lang/String:substring	(I)Ljava/lang/String;
    //   804: invokevirtual 249	java/lang/String:getBytes	()[B
    //   807: astore 26
    //   809: aload 26
    //   811: astore 18
    //   813: aload 16
    //   815: astore 17
    //   817: goto +10891 -> 11708
    //   820: aload 16
    //   822: astore 18
    //   824: aload 16
    //   826: astore 19
    //   828: aload 16
    //   830: astore 20
    //   832: aload 16
    //   834: astore 17
    //   836: new 251	java/lang/StringBuilder
    //   839: dup
    //   840: invokespecial 252	java/lang/StringBuilder:<init>	()V
    //   843: aload 16
    //   845: invokevirtual 256	java/lang/StringBuilder:append	(Ljava/lang/String;)Ljava/lang/StringBuilder;
    //   848: aload_0
    //   849: getfield 87	com/taobao/munion/net/b:p	Lcom/taobao/munion/net/e;
    //   852: invokevirtual 258	com/taobao/munion/net/e:m	()Ljava/lang/String;
    //   855: invokevirtual 256	java/lang/StringBuilder:append	(Ljava/lang/String;)Ljava/lang/StringBuilder;
    //   858: invokevirtual 261	java/lang/StringBuilder:toString	()Ljava/lang/String;
    //   861: astore 16
    //   863: aconst_null
    //   864: astore 17
    //   866: goto -643 -> 223
    //   869: iload_1
    //   870: istore_2
    //   871: aload 16
    //   873: astore 29
    //   875: aload 53
    //   877: astore 28
    //   879: aload 46
    //   881: astore 27
    //   883: aload 61
    //   885: astore 26
    //   887: aload 58
    //   889: astore 25
    //   891: aload 51
    //   893: astore 24
    //   895: aload 19
    //   897: ldc2_w 262
    //   900: invokestatic 268	com/taobao/munion/net/o:a	(Ljava/lang/String;J)Ljava/lang/String;
    //   903: astore 20
    //   905: iload_1
    //   906: istore_2
    //   907: aload 16
    //   909: astore 29
    //   911: aload 53
    //   913: astore 28
    //   915: aload 46
    //   917: astore 27
    //   919: aload 61
    //   921: astore 26
    //   923: aload 58
    //   925: astore 25
    //   927: aload 51
    //   929: astore 24
    //   931: aload_0
    //   932: getfield 225	com/taobao/munion/net/b:r	Z
    //   935: ifeq +147 -> 1082
    //   938: iload_1
    //   939: istore_2
    //   940: aload 16
    //   942: astore 29
    //   944: aload 53
    //   946: astore 28
    //   948: aload 46
    //   950: astore 27
    //   952: aload 61
    //   954: astore 26
    //   956: aload 58
    //   958: astore 25
    //   960: aload 51
    //   962: astore 24
    //   964: getstatic 230	com/taobao/munion/net/h:h	Lcom/taobao/munion/net/h;
    //   967: astore 17
    //   969: getstatic 104	com/taobao/munion/net/b:u	Lcom/taobao/munion/net/c;
    //   972: ifnull +47 -> 1019
    //   975: iconst_0
    //   976: ifeq +11 -> 987
    //   979: new 232	java/lang/NullPointerException
    //   982: dup
    //   983: invokespecial 233	java/lang/NullPointerException:<init>	()V
    //   986: athrow
    //   987: iconst_0
    //   988: ifeq +11 -> 999
    //   991: new 232	java/lang/NullPointerException
    //   994: dup
    //   995: invokespecial 233	java/lang/NullPointerException:<init>	()V
    //   998: athrow
    //   999: getstatic 104	com/taobao/munion/net/b:u	Lcom/taobao/munion/net/c;
    //   1002: iconst_m1
    //   1003: iconst_0
    //   1004: invokestatic 183	java/lang/System:currentTimeMillis	()J
    //   1007: aload_0
    //   1008: getfield 67	com/taobao/munion/net/b:t	J
    //   1011: lsub
    //   1012: aload 16
    //   1014: invokeinterface 238 6 0
    //   1019: iconst_0
    //   1020: ifeq +11 -> 1031
    //   1023: new 232	java/lang/NullPointerException
    //   1026: dup
    //   1027: invokespecial 233	java/lang/NullPointerException:<init>	()V
    //   1030: athrow
    //   1031: iconst_0
    //   1032: ifeq +11 -> 1043
    //   1035: new 232	java/lang/NullPointerException
    //   1038: dup
    //   1039: invokespecial 233	java/lang/NullPointerException:<init>	()V
    //   1042: athrow
    //   1043: iconst_0
    //   1044: ifeq +11 -> 1055
    //   1047: new 232	java/lang/NullPointerException
    //   1050: dup
    //   1051: invokespecial 233	java/lang/NullPointerException:<init>	()V
    //   1054: athrow
    //   1055: iconst_0
    //   1056: ifeq +11 -> 1067
    //   1059: new 232	java/lang/NullPointerException
    //   1062: dup
    //   1063: invokespecial 233	java/lang/NullPointerException:<init>	()V
    //   1066: athrow
    //   1067: iconst_0
    //   1068: ifeq +11 -> 1079
    //   1071: new 232	java/lang/NullPointerException
    //   1074: dup
    //   1075: invokespecial 233	java/lang/NullPointerException:<init>	()V
    //   1078: athrow
    //   1079: aload 17
    //   1081: areturn
    //   1082: aload 20
    //   1084: ifnull +38 -> 1122
    //   1087: iload_1
    //   1088: istore_2
    //   1089: aload 16
    //   1091: astore 29
    //   1093: aload 53
    //   1095: astore 28
    //   1097: aload 46
    //   1099: astore 27
    //   1101: aload 61
    //   1103: astore 26
    //   1105: aload 58
    //   1107: astore 25
    //   1109: aload 51
    //   1111: astore 24
    //   1113: aload 20
    //   1115: invokevirtual 271	java/lang/String:length	()I
    //   1118: iconst_3
    //   1119: if_icmpge +315 -> 1434
    //   1122: iload_1
    //   1123: istore_2
    //   1124: aload 16
    //   1126: astore 29
    //   1128: aload 53
    //   1130: astore 28
    //   1132: aload 46
    //   1134: astore 27
    //   1136: aload 61
    //   1138: astore 26
    //   1140: aload 58
    //   1142: astore 25
    //   1144: aload 51
    //   1146: astore 24
    //   1148: new 273	com/taobao/munion/net/b$d
    //   1151: dup
    //   1152: aload_0
    //   1153: ldc_w 275
    //   1156: iload 10
    //   1158: invokespecial 278	com/taobao/munion/net/b$d:<init>	(Lcom/taobao/munion/net/b;Ljava/lang/String;I)V
    //   1161: athrow
    //   1162: astore 22
    //   1164: iconst_m1
    //   1165: istore_1
    //   1166: aload 19
    //   1168: astore 24
    //   1170: aconst_null
    //   1171: astore 18
    //   1173: aconst_null
    //   1174: astore 23
    //   1176: aconst_null
    //   1177: astore 19
    //   1179: aconst_null
    //   1180: astore 25
    //   1182: aconst_null
    //   1183: astore 20
    //   1185: aconst_null
    //   1186: astore 17
    //   1188: aload 16
    //   1190: astore 21
    //   1192: aload 25
    //   1194: astore 16
    //   1196: aload 23
    //   1198: ifnull +21 -> 1219
    //   1201: aload 23
    //   1203: monitorenter
    //   1204: aload 23
    //   1206: aload 23
    //   1208: getfield 280	com/taobao/munion/net/b$f:b	J
    //   1211: lconst_1
    //   1212: ladd
    //   1213: putfield 280	com/taobao/munion/net/b$f:b	J
    //   1216: aload 23
    //   1218: monitorexit
    //   1219: invokestatic 200	com/taobao/munion/net/f:a	()Lcom/taobao/munion/net/f;
    //   1222: invokevirtual 202	com/taobao/munion/net/f:d	()I
    //   1225: invokestatic 200	com/taobao/munion/net/f:a	()Lcom/taobao/munion/net/f;
    //   1228: getfield 282	com/taobao/munion/net/f:k	I
    //   1231: if_icmplt +8 -> 1239
    //   1234: aload 24
    //   1236: invokestatic 284	com/taobao/munion/net/o:b	(Ljava/lang/String;)V
    //   1239: invokestatic 200	com/taobao/munion/net/f:a	()Lcom/taobao/munion/net/f;
    //   1242: invokevirtual 286	com/taobao/munion/net/f:e	()V
    //   1245: aload 22
    //   1247: invokevirtual 289	java/net/SocketTimeoutException:printStackTrace	()V
    //   1250: new 273	com/taobao/munion/net/b$d
    //   1253: dup
    //   1254: aload_0
    //   1255: new 251	java/lang/StringBuilder
    //   1258: dup
    //   1259: ldc_w 291
    //   1262: invokespecial 292	java/lang/StringBuilder:<init>	(Ljava/lang/String;)V
    //   1265: aload 24
    //   1267: invokevirtual 256	java/lang/StringBuilder:append	(Ljava/lang/String;)Ljava/lang/StringBuilder;
    //   1270: ldc_w 294
    //   1273: invokevirtual 256	java/lang/StringBuilder:append	(Ljava/lang/String;)Ljava/lang/StringBuilder;
    //   1276: aload 22
    //   1278: invokevirtual 297	java/net/SocketTimeoutException:getMessage	()Ljava/lang/String;
    //   1281: invokevirtual 256	java/lang/StringBuilder:append	(Ljava/lang/String;)Ljava/lang/StringBuilder;
    //   1284: invokevirtual 261	java/lang/StringBuilder:toString	()Ljava/lang/String;
    //   1287: iload 10
    //   1289: invokespecial 278	com/taobao/munion/net/b$d:<init>	(Lcom/taobao/munion/net/b;Ljava/lang/String;I)V
    //   1292: athrow
    //   1293: astore 23
    //   1295: aload 18
    //   1297: astore 22
    //   1299: aload 23
    //   1301: astore 18
    //   1303: aload 17
    //   1305: astore 27
    //   1307: aload 20
    //   1309: astore 24
    //   1311: aload 19
    //   1313: astore 25
    //   1315: aload 22
    //   1317: astore 17
    //   1319: aload 16
    //   1321: astore 28
    //   1323: aload 18
    //   1325: astore 16
    //   1327: aload 21
    //   1329: astore 29
    //   1331: getstatic 104	com/taobao/munion/net/b:u	Lcom/taobao/munion/net/c;
    //   1334: ifnull +47 -> 1381
    //   1337: iconst_0
    //   1338: istore_2
    //   1339: aload 27
    //   1341: ifnull +9 -> 1350
    //   1344: aload 27
    //   1346: invokevirtual 302	java/io/ByteArrayOutputStream:size	()I
    //   1349: istore_2
    //   1350: aload 25
    //   1352: ifnull +9 -> 1361
    //   1355: aload 25
    //   1357: getfield 306	com/taobao/munion/net/n:a	I
    //   1360: istore_2
    //   1361: getstatic 104	com/taobao/munion/net/b:u	Lcom/taobao/munion/net/c;
    //   1364: iload_1
    //   1365: iload_2
    //   1366: invokestatic 183	java/lang/System:currentTimeMillis	()J
    //   1369: aload_0
    //   1370: getfield 67	com/taobao/munion/net/b:t	J
    //   1373: lsub
    //   1374: aload 29
    //   1376: invokeinterface 238 6 0
    //   1381: aload 28
    //   1383: ifnull +8 -> 1391
    //   1386: aload 28
    //   1388: invokevirtual 311	java/io/DataInputStream:close	()V
    //   1391: aload 17
    //   1393: ifnull +8 -> 1401
    //   1396: aload 17
    //   1398: invokevirtual 314	java/io/InputStream:close	()V
    //   1401: aload 25
    //   1403: ifnull +8 -> 1411
    //   1406: aload 25
    //   1408: invokevirtual 315	com/taobao/munion/net/n:close	()V
    //   1411: aload 24
    //   1413: ifnull +8 -> 1421
    //   1416: aload 24
    //   1418: invokevirtual 318	java/util/zip/GZIPInputStream:close	()V
    //   1421: aload 27
    //   1423: ifnull +8 -> 1431
    //   1426: aload 27
    //   1428: invokevirtual 319	java/io/ByteArrayOutputStream:close	()V
    //   1431: aload 16
    //   1433: athrow
    //   1434: iload_1
    //   1435: istore_2
    //   1436: aload 16
    //   1438: astore 29
    //   1440: aload 53
    //   1442: astore 28
    //   1444: aload 46
    //   1446: astore 27
    //   1448: aload 61
    //   1450: astore 26
    //   1452: aload 58
    //   1454: astore 25
    //   1456: aload 51
    //   1458: astore 24
    //   1460: new 209	java/net/URL
    //   1463: dup
    //   1464: aload 18
    //   1466: invokevirtual 322	java/net/URL:getProtocol	()Ljava/lang/String;
    //   1469: aload 20
    //   1471: aload 18
    //   1473: invokevirtual 325	java/net/URL:getPort	()I
    //   1476: aload 18
    //   1478: invokevirtual 328	java/net/URL:getFile	()Ljava/lang/String;
    //   1481: invokespecial 331	java/net/URL:<init>	(Ljava/lang/String;Ljava/lang/String;ILjava/lang/String;)V
    //   1484: pop
    //   1485: goto -1156 -> 329
    //   1488: astore 19
    //   1490: aconst_null
    //   1491: astore 21
    //   1493: aload 22
    //   1495: astore 20
    //   1497: aload 32
    //   1499: astore 17
    //   1501: aload 33
    //   1503: astore 18
    //   1505: aload 42
    //   1507: astore 34
    //   1509: aload 43
    //   1511: astore 36
    //   1513: aload 21
    //   1515: ifnull +47 -> 1562
    //   1518: iload_1
    //   1519: istore_2
    //   1520: aload 16
    //   1522: astore 29
    //   1524: aload 36
    //   1526: astore 28
    //   1528: aload 34
    //   1530: astore 27
    //   1532: aload 18
    //   1534: astore 26
    //   1536: aload 17
    //   1538: astore 25
    //   1540: aload 20
    //   1542: astore 24
    //   1544: aload 21
    //   1546: monitorenter
    //   1547: aload 21
    //   1549: aload 21
    //   1551: getfield 280	com/taobao/munion/net/b$f:b	J
    //   1554: lconst_1
    //   1555: ladd
    //   1556: putfield 280	com/taobao/munion/net/b$f:b	J
    //   1559: aload 21
    //   1561: monitorexit
    //   1562: iload_1
    //   1563: istore_2
    //   1564: aload 16
    //   1566: astore 29
    //   1568: aload 36
    //   1570: astore 28
    //   1572: aload 34
    //   1574: astore 27
    //   1576: aload 18
    //   1578: astore 26
    //   1580: aload 17
    //   1582: astore 25
    //   1584: aload 20
    //   1586: astore 24
    //   1588: aload 19
    //   1590: invokevirtual 332	java/io/FileNotFoundException:printStackTrace	()V
    //   1593: iload_1
    //   1594: istore_2
    //   1595: aload 16
    //   1597: astore 29
    //   1599: aload 36
    //   1601: astore 28
    //   1603: aload 34
    //   1605: astore 27
    //   1607: aload 18
    //   1609: astore 26
    //   1611: aload 17
    //   1613: astore 25
    //   1615: aload 20
    //   1617: astore 24
    //   1619: new 227	com/taobao/munion/net/h
    //   1622: dup
    //   1623: sipush 404
    //   1626: aload 19
    //   1628: invokevirtual 333	java/io/FileNotFoundException:getMessage	()Ljava/lang/String;
    //   1631: aconst_null
    //   1632: invokespecial 336	com/taobao/munion/net/h:<init>	(ILjava/lang/String;[B)V
    //   1635: astore 19
    //   1637: getstatic 104	com/taobao/munion/net/b:u	Lcom/taobao/munion/net/c;
    //   1640: ifnull +47 -> 1687
    //   1643: iconst_0
    //   1644: istore_2
    //   1645: aload 34
    //   1647: ifnull +9 -> 1656
    //   1650: aload 34
    //   1652: invokevirtual 302	java/io/ByteArrayOutputStream:size	()I
    //   1655: istore_2
    //   1656: aload 17
    //   1658: ifnull +9 -> 1667
    //   1661: aload 17
    //   1663: getfield 306	com/taobao/munion/net/n:a	I
    //   1666: istore_2
    //   1667: getstatic 104	com/taobao/munion/net/b:u	Lcom/taobao/munion/net/c;
    //   1670: iload_1
    //   1671: iload_2
    //   1672: invokestatic 183	java/lang/System:currentTimeMillis	()J
    //   1675: aload_0
    //   1676: getfield 67	com/taobao/munion/net/b:t	J
    //   1679: lsub
    //   1680: aload 16
    //   1682: invokeinterface 238 6 0
    //   1687: aload 36
    //   1689: ifnull +8 -> 1697
    //   1692: aload 36
    //   1694: invokevirtual 311	java/io/DataInputStream:close	()V
    //   1697: aload 18
    //   1699: ifnull +8 -> 1707
    //   1702: aload 18
    //   1704: invokevirtual 314	java/io/InputStream:close	()V
    //   1707: aload 17
    //   1709: ifnull +8 -> 1717
    //   1712: aload 17
    //   1714: invokevirtual 315	com/taobao/munion/net/n:close	()V
    //   1717: aload 20
    //   1719: ifnull +8 -> 1727
    //   1722: aload 20
    //   1724: invokevirtual 318	java/util/zip/GZIPInputStream:close	()V
    //   1727: aload 34
    //   1729: ifnull +8 -> 1737
    //   1732: aload 34
    //   1734: invokevirtual 319	java/io/ByteArrayOutputStream:close	()V
    //   1737: aload 19
    //   1739: areturn
    //   1740: iconst_0
    //   1741: istore_2
    //   1742: goto -1342 -> 400
    //   1745: iload_1
    //   1746: istore_2
    //   1747: aload 16
    //   1749: astore 29
    //   1751: aload 53
    //   1753: astore 28
    //   1755: aload 46
    //   1757: astore 27
    //   1759: aload 61
    //   1761: astore 26
    //   1763: aload 58
    //   1765: astore 25
    //   1767: aload 51
    //   1769: astore 24
    //   1771: getstatic 71	com/taobao/munion/net/b:a	Lcom/taobao/munion/net/b$f;
    //   1774: astore 18
    //   1776: goto -1341 -> 435
    //   1779: aload 17
    //   1781: ifnull +725 -> 2506
    //   1784: iload_1
    //   1785: istore 4
    //   1787: aload 59
    //   1789: astore 33
    //   1791: aload 48
    //   1793: astore 35
    //   1795: aload 62
    //   1797: astore 37
    //   1799: aload 57
    //   1801: astore 38
    //   1803: aload 54
    //   1805: astore 39
    //   1807: iload_1
    //   1808: istore_2
    //   1809: aload 16
    //   1811: astore 29
    //   1813: aload 53
    //   1815: astore 28
    //   1817: aload 46
    //   1819: astore 27
    //   1821: aload 61
    //   1823: astore 26
    //   1825: aload 58
    //   1827: astore 25
    //   1829: aload 51
    //   1831: astore 24
    //   1833: iload_1
    //   1834: istore 5
    //   1836: iload_1
    //   1837: istore_3
    //   1838: aload 52
    //   1840: astore 36
    //   1842: aload 47
    //   1844: astore 34
    //   1846: aload 63
    //   1848: astore 32
    //   1850: aload 56
    //   1852: astore 31
    //   1854: aload 60
    //   1856: astore 30
    //   1858: new 338	org/apache/http/client/methods/HttpPost
    //   1861: dup
    //   1862: aload_0
    //   1863: getfield 85	com/taobao/munion/net/b:q	Ljava/lang/String;
    //   1866: invokespecial 339	org/apache/http/client/methods/HttpPost:<init>	(Ljava/lang/String;)V
    //   1869: astore 20
    //   1871: iload_1
    //   1872: istore 4
    //   1874: aload 59
    //   1876: astore 33
    //   1878: aload 48
    //   1880: astore 35
    //   1882: aload 62
    //   1884: astore 37
    //   1886: aload 57
    //   1888: astore 38
    //   1890: aload 54
    //   1892: astore 39
    //   1894: iload_1
    //   1895: istore_2
    //   1896: aload 16
    //   1898: astore 29
    //   1900: aload 53
    //   1902: astore 28
    //   1904: aload 46
    //   1906: astore 27
    //   1908: aload 61
    //   1910: astore 26
    //   1912: aload 58
    //   1914: astore 25
    //   1916: aload 51
    //   1918: astore 24
    //   1920: iload_1
    //   1921: istore 5
    //   1923: iload_1
    //   1924: istore_3
    //   1925: aload 52
    //   1927: astore 36
    //   1929: aload 47
    //   1931: astore 34
    //   1933: aload 63
    //   1935: astore 32
    //   1937: aload 56
    //   1939: astore 31
    //   1941: aload 60
    //   1943: astore 30
    //   1945: new 341	org/apache/http/entity/InputStreamEntity
    //   1948: dup
    //   1949: new 343	java/io/ByteArrayInputStream
    //   1952: dup
    //   1953: aload 17
    //   1955: invokespecial 346	java/io/ByteArrayInputStream:<init>	([B)V
    //   1958: aload 17
    //   1960: arraylength
    //   1961: i2l
    //   1962: invokespecial 349	org/apache/http/entity/InputStreamEntity:<init>	(Ljava/io/InputStream;J)V
    //   1965: astore 17
    //   1967: iload_1
    //   1968: istore 4
    //   1970: aload 59
    //   1972: astore 33
    //   1974: aload 48
    //   1976: astore 35
    //   1978: aload 62
    //   1980: astore 37
    //   1982: aload 57
    //   1984: astore 38
    //   1986: aload 54
    //   1988: astore 39
    //   1990: iload_1
    //   1991: istore_2
    //   1992: aload 16
    //   1994: astore 29
    //   1996: aload 53
    //   1998: astore 28
    //   2000: aload 46
    //   2002: astore 27
    //   2004: aload 61
    //   2006: astore 26
    //   2008: aload 58
    //   2010: astore 25
    //   2012: aload 51
    //   2014: astore 24
    //   2016: iload_1
    //   2017: istore 5
    //   2019: iload_1
    //   2020: istore_3
    //   2021: aload 52
    //   2023: astore 36
    //   2025: aload 47
    //   2027: astore 34
    //   2029: aload 63
    //   2031: astore 32
    //   2033: aload 56
    //   2035: astore 31
    //   2037: aload 60
    //   2039: astore 30
    //   2041: aload 20
    //   2043: checkcast 338	org/apache/http/client/methods/HttpPost
    //   2046: aload 17
    //   2048: invokevirtual 353	org/apache/http/client/methods/HttpPost:setEntity	(Lorg/apache/http/HttpEntity;)V
    //   2051: aload 20
    //   2053: astore 17
    //   2055: iload_1
    //   2056: istore 4
    //   2058: aload 59
    //   2060: astore 33
    //   2062: aload 48
    //   2064: astore 35
    //   2066: aload 62
    //   2068: astore 37
    //   2070: aload 57
    //   2072: astore 38
    //   2074: aload 54
    //   2076: astore 39
    //   2078: iload_1
    //   2079: istore_2
    //   2080: aload 16
    //   2082: astore 29
    //   2084: aload 53
    //   2086: astore 28
    //   2088: aload 46
    //   2090: astore 27
    //   2092: aload 61
    //   2094: astore 26
    //   2096: aload 58
    //   2098: astore 25
    //   2100: aload 51
    //   2102: astore 24
    //   2104: iload_1
    //   2105: istore 5
    //   2107: iload_1
    //   2108: istore_3
    //   2109: aload 52
    //   2111: astore 36
    //   2113: aload 47
    //   2115: astore 34
    //   2117: aload 63
    //   2119: astore 32
    //   2121: aload 56
    //   2123: astore 31
    //   2125: aload 60
    //   2127: astore 30
    //   2129: aload_0
    //   2130: getfield 87	com/taobao/munion/net/b:p	Lcom/taobao/munion/net/e;
    //   2133: getfield 356	com/taobao/munion/net/e:k	Ljava/util/Map;
    //   2136: ifnull +458 -> 2594
    //   2139: iload_1
    //   2140: istore 4
    //   2142: aload 59
    //   2144: astore 33
    //   2146: aload 48
    //   2148: astore 35
    //   2150: aload 62
    //   2152: astore 37
    //   2154: aload 57
    //   2156: astore 38
    //   2158: aload 54
    //   2160: astore 39
    //   2162: iload_1
    //   2163: istore_2
    //   2164: aload 16
    //   2166: astore 29
    //   2168: aload 53
    //   2170: astore 28
    //   2172: aload 46
    //   2174: astore 27
    //   2176: aload 61
    //   2178: astore 26
    //   2180: aload 58
    //   2182: astore 25
    //   2184: aload 51
    //   2186: astore 24
    //   2188: iload_1
    //   2189: istore 5
    //   2191: iload_1
    //   2192: istore_3
    //   2193: aload 52
    //   2195: astore 36
    //   2197: aload 47
    //   2199: astore 34
    //   2201: aload 63
    //   2203: astore 32
    //   2205: aload 56
    //   2207: astore 31
    //   2209: aload 60
    //   2211: astore 30
    //   2213: aload_0
    //   2214: getfield 87	com/taobao/munion/net/b:p	Lcom/taobao/munion/net/e;
    //   2217: getfield 356	com/taobao/munion/net/e:k	Ljava/util/Map;
    //   2220: invokeinterface 362 1 0
    //   2225: invokeinterface 368 1 0
    //   2230: astore 20
    //   2232: iload_1
    //   2233: istore 4
    //   2235: aload 59
    //   2237: astore 33
    //   2239: aload 48
    //   2241: astore 35
    //   2243: aload 62
    //   2245: astore 37
    //   2247: aload 57
    //   2249: astore 38
    //   2251: aload 54
    //   2253: astore 39
    //   2255: iload_1
    //   2256: istore_2
    //   2257: aload 16
    //   2259: astore 29
    //   2261: aload 53
    //   2263: astore 28
    //   2265: aload 46
    //   2267: astore 27
    //   2269: aload 61
    //   2271: astore 26
    //   2273: aload 58
    //   2275: astore 25
    //   2277: aload 51
    //   2279: astore 24
    //   2281: iload_1
    //   2282: istore 5
    //   2284: iload_1
    //   2285: istore_3
    //   2286: aload 52
    //   2288: astore 36
    //   2290: aload 47
    //   2292: astore 34
    //   2294: aload 63
    //   2296: astore 32
    //   2298: aload 56
    //   2300: astore 31
    //   2302: aload 60
    //   2304: astore 30
    //   2306: aload 20
    //   2308: invokeinterface 374 1 0
    //   2313: ifeq +281 -> 2594
    //   2316: iload_1
    //   2317: istore 4
    //   2319: aload 59
    //   2321: astore 33
    //   2323: aload 48
    //   2325: astore 35
    //   2327: aload 62
    //   2329: astore 37
    //   2331: aload 57
    //   2333: astore 38
    //   2335: aload 54
    //   2337: astore 39
    //   2339: iload_1
    //   2340: istore_2
    //   2341: aload 16
    //   2343: astore 29
    //   2345: aload 53
    //   2347: astore 28
    //   2349: aload 46
    //   2351: astore 27
    //   2353: aload 61
    //   2355: astore 26
    //   2357: aload 58
    //   2359: astore 25
    //   2361: aload 51
    //   2363: astore 24
    //   2365: iload_1
    //   2366: istore 5
    //   2368: iload_1
    //   2369: istore_3
    //   2370: aload 52
    //   2372: astore 36
    //   2374: aload 47
    //   2376: astore 34
    //   2378: aload 63
    //   2380: astore 32
    //   2382: aload 56
    //   2384: astore 31
    //   2386: aload 60
    //   2388: astore 30
    //   2390: aload 20
    //   2392: invokeinterface 378 1 0
    //   2397: checkcast 380	java/util/Map$Entry
    //   2400: astore 65
    //   2402: iload_1
    //   2403: istore 4
    //   2405: aload 59
    //   2407: astore 33
    //   2409: aload 48
    //   2411: astore 35
    //   2413: aload 62
    //   2415: astore 37
    //   2417: aload 57
    //   2419: astore 38
    //   2421: aload 54
    //   2423: astore 39
    //   2425: iload_1
    //   2426: istore_2
    //   2427: aload 16
    //   2429: astore 29
    //   2431: aload 53
    //   2433: astore 28
    //   2435: aload 46
    //   2437: astore 27
    //   2439: aload 61
    //   2441: astore 26
    //   2443: aload 58
    //   2445: astore 25
    //   2447: aload 51
    //   2449: astore 24
    //   2451: iload_1
    //   2452: istore 5
    //   2454: iload_1
    //   2455: istore_3
    //   2456: aload 52
    //   2458: astore 36
    //   2460: aload 47
    //   2462: astore 34
    //   2464: aload 63
    //   2466: astore 32
    //   2468: aload 56
    //   2470: astore 31
    //   2472: aload 60
    //   2474: astore 30
    //   2476: aload 17
    //   2478: aload 65
    //   2480: invokeinterface 383 1 0
    //   2485: checkcast 187	java/lang/String
    //   2488: aload 65
    //   2490: invokeinterface 386 1 0
    //   2495: checkcast 187	java/lang/String
    //   2498: invokeinterface 392 3 0
    //   2503: goto -271 -> 2232
    //   2506: iload_1
    //   2507: istore 4
    //   2509: aload 59
    //   2511: astore 33
    //   2513: aload 48
    //   2515: astore 35
    //   2517: aload 62
    //   2519: astore 37
    //   2521: aload 57
    //   2523: astore 38
    //   2525: aload 54
    //   2527: astore 39
    //   2529: iload_1
    //   2530: istore_2
    //   2531: aload 16
    //   2533: astore 29
    //   2535: aload 53
    //   2537: astore 28
    //   2539: aload 46
    //   2541: astore 27
    //   2543: aload 61
    //   2545: astore 26
    //   2547: aload 58
    //   2549: astore 25
    //   2551: aload 51
    //   2553: astore 24
    //   2555: iload_1
    //   2556: istore 5
    //   2558: iload_1
    //   2559: istore_3
    //   2560: aload 52
    //   2562: astore 36
    //   2564: aload 47
    //   2566: astore 34
    //   2568: aload 63
    //   2570: astore 32
    //   2572: aload 56
    //   2574: astore 31
    //   2576: aload 60
    //   2578: astore 30
    //   2580: new 394	org/apache/http/client/methods/HttpGet
    //   2583: dup
    //   2584: aload 16
    //   2586: invokespecial 395	org/apache/http/client/methods/HttpGet:<init>	(Ljava/lang/String;)V
    //   2589: astore 17
    //   2591: goto -536 -> 2055
    //   2594: iload_1
    //   2595: istore 4
    //   2597: aload 59
    //   2599: astore 33
    //   2601: aload 48
    //   2603: astore 35
    //   2605: aload 62
    //   2607: astore 37
    //   2609: aload 57
    //   2611: astore 38
    //   2613: aload 54
    //   2615: astore 39
    //   2617: iload_1
    //   2618: istore_2
    //   2619: aload 16
    //   2621: astore 29
    //   2623: aload 53
    //   2625: astore 28
    //   2627: aload 46
    //   2629: astore 27
    //   2631: aload 61
    //   2633: astore 26
    //   2635: aload 58
    //   2637: astore 25
    //   2639: aload 51
    //   2641: astore 24
    //   2643: iload_1
    //   2644: istore 5
    //   2646: iload_1
    //   2647: istore_3
    //   2648: aload 52
    //   2650: astore 36
    //   2652: aload 47
    //   2654: astore 34
    //   2656: aload 63
    //   2658: astore 32
    //   2660: aload 56
    //   2662: astore 31
    //   2664: aload 60
    //   2666: astore 30
    //   2668: aload_0
    //   2669: aload 64
    //   2671: invokevirtual 398	com/taobao/munion/net/b:a	(Lorg/apache/http/client/HttpClient;)V
    //   2674: iload_1
    //   2675: istore 4
    //   2677: aload 59
    //   2679: astore 33
    //   2681: aload 48
    //   2683: astore 35
    //   2685: aload 62
    //   2687: astore 37
    //   2689: aload 57
    //   2691: astore 38
    //   2693: aload 54
    //   2695: astore 39
    //   2697: iload_1
    //   2698: istore_2
    //   2699: aload 16
    //   2701: astore 29
    //   2703: aload 53
    //   2705: astore 28
    //   2707: aload 46
    //   2709: astore 27
    //   2711: aload 61
    //   2713: astore 26
    //   2715: aload 58
    //   2717: astore 25
    //   2719: aload 51
    //   2721: astore 24
    //   2723: iload_1
    //   2724: istore 5
    //   2726: iload_1
    //   2727: istore_3
    //   2728: aload 52
    //   2730: astore 36
    //   2732: aload 47
    //   2734: astore 34
    //   2736: aload 63
    //   2738: astore 32
    //   2740: aload 56
    //   2742: astore 31
    //   2744: aload 60
    //   2746: astore 30
    //   2748: aload 64
    //   2750: aload 17
    //   2752: invokevirtual 402	org/apache/http/impl/client/DefaultHttpClient:execute	(Lorg/apache/http/client/methods/HttpUriRequest;)Lorg/apache/http/HttpResponse;
    //   2755: astore 64
    //   2757: iload_1
    //   2758: istore 4
    //   2760: aload 59
    //   2762: astore 33
    //   2764: aload 48
    //   2766: astore 35
    //   2768: aload 62
    //   2770: astore 37
    //   2772: aload 57
    //   2774: astore 38
    //   2776: aload 54
    //   2778: astore 39
    //   2780: iload_1
    //   2781: istore_2
    //   2782: aload 16
    //   2784: astore 29
    //   2786: aload 53
    //   2788: astore 28
    //   2790: aload 46
    //   2792: astore 27
    //   2794: aload 61
    //   2796: astore 26
    //   2798: aload 58
    //   2800: astore 25
    //   2802: aload 51
    //   2804: astore 24
    //   2806: iload_1
    //   2807: istore 5
    //   2809: iload_1
    //   2810: istore_3
    //   2811: aload 52
    //   2813: astore 36
    //   2815: aload 47
    //   2817: astore 34
    //   2819: aload 63
    //   2821: astore 32
    //   2823: aload 56
    //   2825: astore 31
    //   2827: aload 60
    //   2829: astore 30
    //   2831: aload 18
    //   2833: monitorenter
    //   2834: aload 18
    //   2836: aload 18
    //   2838: getfield 404	com/taobao/munion/net/b$f:a	J
    //   2841: lconst_1
    //   2842: ladd
    //   2843: putfield 404	com/taobao/munion/net/b$f:a	J
    //   2846: aload 18
    //   2848: aload 18
    //   2850: getfield 406	com/taobao/munion/net/b$f:c	J
    //   2853: invokestatic 409	java/lang/System:nanoTime	()J
    //   2856: lconst_0
    //   2857: lsub
    //   2858: ldc2_w 410
    //   2861: ldiv
    //   2862: ladd
    //   2863: putfield 406	com/taobao/munion/net/b$f:c	J
    //   2866: aload 18
    //   2868: monitorexit
    //   2869: aload 64
    //   2871: ifnonnull +362 -> 3233
    //   2874: iload_1
    //   2875: istore 4
    //   2877: aload 59
    //   2879: astore 33
    //   2881: aload 48
    //   2883: astore 35
    //   2885: aload 62
    //   2887: astore 37
    //   2889: aload 57
    //   2891: astore 38
    //   2893: aload 54
    //   2895: astore 39
    //   2897: iload_1
    //   2898: istore_2
    //   2899: aload 16
    //   2901: astore 29
    //   2903: aload 53
    //   2905: astore 28
    //   2907: aload 46
    //   2909: astore 27
    //   2911: aload 61
    //   2913: astore 26
    //   2915: aload 58
    //   2917: astore 25
    //   2919: aload 51
    //   2921: astore 24
    //   2923: iload_1
    //   2924: istore 5
    //   2926: iload_1
    //   2927: istore_3
    //   2928: aload 52
    //   2930: astore 36
    //   2932: aload 47
    //   2934: astore 34
    //   2936: aload 63
    //   2938: astore 32
    //   2940: aload 56
    //   2942: astore 31
    //   2944: aload 60
    //   2946: astore 30
    //   2948: new 227	com/taobao/munion/net/h
    //   2951: dup
    //   2952: sipush 400
    //   2955: ldc_w 413
    //   2958: aconst_null
    //   2959: invokespecial 336	com/taobao/munion/net/h:<init>	(ILjava/lang/String;[B)V
    //   2962: astore 17
    //   2964: getstatic 104	com/taobao/munion/net/b:u	Lcom/taobao/munion/net/c;
    //   2967: ifnull +47 -> 3014
    //   2970: iconst_0
    //   2971: ifeq +11 -> 2982
    //   2974: new 232	java/lang/NullPointerException
    //   2977: dup
    //   2978: invokespecial 233	java/lang/NullPointerException:<init>	()V
    //   2981: athrow
    //   2982: iconst_0
    //   2983: ifeq +11 -> 2994
    //   2986: new 232	java/lang/NullPointerException
    //   2989: dup
    //   2990: invokespecial 233	java/lang/NullPointerException:<init>	()V
    //   2993: athrow
    //   2994: getstatic 104	com/taobao/munion/net/b:u	Lcom/taobao/munion/net/c;
    //   2997: iconst_m1
    //   2998: iconst_0
    //   2999: invokestatic 183	java/lang/System:currentTimeMillis	()J
    //   3002: aload_0
    //   3003: getfield 67	com/taobao/munion/net/b:t	J
    //   3006: lsub
    //   3007: aload 16
    //   3009: invokeinterface 238 6 0
    //   3014: iconst_0
    //   3015: ifeq +11 -> 3026
    //   3018: new 232	java/lang/NullPointerException
    //   3021: dup
    //   3022: invokespecial 233	java/lang/NullPointerException:<init>	()V
    //   3025: athrow
    //   3026: iconst_0
    //   3027: ifeq +11 -> 3038
    //   3030: new 232	java/lang/NullPointerException
    //   3033: dup
    //   3034: invokespecial 233	java/lang/NullPointerException:<init>	()V
    //   3037: athrow
    //   3038: iconst_0
    //   3039: ifeq +11 -> 3050
    //   3042: new 232	java/lang/NullPointerException
    //   3045: dup
    //   3046: invokespecial 233	java/lang/NullPointerException:<init>	()V
    //   3049: athrow
    //   3050: iconst_0
    //   3051: ifeq +11 -> 3062
    //   3054: new 232	java/lang/NullPointerException
    //   3057: dup
    //   3058: invokespecial 233	java/lang/NullPointerException:<init>	()V
    //   3061: athrow
    //   3062: iconst_0
    //   3063: ifeq +11 -> 3074
    //   3066: new 232	java/lang/NullPointerException
    //   3069: dup
    //   3070: invokespecial 233	java/lang/NullPointerException:<init>	()V
    //   3073: athrow
    //   3074: aload 17
    //   3076: areturn
    //   3077: astore 17
    //   3079: iload_1
    //   3080: istore 4
    //   3082: aload 59
    //   3084: astore 33
    //   3086: aload 48
    //   3088: astore 35
    //   3090: aload 62
    //   3092: astore 37
    //   3094: aload 57
    //   3096: astore 38
    //   3098: aload 54
    //   3100: astore 39
    //   3102: iload_1
    //   3103: istore_2
    //   3104: aload 16
    //   3106: astore 29
    //   3108: aload 53
    //   3110: astore 28
    //   3112: aload 46
    //   3114: astore 27
    //   3116: aload 61
    //   3118: astore 26
    //   3120: aload 58
    //   3122: astore 25
    //   3124: aload 51
    //   3126: astore 24
    //   3128: iload_1
    //   3129: istore 5
    //   3131: iload_1
    //   3132: istore_3
    //   3133: aload 52
    //   3135: astore 36
    //   3137: aload 47
    //   3139: astore 34
    //   3141: aload 63
    //   3143: astore 32
    //   3145: aload 56
    //   3147: astore 31
    //   3149: aload 60
    //   3151: astore 30
    //   3153: aload 18
    //   3155: monitorexit
    //   3156: iload_1
    //   3157: istore 4
    //   3159: aload 59
    //   3161: astore 33
    //   3163: aload 48
    //   3165: astore 35
    //   3167: aload 62
    //   3169: astore 37
    //   3171: aload 57
    //   3173: astore 38
    //   3175: aload 54
    //   3177: astore 39
    //   3179: iload_1
    //   3180: istore_2
    //   3181: aload 16
    //   3183: astore 29
    //   3185: aload 53
    //   3187: astore 28
    //   3189: aload 46
    //   3191: astore 27
    //   3193: aload 61
    //   3195: astore 26
    //   3197: aload 58
    //   3199: astore 25
    //   3201: aload 51
    //   3203: astore 24
    //   3205: iload_1
    //   3206: istore 5
    //   3208: iload_1
    //   3209: istore_3
    //   3210: aload 52
    //   3212: astore 36
    //   3214: aload 47
    //   3216: astore 34
    //   3218: aload 63
    //   3220: astore 32
    //   3222: aload 56
    //   3224: astore 31
    //   3226: aload 60
    //   3228: astore 30
    //   3230: aload 17
    //   3232: athrow
    //   3233: iload_1
    //   3234: istore 4
    //   3236: aload 59
    //   3238: astore 33
    //   3240: aload 48
    //   3242: astore 35
    //   3244: aload 62
    //   3246: astore 37
    //   3248: aload 57
    //   3250: astore 38
    //   3252: aload 54
    //   3254: astore 39
    //   3256: iload_1
    //   3257: istore_2
    //   3258: aload 16
    //   3260: astore 29
    //   3262: aload 53
    //   3264: astore 28
    //   3266: aload 46
    //   3268: astore 27
    //   3270: aload 61
    //   3272: astore 26
    //   3274: aload 58
    //   3276: astore 25
    //   3278: aload 51
    //   3280: astore 24
    //   3282: iload_1
    //   3283: istore 5
    //   3285: iload_1
    //   3286: istore_3
    //   3287: aload 52
    //   3289: astore 36
    //   3291: aload 47
    //   3293: astore 34
    //   3295: aload 63
    //   3297: astore 32
    //   3299: aload 56
    //   3301: astore 31
    //   3303: aload 60
    //   3305: astore 30
    //   3307: aload 64
    //   3309: invokeinterface 419 1 0
    //   3314: invokeinterface 424 1 0
    //   3319: istore_1
    //   3320: iload_1
    //   3321: istore 4
    //   3323: aload 59
    //   3325: astore 33
    //   3327: aload 48
    //   3329: astore 35
    //   3331: aload 62
    //   3333: astore 37
    //   3335: aload 57
    //   3337: astore 38
    //   3339: aload 54
    //   3341: astore 39
    //   3343: iload_1
    //   3344: istore_2
    //   3345: aload 16
    //   3347: astore 29
    //   3349: aload 53
    //   3351: astore 28
    //   3353: aload 46
    //   3355: astore 27
    //   3357: aload 61
    //   3359: astore 26
    //   3361: aload 58
    //   3363: astore 25
    //   3365: aload 51
    //   3367: astore 24
    //   3369: iload_1
    //   3370: istore 5
    //   3372: iload_1
    //   3373: istore_3
    //   3374: aload 52
    //   3376: astore 36
    //   3378: aload 47
    //   3380: astore 34
    //   3382: aload 63
    //   3384: astore 32
    //   3386: aload 56
    //   3388: astore 31
    //   3390: aload 60
    //   3392: astore 30
    //   3394: invokestatic 200	com/taobao/munion/net/f:a	()Lcom/taobao/munion/net/f;
    //   3397: invokestatic 409	java/lang/System:nanoTime	()J
    //   3400: lconst_0
    //   3401: lsub
    //   3402: ldc2_w 425
    //   3405: ldiv
    //   3406: invokevirtual 429	com/taobao/munion/net/f:a	(J)V
    //   3409: sipush 416
    //   3412: iload_1
    //   3413: if_icmpne +206 -> 3619
    //   3416: iload_1
    //   3417: istore 4
    //   3419: aload 59
    //   3421: astore 33
    //   3423: aload 48
    //   3425: astore 35
    //   3427: aload 62
    //   3429: astore 37
    //   3431: aload 57
    //   3433: astore 38
    //   3435: aload 54
    //   3437: astore 39
    //   3439: iload_1
    //   3440: istore_2
    //   3441: aload 16
    //   3443: astore 29
    //   3445: aload 53
    //   3447: astore 28
    //   3449: aload 46
    //   3451: astore 27
    //   3453: aload 61
    //   3455: astore 26
    //   3457: aload 58
    //   3459: astore 25
    //   3461: aload 51
    //   3463: astore 24
    //   3465: iload_1
    //   3466: istore 5
    //   3468: iload_1
    //   3469: istore_3
    //   3470: aload 52
    //   3472: astore 36
    //   3474: aload 47
    //   3476: astore 34
    //   3478: aload 63
    //   3480: astore 32
    //   3482: aload 56
    //   3484: astore 31
    //   3486: aload 60
    //   3488: astore 30
    //   3490: new 227	com/taobao/munion/net/h
    //   3493: dup
    //   3494: sipush 416
    //   3497: ldc_w 431
    //   3500: aconst_null
    //   3501: invokespecial 336	com/taobao/munion/net/h:<init>	(ILjava/lang/String;[B)V
    //   3504: astore 17
    //   3506: getstatic 104	com/taobao/munion/net/b:u	Lcom/taobao/munion/net/c;
    //   3509: ifnull +47 -> 3556
    //   3512: iconst_0
    //   3513: ifeq +11 -> 3524
    //   3516: new 232	java/lang/NullPointerException
    //   3519: dup
    //   3520: invokespecial 233	java/lang/NullPointerException:<init>	()V
    //   3523: athrow
    //   3524: iconst_0
    //   3525: ifeq +11 -> 3536
    //   3528: new 232	java/lang/NullPointerException
    //   3531: dup
    //   3532: invokespecial 233	java/lang/NullPointerException:<init>	()V
    //   3535: athrow
    //   3536: getstatic 104	com/taobao/munion/net/b:u	Lcom/taobao/munion/net/c;
    //   3539: iload_1
    //   3540: iconst_0
    //   3541: invokestatic 183	java/lang/System:currentTimeMillis	()J
    //   3544: aload_0
    //   3545: getfield 67	com/taobao/munion/net/b:t	J
    //   3548: lsub
    //   3549: aload 16
    //   3551: invokeinterface 238 6 0
    //   3556: iconst_0
    //   3557: ifeq +11 -> 3568
    //   3560: new 232	java/lang/NullPointerException
    //   3563: dup
    //   3564: invokespecial 233	java/lang/NullPointerException:<init>	()V
    //   3567: athrow
    //   3568: iconst_0
    //   3569: ifeq +11 -> 3580
    //   3572: new 232	java/lang/NullPointerException
    //   3575: dup
    //   3576: invokespecial 233	java/lang/NullPointerException:<init>	()V
    //   3579: athrow
    //   3580: iconst_0
    //   3581: ifeq +11 -> 3592
    //   3584: new 232	java/lang/NullPointerException
    //   3587: dup
    //   3588: invokespecial 233	java/lang/NullPointerException:<init>	()V
    //   3591: athrow
    //   3592: iconst_0
    //   3593: ifeq +11 -> 3604
    //   3596: new 232	java/lang/NullPointerException
    //   3599: dup
    //   3600: invokespecial 233	java/lang/NullPointerException:<init>	()V
    //   3603: athrow
    //   3604: iconst_0
    //   3605: ifeq +11 -> 3616
    //   3608: new 232	java/lang/NullPointerException
    //   3611: dup
    //   3612: invokespecial 233	java/lang/NullPointerException:<init>	()V
    //   3615: athrow
    //   3616: aload 17
    //   3618: areturn
    //   3619: sipush 403
    //   3622: iload_1
    //   3623: if_icmpne +206 -> 3829
    //   3626: iload_1
    //   3627: istore 4
    //   3629: aload 59
    //   3631: astore 33
    //   3633: aload 48
    //   3635: astore 35
    //   3637: aload 62
    //   3639: astore 37
    //   3641: aload 57
    //   3643: astore 38
    //   3645: aload 54
    //   3647: astore 39
    //   3649: iload_1
    //   3650: istore_2
    //   3651: aload 16
    //   3653: astore 29
    //   3655: aload 53
    //   3657: astore 28
    //   3659: aload 46
    //   3661: astore 27
    //   3663: aload 61
    //   3665: astore 26
    //   3667: aload 58
    //   3669: astore 25
    //   3671: aload 51
    //   3673: astore 24
    //   3675: iload_1
    //   3676: istore 5
    //   3678: iload_1
    //   3679: istore_3
    //   3680: aload 52
    //   3682: astore 36
    //   3684: aload 47
    //   3686: astore 34
    //   3688: aload 63
    //   3690: astore 32
    //   3692: aload 56
    //   3694: astore 31
    //   3696: aload 60
    //   3698: astore 30
    //   3700: new 227	com/taobao/munion/net/h
    //   3703: dup
    //   3704: sipush 403
    //   3707: ldc_w 433
    //   3710: aconst_null
    //   3711: invokespecial 336	com/taobao/munion/net/h:<init>	(ILjava/lang/String;[B)V
    //   3714: astore 17
    //   3716: getstatic 104	com/taobao/munion/net/b:u	Lcom/taobao/munion/net/c;
    //   3719: ifnull +47 -> 3766
    //   3722: iconst_0
    //   3723: ifeq +11 -> 3734
    //   3726: new 232	java/lang/NullPointerException
    //   3729: dup
    //   3730: invokespecial 233	java/lang/NullPointerException:<init>	()V
    //   3733: athrow
    //   3734: iconst_0
    //   3735: ifeq +11 -> 3746
    //   3738: new 232	java/lang/NullPointerException
    //   3741: dup
    //   3742: invokespecial 233	java/lang/NullPointerException:<init>	()V
    //   3745: athrow
    //   3746: getstatic 104	com/taobao/munion/net/b:u	Lcom/taobao/munion/net/c;
    //   3749: iload_1
    //   3750: iconst_0
    //   3751: invokestatic 183	java/lang/System:currentTimeMillis	()J
    //   3754: aload_0
    //   3755: getfield 67	com/taobao/munion/net/b:t	J
    //   3758: lsub
    //   3759: aload 16
    //   3761: invokeinterface 238 6 0
    //   3766: iconst_0
    //   3767: ifeq +11 -> 3778
    //   3770: new 232	java/lang/NullPointerException
    //   3773: dup
    //   3774: invokespecial 233	java/lang/NullPointerException:<init>	()V
    //   3777: athrow
    //   3778: iconst_0
    //   3779: ifeq +11 -> 3790
    //   3782: new 232	java/lang/NullPointerException
    //   3785: dup
    //   3786: invokespecial 233	java/lang/NullPointerException:<init>	()V
    //   3789: athrow
    //   3790: iconst_0
    //   3791: ifeq +11 -> 3802
    //   3794: new 232	java/lang/NullPointerException
    //   3797: dup
    //   3798: invokespecial 233	java/lang/NullPointerException:<init>	()V
    //   3801: athrow
    //   3802: iconst_0
    //   3803: ifeq +11 -> 3814
    //   3806: new 232	java/lang/NullPointerException
    //   3809: dup
    //   3810: invokespecial 233	java/lang/NullPointerException:<init>	()V
    //   3813: athrow
    //   3814: iconst_0
    //   3815: ifeq +11 -> 3826
    //   3818: new 232	java/lang/NullPointerException
    //   3821: dup
    //   3822: invokespecial 233	java/lang/NullPointerException:<init>	()V
    //   3825: athrow
    //   3826: aload 17
    //   3828: areturn
    //   3829: iload_1
    //   3830: istore 4
    //   3832: aload 59
    //   3834: astore 33
    //   3836: aload 48
    //   3838: astore 35
    //   3840: aload 62
    //   3842: astore 37
    //   3844: aload 57
    //   3846: astore 38
    //   3848: aload 54
    //   3850: astore 39
    //   3852: iload_1
    //   3853: istore_2
    //   3854: aload 16
    //   3856: astore 29
    //   3858: aload 53
    //   3860: astore 28
    //   3862: aload 46
    //   3864: astore 27
    //   3866: aload 61
    //   3868: astore 26
    //   3870: aload 58
    //   3872: astore 25
    //   3874: aload 51
    //   3876: astore 24
    //   3878: iload_1
    //   3879: istore 5
    //   3881: iload_1
    //   3882: istore_3
    //   3883: aload 52
    //   3885: astore 36
    //   3887: aload 47
    //   3889: astore 34
    //   3891: aload 63
    //   3893: astore 32
    //   3895: aload 56
    //   3897: astore 31
    //   3899: aload 60
    //   3901: astore 30
    //   3903: aload_0
    //   3904: getfield 87	com/taobao/munion/net/b:p	Lcom/taobao/munion/net/e;
    //   3907: getfield 435	com/taobao/munion/net/e:t	Ljava/lang/String;
    //   3910: ifnull +678 -> 4588
    //   3913: iload_1
    //   3914: istore 4
    //   3916: aload 59
    //   3918: astore 33
    //   3920: aload 48
    //   3922: astore 35
    //   3924: aload 62
    //   3926: astore 37
    //   3928: aload 57
    //   3930: astore 38
    //   3932: aload 54
    //   3934: astore 39
    //   3936: iload_1
    //   3937: istore_2
    //   3938: aload 16
    //   3940: astore 29
    //   3942: aload 53
    //   3944: astore 28
    //   3946: aload 46
    //   3948: astore 27
    //   3950: aload 61
    //   3952: astore 26
    //   3954: aload 58
    //   3956: astore 25
    //   3958: aload 51
    //   3960: astore 24
    //   3962: iload_1
    //   3963: istore 5
    //   3965: iload_1
    //   3966: istore_3
    //   3967: aload 52
    //   3969: astore 36
    //   3971: aload 47
    //   3973: astore 34
    //   3975: aload 63
    //   3977: astore 32
    //   3979: aload 56
    //   3981: astore 31
    //   3983: aload 60
    //   3985: astore 30
    //   3987: aload 19
    //   3989: aload_0
    //   3990: getfield 87	com/taobao/munion/net/b:p	Lcom/taobao/munion/net/e;
    //   3993: getfield 435	com/taobao/munion/net/e:t	Ljava/lang/String;
    //   3996: invokevirtual 439	java/lang/String:contains	(Ljava/lang/CharSequence;)Z
    //   3999: ifeq +589 -> 4588
    //   4002: iconst_1
    //   4003: istore 6
    //   4005: iload_1
    //   4006: sipush 302
    //   4009: if_icmpne +1322 -> 5331
    //   4012: iload_1
    //   4013: istore 4
    //   4015: aload 59
    //   4017: astore 33
    //   4019: aload 48
    //   4021: astore 35
    //   4023: aload 62
    //   4025: astore 37
    //   4027: aload 57
    //   4029: astore 38
    //   4031: aload 54
    //   4033: astore 39
    //   4035: iload_1
    //   4036: istore_2
    //   4037: aload 16
    //   4039: astore 29
    //   4041: aload 53
    //   4043: astore 28
    //   4045: aload 46
    //   4047: astore 27
    //   4049: aload 61
    //   4051: astore 26
    //   4053: aload 58
    //   4055: astore 25
    //   4057: aload 51
    //   4059: astore 24
    //   4061: iload_1
    //   4062: istore 5
    //   4064: iload_1
    //   4065: istore_3
    //   4066: aload 52
    //   4068: astore 36
    //   4070: aload 47
    //   4072: astore 34
    //   4074: aload 63
    //   4076: astore 32
    //   4078: aload 56
    //   4080: astore 31
    //   4082: aload 60
    //   4084: astore 30
    //   4086: aload_0
    //   4087: getfield 87	com/taobao/munion/net/b:p	Lcom/taobao/munion/net/e;
    //   4090: getfield 441	com/taobao/munion/net/e:d	Z
    //   4093: ifeq +1238 -> 5331
    //   4096: iload 6
    //   4098: ifne +1233 -> 5331
    //   4101: iload_1
    //   4102: istore 4
    //   4104: aload 59
    //   4106: astore 33
    //   4108: aload 48
    //   4110: astore 35
    //   4112: aload 62
    //   4114: astore 37
    //   4116: aload 57
    //   4118: astore 38
    //   4120: aload 54
    //   4122: astore 39
    //   4124: iload_1
    //   4125: istore_2
    //   4126: aload 16
    //   4128: astore 29
    //   4130: aload 53
    //   4132: astore 28
    //   4134: aload 46
    //   4136: astore 27
    //   4138: aload 61
    //   4140: astore 26
    //   4142: aload 58
    //   4144: astore 25
    //   4146: aload 51
    //   4148: astore 24
    //   4150: iload_1
    //   4151: istore 5
    //   4153: iload_1
    //   4154: istore_3
    //   4155: aload 52
    //   4157: astore 36
    //   4159: aload 47
    //   4161: astore 34
    //   4163: aload 63
    //   4165: astore 32
    //   4167: aload 56
    //   4169: astore 31
    //   4171: aload 60
    //   4173: astore 30
    //   4175: aload_0
    //   4176: getfield 65	com/taobao/munion/net/b:s	I
    //   4179: iconst_5
    //   4180: if_icmple +414 -> 4594
    //   4183: iload_1
    //   4184: istore 4
    //   4186: aload 59
    //   4188: astore 33
    //   4190: aload 48
    //   4192: astore 35
    //   4194: aload 62
    //   4196: astore 37
    //   4198: aload 57
    //   4200: astore 38
    //   4202: aload 54
    //   4204: astore 39
    //   4206: iload_1
    //   4207: istore_2
    //   4208: aload 16
    //   4210: astore 29
    //   4212: aload 53
    //   4214: astore 28
    //   4216: aload 46
    //   4218: astore 27
    //   4220: aload 61
    //   4222: astore 26
    //   4224: aload 58
    //   4226: astore 25
    //   4228: aload 51
    //   4230: astore 24
    //   4232: iload_1
    //   4233: istore 5
    //   4235: iload_1
    //   4236: istore_3
    //   4237: aload 52
    //   4239: astore 36
    //   4241: aload 47
    //   4243: astore 34
    //   4245: aload 63
    //   4247: astore 32
    //   4249: aload 56
    //   4251: astore 31
    //   4253: aload 60
    //   4255: astore 30
    //   4257: new 443	com/taobao/munion/net/b$h
    //   4260: dup
    //   4261: aload_0
    //   4262: ldc_w 445
    //   4265: invokespecial 448	com/taobao/munion/net/b$h:<init>	(Lcom/taobao/munion/net/b;Ljava/lang/String;)V
    //   4268: athrow
    //   4269: astore 20
    //   4271: aload 39
    //   4273: astore 22
    //   4275: aload 38
    //   4277: astore 17
    //   4279: aload 37
    //   4281: astore 21
    //   4283: iload 4
    //   4285: istore_1
    //   4286: aload 18
    //   4288: ifnull +47 -> 4335
    //   4291: iload_1
    //   4292: istore_2
    //   4293: aload 16
    //   4295: astore 29
    //   4297: aload 33
    //   4299: astore 28
    //   4301: aload 35
    //   4303: astore 27
    //   4305: aload 21
    //   4307: astore 26
    //   4309: aload 17
    //   4311: astore 25
    //   4313: aload 22
    //   4315: astore 24
    //   4317: aload 18
    //   4319: monitorenter
    //   4320: aload 18
    //   4322: aload 18
    //   4324: getfield 280	com/taobao/munion/net/b$f:b	J
    //   4327: lconst_1
    //   4328: ladd
    //   4329: putfield 280	com/taobao/munion/net/b$f:b	J
    //   4332: aload 18
    //   4334: monitorexit
    //   4335: iload_1
    //   4336: istore_2
    //   4337: aload 16
    //   4339: astore 29
    //   4341: aload 33
    //   4343: astore 28
    //   4345: aload 35
    //   4347: astore 27
    //   4349: aload 21
    //   4351: astore 26
    //   4353: aload 17
    //   4355: astore 25
    //   4357: aload 22
    //   4359: astore 24
    //   4361: invokestatic 200	com/taobao/munion/net/f:a	()Lcom/taobao/munion/net/f;
    //   4364: invokevirtual 286	com/taobao/munion/net/f:e	()V
    //   4367: iload_1
    //   4368: istore_2
    //   4369: aload 16
    //   4371: astore 29
    //   4373: aload 33
    //   4375: astore 28
    //   4377: aload 35
    //   4379: astore 27
    //   4381: aload 21
    //   4383: astore 26
    //   4385: aload 17
    //   4387: astore 25
    //   4389: aload 22
    //   4391: astore 24
    //   4393: aload 19
    //   4395: invokestatic 284	com/taobao/munion/net/o:b	(Ljava/lang/String;)V
    //   4398: aload 35
    //   4400: ifnull +34 -> 4434
    //   4403: iload_1
    //   4404: istore_2
    //   4405: aload 16
    //   4407: astore 29
    //   4409: aload 33
    //   4411: astore 28
    //   4413: aload 35
    //   4415: astore 27
    //   4417: aload 21
    //   4419: astore 26
    //   4421: aload 17
    //   4423: astore 25
    //   4425: aload 22
    //   4427: astore 24
    //   4429: aload 35
    //   4431: invokevirtual 451	java/io/ByteArrayOutputStream:reset	()V
    //   4434: iload_1
    //   4435: istore_2
    //   4436: aload 16
    //   4438: astore 29
    //   4440: aload 33
    //   4442: astore 28
    //   4444: aload 35
    //   4446: astore 27
    //   4448: aload 21
    //   4450: astore 26
    //   4452: aload 17
    //   4454: astore 25
    //   4456: aload 22
    //   4458: astore 24
    //   4460: aload_0
    //   4461: getfield 87	com/taobao/munion/net/b:p	Lcom/taobao/munion/net/e;
    //   4464: getfield 356	com/taobao/munion/net/e:k	Ljava/util/Map;
    //   4467: ifnull +41 -> 4508
    //   4470: iload_1
    //   4471: istore_2
    //   4472: aload 16
    //   4474: astore 29
    //   4476: aload 33
    //   4478: astore 28
    //   4480: aload 35
    //   4482: astore 27
    //   4484: aload 21
    //   4486: astore 26
    //   4488: aload 17
    //   4490: astore 25
    //   4492: aload 22
    //   4494: astore 24
    //   4496: aload_0
    //   4497: getfield 87	com/taobao/munion/net/b:p	Lcom/taobao/munion/net/e;
    //   4500: getfield 356	com/taobao/munion/net/e:k	Ljava/util/Map;
    //   4503: invokeinterface 454 1 0
    //   4508: iload_1
    //   4509: istore_2
    //   4510: aload 16
    //   4512: astore 29
    //   4514: aload 33
    //   4516: astore 28
    //   4518: aload 35
    //   4520: astore 27
    //   4522: aload 21
    //   4524: astore 26
    //   4526: aload 17
    //   4528: astore 25
    //   4530: aload 22
    //   4532: astore 24
    //   4534: new 456	com/taobao/munion/net/b$c
    //   4537: dup
    //   4538: aload_0
    //   4539: new 251	java/lang/StringBuilder
    //   4542: dup
    //   4543: ldc_w 291
    //   4546: invokespecial 292	java/lang/StringBuilder:<init>	(Ljava/lang/String;)V
    //   4549: aload 19
    //   4551: invokevirtual 256	java/lang/StringBuilder:append	(Ljava/lang/String;)Ljava/lang/StringBuilder;
    //   4554: ldc_w 294
    //   4557: invokevirtual 256	java/lang/StringBuilder:append	(Ljava/lang/String;)Ljava/lang/StringBuilder;
    //   4560: aload 20
    //   4562: invokevirtual 457	java/lang/Exception:getMessage	()Ljava/lang/String;
    //   4565: invokevirtual 256	java/lang/StringBuilder:append	(Ljava/lang/String;)Ljava/lang/StringBuilder;
    //   4568: invokevirtual 261	java/lang/StringBuilder:toString	()Ljava/lang/String;
    //   4571: iload 10
    //   4573: invokespecial 458	com/taobao/munion/net/b$c:<init>	(Lcom/taobao/munion/net/b;Ljava/lang/String;I)V
    //   4576: athrow
    //   4577: astore 16
    //   4579: iload_2
    //   4580: istore_1
    //   4581: aload 26
    //   4583: astore 17
    //   4585: goto -3254 -> 1331
    //   4588: iconst_0
    //   4589: istore 6
    //   4591: goto -586 -> 4005
    //   4594: iload_1
    //   4595: istore 4
    //   4597: aload 59
    //   4599: astore 33
    //   4601: aload 48
    //   4603: astore 35
    //   4605: aload 62
    //   4607: astore 37
    //   4609: aload 57
    //   4611: astore 38
    //   4613: aload 54
    //   4615: astore 39
    //   4617: iload_1
    //   4618: istore_2
    //   4619: aload 16
    //   4621: astore 29
    //   4623: aload 53
    //   4625: astore 28
    //   4627: aload 46
    //   4629: astore 27
    //   4631: aload 61
    //   4633: astore 26
    //   4635: aload 58
    //   4637: astore 25
    //   4639: aload 51
    //   4641: astore 24
    //   4643: iload_1
    //   4644: istore 5
    //   4646: iload_1
    //   4647: istore_3
    //   4648: aload 52
    //   4650: astore 36
    //   4652: aload 47
    //   4654: astore 34
    //   4656: aload 63
    //   4658: astore 32
    //   4660: aload 56
    //   4662: astore 31
    //   4664: aload 60
    //   4666: astore 30
    //   4668: aload_0
    //   4669: aload_0
    //   4670: getfield 65	com/taobao/munion/net/b:s	I
    //   4673: iconst_1
    //   4674: iadd
    //   4675: putfield 65	com/taobao/munion/net/b:s	I
    //   4678: iload_1
    //   4679: istore 4
    //   4681: aload 59
    //   4683: astore 33
    //   4685: aload 48
    //   4687: astore 35
    //   4689: aload 62
    //   4691: astore 37
    //   4693: aload 57
    //   4695: astore 38
    //   4697: aload 54
    //   4699: astore 39
    //   4701: iload_1
    //   4702: istore_2
    //   4703: aload 16
    //   4705: astore 29
    //   4707: aload 53
    //   4709: astore 28
    //   4711: aload 46
    //   4713: astore 27
    //   4715: aload 61
    //   4717: astore 26
    //   4719: aload 58
    //   4721: astore 25
    //   4723: aload 51
    //   4725: astore 24
    //   4727: iload_1
    //   4728: istore 5
    //   4730: iload_1
    //   4731: istore_3
    //   4732: aload 52
    //   4734: astore 36
    //   4736: aload 47
    //   4738: astore 34
    //   4740: aload 63
    //   4742: astore 32
    //   4744: aload 56
    //   4746: astore 31
    //   4748: aload 60
    //   4750: astore 30
    //   4752: aload 64
    //   4754: ldc 22
    //   4756: invokeinterface 462 2 0
    //   4761: invokeinterface 466 1 0
    //   4766: astore 20
    //   4768: aload 20
    //   4770: astore 17
    //   4772: aload 20
    //   4774: ifnonnull +94 -> 4868
    //   4777: iload_1
    //   4778: istore 4
    //   4780: aload 59
    //   4782: astore 33
    //   4784: aload 48
    //   4786: astore 35
    //   4788: aload 62
    //   4790: astore 37
    //   4792: aload 57
    //   4794: astore 38
    //   4796: aload 54
    //   4798: astore 39
    //   4800: iload_1
    //   4801: istore_2
    //   4802: aload 16
    //   4804: astore 29
    //   4806: aload 53
    //   4808: astore 28
    //   4810: aload 46
    //   4812: astore 27
    //   4814: aload 61
    //   4816: astore 26
    //   4818: aload 58
    //   4820: astore 25
    //   4822: aload 51
    //   4824: astore 24
    //   4826: iload_1
    //   4827: istore 5
    //   4829: iload_1
    //   4830: istore_3
    //   4831: aload 52
    //   4833: astore 36
    //   4835: aload 47
    //   4837: astore 34
    //   4839: aload 63
    //   4841: astore 32
    //   4843: aload 56
    //   4845: astore 31
    //   4847: aload 60
    //   4849: astore 30
    //   4851: aload 64
    //   4853: ldc_w 468
    //   4856: invokeinterface 462 2 0
    //   4861: invokeinterface 466 1 0
    //   4866: astore 17
    //   4868: aload 17
    //   4870: ifnull +461 -> 5331
    //   4873: iload_1
    //   4874: istore 4
    //   4876: aload 59
    //   4878: astore 33
    //   4880: aload 48
    //   4882: astore 35
    //   4884: aload 62
    //   4886: astore 37
    //   4888: aload 57
    //   4890: astore 38
    //   4892: aload 54
    //   4894: astore 39
    //   4896: iload_1
    //   4897: istore_2
    //   4898: aload 16
    //   4900: astore 29
    //   4902: aload 53
    //   4904: astore 28
    //   4906: aload 46
    //   4908: astore 27
    //   4910: aload 61
    //   4912: astore 26
    //   4914: aload 58
    //   4916: astore 25
    //   4918: aload 51
    //   4920: astore 24
    //   4922: aload 17
    //   4924: astore 20
    //   4926: iload_1
    //   4927: istore 5
    //   4929: iload_1
    //   4930: istore_3
    //   4931: aload 52
    //   4933: astore 36
    //   4935: aload 47
    //   4937: astore 34
    //   4939: aload 63
    //   4941: astore 32
    //   4943: aload 56
    //   4945: astore 31
    //   4947: aload 60
    //   4949: astore 30
    //   4951: aload 17
    //   4953: invokevirtual 471	java/lang/String:toLowerCase	()Ljava/lang/String;
    //   4956: ldc_w 473
    //   4959: invokevirtual 477	java/lang/String:startsWith	(Ljava/lang/String;)Z
    //   4962: ifne +96 -> 5058
    //   4965: iload_1
    //   4966: istore 4
    //   4968: aload 59
    //   4970: astore 33
    //   4972: aload 48
    //   4974: astore 35
    //   4976: aload 62
    //   4978: astore 37
    //   4980: aload 57
    //   4982: astore 38
    //   4984: aload 54
    //   4986: astore 39
    //   4988: iload_1
    //   4989: istore_2
    //   4990: aload 16
    //   4992: astore 29
    //   4994: aload 53
    //   4996: astore 28
    //   4998: aload 46
    //   5000: astore 27
    //   5002: aload 61
    //   5004: astore 26
    //   5006: aload 58
    //   5008: astore 25
    //   5010: aload 51
    //   5012: astore 24
    //   5014: iload_1
    //   5015: istore 5
    //   5017: iload_1
    //   5018: istore_3
    //   5019: aload 52
    //   5021: astore 36
    //   5023: aload 47
    //   5025: astore 34
    //   5027: aload 63
    //   5029: astore 32
    //   5031: aload 56
    //   5033: astore 31
    //   5035: aload 60
    //   5037: astore 30
    //   5039: new 209	java/net/URL
    //   5042: dup
    //   5043: ldc_w 473
    //   5046: aload 19
    //   5048: aload 17
    //   5050: invokespecial 480	java/net/URL:<init>	(Ljava/lang/String;Ljava/lang/String;Ljava/lang/String;)V
    //   5053: invokevirtual 481	java/net/URL:toString	()Ljava/lang/String;
    //   5056: astore 20
    //   5058: iload_1
    //   5059: istore 4
    //   5061: aload 59
    //   5063: astore 33
    //   5065: aload 48
    //   5067: astore 35
    //   5069: aload 62
    //   5071: astore 37
    //   5073: aload 57
    //   5075: astore 38
    //   5077: aload 54
    //   5079: astore 39
    //   5081: iload_1
    //   5082: istore_2
    //   5083: aload 16
    //   5085: astore 29
    //   5087: aload 53
    //   5089: astore 28
    //   5091: aload 46
    //   5093: astore 27
    //   5095: aload 61
    //   5097: astore 26
    //   5099: aload 58
    //   5101: astore 25
    //   5103: aload 51
    //   5105: astore 24
    //   5107: iload_1
    //   5108: istore 5
    //   5110: iload_1
    //   5111: istore_3
    //   5112: aload 52
    //   5114: astore 36
    //   5116: aload 47
    //   5118: astore 34
    //   5120: aload 63
    //   5122: astore 32
    //   5124: aload 56
    //   5126: astore 31
    //   5128: aload 60
    //   5130: astore 30
    //   5132: aload_0
    //   5133: aload 20
    //   5135: putfield 85	com/taobao/munion/net/b:q	Ljava/lang/String;
    //   5138: iload_1
    //   5139: istore 4
    //   5141: aload 59
    //   5143: astore 33
    //   5145: aload 48
    //   5147: astore 35
    //   5149: aload 62
    //   5151: astore 37
    //   5153: aload 57
    //   5155: astore 38
    //   5157: aload 54
    //   5159: astore 39
    //   5161: iload_1
    //   5162: istore_2
    //   5163: aload 16
    //   5165: astore 29
    //   5167: aload 53
    //   5169: astore 28
    //   5171: aload 46
    //   5173: astore 27
    //   5175: aload 61
    //   5177: astore 26
    //   5179: aload 58
    //   5181: astore 25
    //   5183: aload 51
    //   5185: astore 24
    //   5187: iload_1
    //   5188: istore 5
    //   5190: iload_1
    //   5191: istore_3
    //   5192: aload 52
    //   5194: astore 36
    //   5196: aload 47
    //   5198: astore 34
    //   5200: aload 63
    //   5202: astore 32
    //   5204: aload 56
    //   5206: astore 31
    //   5208: aload 60
    //   5210: astore 30
    //   5212: aload_0
    //   5213: invokespecial 483	com/taobao/munion/net/b:e	()Lcom/taobao/munion/net/h;
    //   5216: astore 17
    //   5218: getstatic 104	com/taobao/munion/net/b:u	Lcom/taobao/munion/net/c;
    //   5221: ifnull +47 -> 5268
    //   5224: iconst_0
    //   5225: ifeq +11 -> 5236
    //   5228: new 232	java/lang/NullPointerException
    //   5231: dup
    //   5232: invokespecial 233	java/lang/NullPointerException:<init>	()V
    //   5235: athrow
    //   5236: iconst_0
    //   5237: ifeq +11 -> 5248
    //   5240: new 232	java/lang/NullPointerException
    //   5243: dup
    //   5244: invokespecial 233	java/lang/NullPointerException:<init>	()V
    //   5247: athrow
    //   5248: getstatic 104	com/taobao/munion/net/b:u	Lcom/taobao/munion/net/c;
    //   5251: iload_1
    //   5252: iconst_0
    //   5253: invokestatic 183	java/lang/System:currentTimeMillis	()J
    //   5256: aload_0
    //   5257: getfield 67	com/taobao/munion/net/b:t	J
    //   5260: lsub
    //   5261: aload 16
    //   5263: invokeinterface 238 6 0
    //   5268: iconst_0
    //   5269: ifeq +11 -> 5280
    //   5272: new 232	java/lang/NullPointerException
    //   5275: dup
    //   5276: invokespecial 233	java/lang/NullPointerException:<init>	()V
    //   5279: athrow
    //   5280: iconst_0
    //   5281: ifeq +11 -> 5292
    //   5284: new 232	java/lang/NullPointerException
    //   5287: dup
    //   5288: invokespecial 233	java/lang/NullPointerException:<init>	()V
    //   5291: athrow
    //   5292: iconst_0
    //   5293: ifeq +11 -> 5304
    //   5296: new 232	java/lang/NullPointerException
    //   5299: dup
    //   5300: invokespecial 233	java/lang/NullPointerException:<init>	()V
    //   5303: athrow
    //   5304: iconst_0
    //   5305: ifeq +11 -> 5316
    //   5308: new 232	java/lang/NullPointerException
    //   5311: dup
    //   5312: invokespecial 233	java/lang/NullPointerException:<init>	()V
    //   5315: athrow
    //   5316: iconst_0
    //   5317: ifeq +11 -> 5328
    //   5320: new 232	java/lang/NullPointerException
    //   5323: dup
    //   5324: invokespecial 233	java/lang/NullPointerException:<init>	()V
    //   5327: athrow
    //   5328: aload 17
    //   5330: areturn
    //   5331: iload_1
    //   5332: sipush 302
    //   5335: if_icmpne +175 -> 5510
    //   5338: iload_1
    //   5339: istore 4
    //   5341: aload 59
    //   5343: astore 33
    //   5345: aload 48
    //   5347: astore 35
    //   5349: aload 62
    //   5351: astore 37
    //   5353: aload 57
    //   5355: astore 38
    //   5357: aload 54
    //   5359: astore 39
    //   5361: iload_1
    //   5362: istore_2
    //   5363: aload 16
    //   5365: astore 29
    //   5367: aload 53
    //   5369: astore 28
    //   5371: aload 46
    //   5373: astore 27
    //   5375: aload 61
    //   5377: astore 26
    //   5379: aload 58
    //   5381: astore 25
    //   5383: aload 51
    //   5385: astore 24
    //   5387: iload_1
    //   5388: istore 5
    //   5390: iload_1
    //   5391: istore_3
    //   5392: aload 52
    //   5394: astore 36
    //   5396: aload 47
    //   5398: astore 34
    //   5400: aload 63
    //   5402: astore 32
    //   5404: aload 56
    //   5406: astore 31
    //   5408: aload 60
    //   5410: astore 30
    //   5412: aload_0
    //   5413: getfield 87	com/taobao/munion/net/b:p	Lcom/taobao/munion/net/e;
    //   5416: getfield 356	com/taobao/munion/net/e:k	Ljava/util/Map;
    //   5419: ifnonnull +91 -> 5510
    //   5422: iload_1
    //   5423: istore 4
    //   5425: aload 59
    //   5427: astore 33
    //   5429: aload 48
    //   5431: astore 35
    //   5433: aload 62
    //   5435: astore 37
    //   5437: aload 57
    //   5439: astore 38
    //   5441: aload 54
    //   5443: astore 39
    //   5445: iload_1
    //   5446: istore_2
    //   5447: aload 16
    //   5449: astore 29
    //   5451: aload 53
    //   5453: astore 28
    //   5455: aload 46
    //   5457: astore 27
    //   5459: aload 61
    //   5461: astore 26
    //   5463: aload 58
    //   5465: astore 25
    //   5467: aload 51
    //   5469: astore 24
    //   5471: iload_1
    //   5472: istore 5
    //   5474: iload_1
    //   5475: istore_3
    //   5476: aload 52
    //   5478: astore 36
    //   5480: aload 47
    //   5482: astore 34
    //   5484: aload 63
    //   5486: astore 32
    //   5488: aload 56
    //   5490: astore 31
    //   5492: aload 60
    //   5494: astore 30
    //   5496: aload_0
    //   5497: getfield 87	com/taobao/munion/net/b:p	Lcom/taobao/munion/net/e;
    //   5500: new 485	java/util/HashMap
    //   5503: dup
    //   5504: invokespecial 486	java/util/HashMap:<init>	()V
    //   5507: putfield 356	com/taobao/munion/net/e:k	Ljava/util/Map;
    //   5510: iload_1
    //   5511: istore 4
    //   5513: aload 59
    //   5515: astore 33
    //   5517: aload 48
    //   5519: astore 35
    //   5521: aload 62
    //   5523: astore 37
    //   5525: aload 57
    //   5527: astore 38
    //   5529: aload 54
    //   5531: astore 39
    //   5533: iload_1
    //   5534: istore_2
    //   5535: aload 16
    //   5537: astore 29
    //   5539: aload 53
    //   5541: astore 28
    //   5543: aload 46
    //   5545: astore 27
    //   5547: aload 61
    //   5549: astore 26
    //   5551: aload 58
    //   5553: astore 25
    //   5555: aload 51
    //   5557: astore 24
    //   5559: iload_1
    //   5560: istore 5
    //   5562: iload_1
    //   5563: istore_3
    //   5564: aload 52
    //   5566: astore 36
    //   5568: aload 47
    //   5570: astore 34
    //   5572: aload 63
    //   5574: astore 32
    //   5576: aload 56
    //   5578: astore 31
    //   5580: aload 60
    //   5582: astore 30
    //   5584: aload_0
    //   5585: getfield 87	com/taobao/munion/net/b:p	Lcom/taobao/munion/net/e;
    //   5588: getfield 356	com/taobao/munion/net/e:k	Ljava/util/Map;
    //   5591: ifnull +633 -> 6224
    //   5594: iload_1
    //   5595: istore 4
    //   5597: aload 59
    //   5599: astore 33
    //   5601: aload 48
    //   5603: astore 35
    //   5605: aload 62
    //   5607: astore 37
    //   5609: aload 57
    //   5611: astore 38
    //   5613: aload 54
    //   5615: astore 39
    //   5617: iload_1
    //   5618: istore_2
    //   5619: aload 16
    //   5621: astore 29
    //   5623: aload 53
    //   5625: astore 28
    //   5627: aload 46
    //   5629: astore 27
    //   5631: aload 61
    //   5633: astore 26
    //   5635: aload 58
    //   5637: astore 25
    //   5639: aload 51
    //   5641: astore 24
    //   5643: iload_1
    //   5644: istore 5
    //   5646: iload_1
    //   5647: istore_3
    //   5648: aload 52
    //   5650: astore 36
    //   5652: aload 47
    //   5654: astore 34
    //   5656: aload 63
    //   5658: astore 32
    //   5660: aload 56
    //   5662: astore 31
    //   5664: aload 60
    //   5666: astore 30
    //   5668: aload_0
    //   5669: getfield 87	com/taobao/munion/net/b:p	Lcom/taobao/munion/net/e;
    //   5672: getfield 356	com/taobao/munion/net/e:k	Ljava/util/Map;
    //   5675: ldc 13
    //   5677: iload_1
    //   5678: invokestatic 490	java/lang/Integer:toString	(I)Ljava/lang/String;
    //   5681: invokeinterface 494 3 0
    //   5686: pop
    //   5687: iload_1
    //   5688: istore 4
    //   5690: aload 59
    //   5692: astore 33
    //   5694: aload 48
    //   5696: astore 35
    //   5698: aload 62
    //   5700: astore 37
    //   5702: aload 57
    //   5704: astore 38
    //   5706: aload 54
    //   5708: astore 39
    //   5710: iload_1
    //   5711: istore_2
    //   5712: aload 16
    //   5714: astore 29
    //   5716: aload 53
    //   5718: astore 28
    //   5720: aload 46
    //   5722: astore 27
    //   5724: aload 61
    //   5726: astore 26
    //   5728: aload 58
    //   5730: astore 25
    //   5732: aload 51
    //   5734: astore 24
    //   5736: iload_1
    //   5737: istore 5
    //   5739: iload_1
    //   5740: istore_3
    //   5741: aload 52
    //   5743: astore 36
    //   5745: aload 47
    //   5747: astore 34
    //   5749: aload 63
    //   5751: astore 32
    //   5753: aload 56
    //   5755: astore 31
    //   5757: aload 60
    //   5759: astore 30
    //   5761: aload 64
    //   5763: invokeinterface 498 1 0
    //   5768: astore 20
    //   5770: iconst_0
    //   5771: istore 6
    //   5773: iload_1
    //   5774: istore 4
    //   5776: aload 59
    //   5778: astore 33
    //   5780: aload 48
    //   5782: astore 35
    //   5784: aload 62
    //   5786: astore 37
    //   5788: aload 57
    //   5790: astore 38
    //   5792: aload 54
    //   5794: astore 39
    //   5796: iload_1
    //   5797: istore_2
    //   5798: aload 16
    //   5800: astore 29
    //   5802: aload 53
    //   5804: astore 28
    //   5806: aload 46
    //   5808: astore 27
    //   5810: aload 61
    //   5812: astore 26
    //   5814: aload 58
    //   5816: astore 25
    //   5818: aload 51
    //   5820: astore 24
    //   5822: iload_1
    //   5823: istore 5
    //   5825: iload_1
    //   5826: istore_3
    //   5827: aload 52
    //   5829: astore 36
    //   5831: aload 47
    //   5833: astore 34
    //   5835: aload 63
    //   5837: astore 32
    //   5839: aload 56
    //   5841: astore 31
    //   5843: aload 60
    //   5845: astore 30
    //   5847: iload 6
    //   5849: aload 20
    //   5851: arraylength
    //   5852: if_icmpge +372 -> 6224
    //   5855: aload 20
    //   5857: iload 6
    //   5859: aaload
    //   5860: astore 65
    //   5862: aload 65
    //   5864: ifnull +5929 -> 11793
    //   5867: iload_1
    //   5868: istore 4
    //   5870: aload 59
    //   5872: astore 33
    //   5874: aload 48
    //   5876: astore 35
    //   5878: aload 62
    //   5880: astore 37
    //   5882: aload 57
    //   5884: astore 38
    //   5886: aload 54
    //   5888: astore 39
    //   5890: iload_1
    //   5891: istore_2
    //   5892: aload 16
    //   5894: astore 29
    //   5896: aload 53
    //   5898: astore 28
    //   5900: aload 46
    //   5902: astore 27
    //   5904: aload 61
    //   5906: astore 26
    //   5908: aload 58
    //   5910: astore 25
    //   5912: aload 51
    //   5914: astore 24
    //   5916: iload_1
    //   5917: istore 5
    //   5919: iload_1
    //   5920: istore_3
    //   5921: aload 52
    //   5923: astore 36
    //   5925: aload 47
    //   5927: astore 34
    //   5929: aload 63
    //   5931: astore 32
    //   5933: aload 56
    //   5935: astore 31
    //   5937: aload 60
    //   5939: astore 30
    //   5941: aload 65
    //   5943: invokeinterface 501 1 0
    //   5948: astore 17
    //   5950: aload 17
    //   5952: ifnull +5841 -> 11793
    //   5955: iload_1
    //   5956: istore 4
    //   5958: aload 59
    //   5960: astore 33
    //   5962: aload 48
    //   5964: astore 35
    //   5966: aload 62
    //   5968: astore 37
    //   5970: aload 57
    //   5972: astore 38
    //   5974: aload 54
    //   5976: astore 39
    //   5978: iload_1
    //   5979: istore_2
    //   5980: aload 16
    //   5982: astore 29
    //   5984: aload 53
    //   5986: astore 28
    //   5988: aload 46
    //   5990: astore 27
    //   5992: aload 61
    //   5994: astore 26
    //   5996: aload 58
    //   5998: astore 25
    //   6000: aload 51
    //   6002: astore 24
    //   6004: iload_1
    //   6005: istore 5
    //   6007: iload_1
    //   6008: istore_3
    //   6009: aload 52
    //   6011: astore 36
    //   6013: aload 47
    //   6015: astore 34
    //   6017: aload 63
    //   6019: astore 32
    //   6021: aload 56
    //   6023: astore 31
    //   6025: aload 60
    //   6027: astore 30
    //   6029: aload 65
    //   6031: invokeinterface 466 1 0
    //   6036: astore 65
    //   6038: iload_1
    //   6039: istore 4
    //   6041: aload 59
    //   6043: astore 33
    //   6045: aload 48
    //   6047: astore 35
    //   6049: aload 62
    //   6051: astore 37
    //   6053: aload 57
    //   6055: astore 38
    //   6057: aload 54
    //   6059: astore 39
    //   6061: iload_1
    //   6062: istore_2
    //   6063: aload 16
    //   6065: astore 29
    //   6067: aload 53
    //   6069: astore 28
    //   6071: aload 46
    //   6073: astore 27
    //   6075: aload 61
    //   6077: astore 26
    //   6079: aload 58
    //   6081: astore 25
    //   6083: aload 51
    //   6085: astore 24
    //   6087: iload_1
    //   6088: istore 5
    //   6090: iload_1
    //   6091: istore_3
    //   6092: aload 52
    //   6094: astore 36
    //   6096: aload 47
    //   6098: astore 34
    //   6100: aload 63
    //   6102: astore 32
    //   6104: aload 56
    //   6106: astore 31
    //   6108: aload 60
    //   6110: astore 30
    //   6112: ldc 22
    //   6114: aload 17
    //   6116: invokevirtual 504	java/lang/String:equalsIgnoreCase	(Ljava/lang/String;)Z
    //   6119: ifeq +5674 -> 11793
    //   6122: aload 65
    //   6124: ifnull +5669 -> 11793
    //   6127: iload_1
    //   6128: istore 4
    //   6130: aload 59
    //   6132: astore 33
    //   6134: aload 48
    //   6136: astore 35
    //   6138: aload 62
    //   6140: astore 37
    //   6142: aload 57
    //   6144: astore 38
    //   6146: aload 54
    //   6148: astore 39
    //   6150: iload_1
    //   6151: istore_2
    //   6152: aload 16
    //   6154: astore 29
    //   6156: aload 53
    //   6158: astore 28
    //   6160: aload 46
    //   6162: astore 27
    //   6164: aload 61
    //   6166: astore 26
    //   6168: aload 58
    //   6170: astore 25
    //   6172: aload 51
    //   6174: astore 24
    //   6176: iload_1
    //   6177: istore 5
    //   6179: iload_1
    //   6180: istore_3
    //   6181: aload 52
    //   6183: astore 36
    //   6185: aload 47
    //   6187: astore 34
    //   6189: aload 63
    //   6191: astore 32
    //   6193: aload 56
    //   6195: astore 31
    //   6197: aload 60
    //   6199: astore 30
    //   6201: aload_0
    //   6202: getfield 87	com/taobao/munion/net/b:p	Lcom/taobao/munion/net/e;
    //   6205: getfield 356	com/taobao/munion/net/e:k	Ljava/util/Map;
    //   6208: aload 17
    //   6210: invokevirtual 471	java/lang/String:toLowerCase	()Ljava/lang/String;
    //   6213: aload 65
    //   6215: invokeinterface 494 3 0
    //   6220: pop
    //   6221: goto +5572 -> 11793
    //   6224: iload_1
    //   6225: istore 4
    //   6227: aload 59
    //   6229: astore 33
    //   6231: aload 48
    //   6233: astore 35
    //   6235: aload 62
    //   6237: astore 37
    //   6239: aload 57
    //   6241: astore 38
    //   6243: aload 54
    //   6245: astore 39
    //   6247: iload_1
    //   6248: istore_2
    //   6249: aload 16
    //   6251: astore 29
    //   6253: aload 53
    //   6255: astore 28
    //   6257: aload 46
    //   6259: astore 27
    //   6261: aload 61
    //   6263: astore 26
    //   6265: aload 58
    //   6267: astore 25
    //   6269: aload 51
    //   6271: astore 24
    //   6273: iload_1
    //   6274: istore 5
    //   6276: iload_1
    //   6277: istore_3
    //   6278: aload 52
    //   6280: astore 36
    //   6282: aload 47
    //   6284: astore 34
    //   6286: aload 63
    //   6288: astore 32
    //   6290: aload 56
    //   6292: astore 31
    //   6294: aload 60
    //   6296: astore 30
    //   6298: invokestatic 409	java/lang/System:nanoTime	()J
    //   6301: lstore 12
    //   6303: iload_1
    //   6304: istore 4
    //   6306: aload 59
    //   6308: astore 33
    //   6310: aload 48
    //   6312: astore 35
    //   6314: aload 62
    //   6316: astore 37
    //   6318: aload 57
    //   6320: astore 38
    //   6322: aload 54
    //   6324: astore 39
    //   6326: iload_1
    //   6327: istore_2
    //   6328: aload 16
    //   6330: astore 29
    //   6332: aload 53
    //   6334: astore 28
    //   6336: aload 46
    //   6338: astore 27
    //   6340: aload 61
    //   6342: astore 26
    //   6344: aload 58
    //   6346: astore 25
    //   6348: aload 51
    //   6350: astore 24
    //   6352: iload_1
    //   6353: istore 5
    //   6355: iload_1
    //   6356: istore_3
    //   6357: aload 52
    //   6359: astore 36
    //   6361: aload 47
    //   6363: astore 34
    //   6365: aload 63
    //   6367: astore 32
    //   6369: aload 56
    //   6371: astore 31
    //   6373: aload 60
    //   6375: astore 30
    //   6377: aload 64
    //   6379: ldc_w 506
    //   6382: invokeinterface 462 2 0
    //   6387: astore 20
    //   6389: iload_1
    //   6390: istore 4
    //   6392: aload 59
    //   6394: astore 33
    //   6396: aload 48
    //   6398: astore 35
    //   6400: aload 62
    //   6402: astore 37
    //   6404: aload 57
    //   6406: astore 38
    //   6408: aload 54
    //   6410: astore 39
    //   6412: iload_1
    //   6413: istore_2
    //   6414: aload 16
    //   6416: astore 29
    //   6418: aload 53
    //   6420: astore 28
    //   6422: aload 46
    //   6424: astore 27
    //   6426: aload 61
    //   6428: astore 26
    //   6430: aload 58
    //   6432: astore 25
    //   6434: aload 51
    //   6436: astore 24
    //   6438: iload_1
    //   6439: istore 5
    //   6441: iload_1
    //   6442: istore_3
    //   6443: aload 52
    //   6445: astore 36
    //   6447: aload 47
    //   6449: astore 34
    //   6451: aload 63
    //   6453: astore 32
    //   6455: aload 56
    //   6457: astore 31
    //   6459: aload 60
    //   6461: astore 30
    //   6463: aload 64
    //   6465: invokeinterface 510 1 0
    //   6470: invokeinterface 516 1 0
    //   6475: astore 17
    //   6477: aload 20
    //   6479: ifnull +2178 -> 8657
    //   6482: iload_1
    //   6483: istore 4
    //   6485: aload 59
    //   6487: astore 33
    //   6489: aload 48
    //   6491: astore 35
    //   6493: aload 17
    //   6495: astore 37
    //   6497: aload 57
    //   6499: astore 38
    //   6501: aload 54
    //   6503: astore 39
    //   6505: iload_1
    //   6506: istore_2
    //   6507: aload 16
    //   6509: astore 29
    //   6511: aload 53
    //   6513: astore 28
    //   6515: aload 46
    //   6517: astore 27
    //   6519: aload 17
    //   6521: astore 26
    //   6523: aload 58
    //   6525: astore 25
    //   6527: aload 51
    //   6529: astore 24
    //   6531: iload_1
    //   6532: istore_3
    //   6533: aload 52
    //   6535: astore 36
    //   6537: aload 47
    //   6539: astore 34
    //   6541: aload 17
    //   6543: astore 32
    //   6545: aload 56
    //   6547: astore 31
    //   6549: aload 60
    //   6551: astore 30
    //   6553: ldc_w 518
    //   6556: aload 20
    //   6558: invokeinterface 466 1 0
    //   6563: invokevirtual 504	java/lang/String:equalsIgnoreCase	(Ljava/lang/String;)Z
    //   6566: ifeq +2091 -> 8657
    //   6569: iload_1
    //   6570: istore 4
    //   6572: aload 59
    //   6574: astore 33
    //   6576: aload 48
    //   6578: astore 35
    //   6580: aload 17
    //   6582: astore 37
    //   6584: aload 57
    //   6586: astore 38
    //   6588: aload 54
    //   6590: astore 39
    //   6592: iload_1
    //   6593: istore_2
    //   6594: aload 16
    //   6596: astore 29
    //   6598: aload 53
    //   6600: astore 28
    //   6602: aload 46
    //   6604: astore 27
    //   6606: aload 17
    //   6608: astore 26
    //   6610: aload 58
    //   6612: astore 25
    //   6614: aload 51
    //   6616: astore 24
    //   6618: iload_1
    //   6619: istore_3
    //   6620: aload 52
    //   6622: astore 36
    //   6624: aload 47
    //   6626: astore 34
    //   6628: aload 17
    //   6630: astore 32
    //   6632: aload 56
    //   6634: astore 31
    //   6636: aload 60
    //   6638: astore 30
    //   6640: new 304	com/taobao/munion/net/n
    //   6643: dup
    //   6644: aload 17
    //   6646: invokespecial 521	com/taobao/munion/net/n:<init>	(Ljava/io/InputStream;)V
    //   6649: astore 20
    //   6651: new 317	java/util/zip/GZIPInputStream
    //   6654: dup
    //   6655: aload 20
    //   6657: invokespecial 522	java/util/zip/GZIPInputStream:<init>	(Ljava/io/InputStream;)V
    //   6660: astore 21
    //   6662: new 308	java/io/DataInputStream
    //   6665: dup
    //   6666: aload 21
    //   6668: invokespecial 523	java/io/DataInputStream:<init>	(Ljava/io/InputStream;)V
    //   6671: astore 22
    //   6673: iload_1
    //   6674: istore 4
    //   6676: aload 22
    //   6678: astore 33
    //   6680: aload 48
    //   6682: astore 35
    //   6684: aload 17
    //   6686: astore 37
    //   6688: aload 20
    //   6690: astore 38
    //   6692: aload 21
    //   6694: astore 39
    //   6696: iload_1
    //   6697: istore_2
    //   6698: aload 16
    //   6700: astore 29
    //   6702: aload 22
    //   6704: astore 28
    //   6706: aload 46
    //   6708: astore 27
    //   6710: aload 17
    //   6712: astore 26
    //   6714: aload 20
    //   6716: astore 25
    //   6718: aload 21
    //   6720: astore 24
    //   6722: iload_1
    //   6723: istore_3
    //   6724: aload 22
    //   6726: astore 36
    //   6728: aload 47
    //   6730: astore 34
    //   6732: aload 17
    //   6734: astore 32
    //   6736: aload 20
    //   6738: astore 31
    //   6740: aload 21
    //   6742: astore 30
    //   6744: sipush 2048
    //   6747: newarray <illegal type>
    //   6749: astore 41
    //   6751: iload_1
    //   6752: istore 4
    //   6754: aload 22
    //   6756: astore 33
    //   6758: aload 48
    //   6760: astore 35
    //   6762: aload 17
    //   6764: astore 37
    //   6766: aload 20
    //   6768: astore 38
    //   6770: aload 21
    //   6772: astore 39
    //   6774: iload_1
    //   6775: istore_2
    //   6776: aload 16
    //   6778: astore 29
    //   6780: aload 22
    //   6782: astore 28
    //   6784: aload 46
    //   6786: astore 27
    //   6788: aload 17
    //   6790: astore 26
    //   6792: aload 20
    //   6794: astore 25
    //   6796: aload 21
    //   6798: astore 24
    //   6800: iload_1
    //   6801: istore_3
    //   6802: aload 22
    //   6804: astore 36
    //   6806: aload 47
    //   6808: astore 34
    //   6810: aload 17
    //   6812: astore 32
    //   6814: aload 20
    //   6816: astore 31
    //   6818: aload 21
    //   6820: astore 30
    //   6822: aload_0
    //   6823: getfield 87	com/taobao/munion/net/b:p	Lcom/taobao/munion/net/e;
    //   6826: getfield 526	com/taobao/munion/net/e:q	Ljava/io/OutputStream;
    //   6829: ifnull +1917 -> 8746
    //   6832: iload_1
    //   6833: istore 4
    //   6835: aload 22
    //   6837: astore 33
    //   6839: aload 48
    //   6841: astore 35
    //   6843: aload 17
    //   6845: astore 37
    //   6847: aload 20
    //   6849: astore 38
    //   6851: aload 21
    //   6853: astore 39
    //   6855: iload_1
    //   6856: istore_2
    //   6857: aload 16
    //   6859: astore 29
    //   6861: aload 22
    //   6863: astore 28
    //   6865: aload 46
    //   6867: astore 27
    //   6869: aload 17
    //   6871: astore 26
    //   6873: aload 20
    //   6875: astore 25
    //   6877: aload 21
    //   6879: astore 24
    //   6881: iload_1
    //   6882: istore_3
    //   6883: aload 22
    //   6885: astore 36
    //   6887: aload 47
    //   6889: astore 34
    //   6891: aload 17
    //   6893: astore 32
    //   6895: aload 20
    //   6897: astore 31
    //   6899: aload 21
    //   6901: astore 30
    //   6903: aload_0
    //   6904: getfield 87	com/taobao/munion/net/b:p	Lcom/taobao/munion/net/e;
    //   6907: getfield 526	com/taobao/munion/net/e:q	Ljava/io/OutputStream;
    //   6910: astore 40
    //   6912: aload 49
    //   6914: astore 23
    //   6916: iload_1
    //   6917: istore 4
    //   6919: aload 22
    //   6921: astore 33
    //   6923: aload 23
    //   6925: astore 35
    //   6927: aload 17
    //   6929: astore 37
    //   6931: aload 20
    //   6933: astore 38
    //   6935: aload 21
    //   6937: astore 39
    //   6939: iload_1
    //   6940: istore_2
    //   6941: aload 16
    //   6943: astore 29
    //   6945: aload 22
    //   6947: astore 28
    //   6949: aload 23
    //   6951: astore 27
    //   6953: aload 17
    //   6955: astore 26
    //   6957: aload 20
    //   6959: astore 25
    //   6961: aload 21
    //   6963: astore 24
    //   6965: iload_1
    //   6966: istore_3
    //   6967: aload 22
    //   6969: astore 36
    //   6971: aload 23
    //   6973: astore 34
    //   6975: aload 17
    //   6977: astore 32
    //   6979: aload 20
    //   6981: astore 31
    //   6983: aload 21
    //   6985: astore 30
    //   6987: iconst_0
    //   6988: aload_0
    //   6989: getfield 87	com/taobao/munion/net/b:p	Lcom/taobao/munion/net/e;
    //   6992: getfield 527	com/taobao/munion/net/e:s	I
    //   6995: idiv
    //   6996: istore 9
    //   6998: iload_1
    //   6999: istore 4
    //   7001: aload 22
    //   7003: astore 33
    //   7005: aload 23
    //   7007: astore 35
    //   7009: aload 17
    //   7011: astore 37
    //   7013: aload 20
    //   7015: astore 38
    //   7017: aload 21
    //   7019: astore 39
    //   7021: iload_1
    //   7022: istore_2
    //   7023: aload 16
    //   7025: astore 29
    //   7027: aload 22
    //   7029: astore 28
    //   7031: aload 23
    //   7033: astore 27
    //   7035: aload 17
    //   7037: astore 26
    //   7039: aload 20
    //   7041: astore 25
    //   7043: aload 21
    //   7045: astore 24
    //   7047: iload_1
    //   7048: istore_3
    //   7049: aload 22
    //   7051: astore 36
    //   7053: aload 23
    //   7055: astore 34
    //   7057: aload 17
    //   7059: astore 32
    //   7061: aload 20
    //   7063: astore 31
    //   7065: aload 21
    //   7067: astore 30
    //   7069: aload_0
    //   7070: getfield 87	com/taobao/munion/net/b:p	Lcom/taobao/munion/net/e;
    //   7073: getfield 529	com/taobao/munion/net/e:p	J
    //   7076: l2i
    //   7077: istore 11
    //   7079: iload_1
    //   7080: istore 4
    //   7082: aload 22
    //   7084: astore 33
    //   7086: aload 23
    //   7088: astore 35
    //   7090: aload 17
    //   7092: astore 37
    //   7094: aload 20
    //   7096: astore 38
    //   7098: aload 21
    //   7100: astore 39
    //   7102: iload_1
    //   7103: istore_2
    //   7104: aload 16
    //   7106: astore 29
    //   7108: aload 22
    //   7110: astore 28
    //   7112: aload 23
    //   7114: astore 27
    //   7116: aload 17
    //   7118: astore 26
    //   7120: aload 20
    //   7122: astore 25
    //   7124: aload 21
    //   7126: astore 24
    //   7128: iload_1
    //   7129: istore_3
    //   7130: aload 22
    //   7132: astore 36
    //   7134: aload 23
    //   7136: astore 34
    //   7138: aload 17
    //   7140: astore 32
    //   7142: aload 20
    //   7144: astore 31
    //   7146: aload 21
    //   7148: astore 30
    //   7150: aload_0
    //   7151: getfield 69	com/taobao/munion/net/b:v	Lcom/taobao/munion/net/i;
    //   7154: ifnull +4648 -> 11802
    //   7157: iload_1
    //   7158: istore 4
    //   7160: aload 22
    //   7162: astore 33
    //   7164: aload 23
    //   7166: astore 35
    //   7168: aload 17
    //   7170: astore 37
    //   7172: aload 20
    //   7174: astore 38
    //   7176: aload 21
    //   7178: astore 39
    //   7180: iload_1
    //   7181: istore_2
    //   7182: aload 16
    //   7184: astore 29
    //   7186: aload 22
    //   7188: astore 28
    //   7190: aload 23
    //   7192: astore 27
    //   7194: aload 17
    //   7196: astore 26
    //   7198: aload 20
    //   7200: astore 25
    //   7202: aload 21
    //   7204: astore 24
    //   7206: iload_1
    //   7207: istore_3
    //   7208: aload 22
    //   7210: astore 36
    //   7212: aload 23
    //   7214: astore 34
    //   7216: aload 17
    //   7218: astore 32
    //   7220: aload 20
    //   7222: astore 31
    //   7224: aload 21
    //   7226: astore 30
    //   7228: aload_0
    //   7229: getfield 69	com/taobao/munion/net/b:v	Lcom/taobao/munion/net/i;
    //   7232: ldc_w 531
    //   7235: aload_0
    //   7236: getfield 87	com/taobao/munion/net/b:p	Lcom/taobao/munion/net/e;
    //   7239: getfield 529	com/taobao/munion/net/e:p	J
    //   7242: l2i
    //   7243: iload 11
    //   7245: iconst_0
    //   7246: iadd
    //   7247: invokeinterface 536 4 0
    //   7252: goto +4550 -> 11802
    //   7255: iload_1
    //   7256: istore 4
    //   7258: aload 22
    //   7260: astore 33
    //   7262: aload 23
    //   7264: astore 35
    //   7266: aload 17
    //   7268: astore 37
    //   7270: aload 20
    //   7272: astore 38
    //   7274: aload 21
    //   7276: astore 39
    //   7278: iload_1
    //   7279: istore_2
    //   7280: aload 16
    //   7282: astore 29
    //   7284: aload 22
    //   7286: astore 28
    //   7288: aload 23
    //   7290: astore 27
    //   7292: aload 17
    //   7294: astore 26
    //   7296: aload 20
    //   7298: astore 25
    //   7300: aload 21
    //   7302: astore 24
    //   7304: iload_1
    //   7305: istore_3
    //   7306: aload 22
    //   7308: astore 36
    //   7310: aload 23
    //   7312: astore 34
    //   7314: aload 17
    //   7316: astore 32
    //   7318: aload 20
    //   7320: astore 31
    //   7322: aload 21
    //   7324: astore 30
    //   7326: aload 22
    //   7328: aload 41
    //   7330: iconst_0
    //   7331: sipush 2048
    //   7334: invokevirtual 540	java/io/DataInputStream:read	([BII)I
    //   7337: istore 8
    //   7339: iload 8
    //   7341: iconst_m1
    //   7342: if_icmpeq +2456 -> 9798
    //   7345: iload_1
    //   7346: istore 4
    //   7348: aload 22
    //   7350: astore 33
    //   7352: aload 23
    //   7354: astore 35
    //   7356: aload 17
    //   7358: astore 37
    //   7360: aload 20
    //   7362: astore 38
    //   7364: aload 21
    //   7366: astore 39
    //   7368: iload_1
    //   7369: istore_2
    //   7370: aload 16
    //   7372: astore 29
    //   7374: aload 22
    //   7376: astore 28
    //   7378: aload 23
    //   7380: astore 27
    //   7382: aload 17
    //   7384: astore 26
    //   7386: aload 20
    //   7388: astore 25
    //   7390: aload 21
    //   7392: astore 24
    //   7394: iload_1
    //   7395: istore_3
    //   7396: aload 22
    //   7398: astore 36
    //   7400: aload 23
    //   7402: astore 34
    //   7404: aload 17
    //   7406: astore 32
    //   7408: aload 20
    //   7410: astore 31
    //   7412: aload 21
    //   7414: astore 30
    //   7416: aload 18
    //   7418: monitorenter
    //   7419: aload 18
    //   7421: aload 18
    //   7423: getfield 542	com/taobao/munion/net/b$f:e	J
    //   7426: iload 8
    //   7428: i2l
    //   7429: ladd
    //   7430: putfield 542	com/taobao/munion/net/b$f:e	J
    //   7433: aload 18
    //   7435: monitorexit
    //   7436: iload 7
    //   7438: istore 6
    //   7440: iload 7
    //   7442: ifeq +104 -> 7546
    //   7445: iload_1
    //   7446: istore 4
    //   7448: aload 22
    //   7450: astore 33
    //   7452: aload 23
    //   7454: astore 35
    //   7456: aload 17
    //   7458: astore 37
    //   7460: aload 20
    //   7462: astore 38
    //   7464: aload 21
    //   7466: astore 39
    //   7468: iload_1
    //   7469: istore_2
    //   7470: aload 16
    //   7472: astore 29
    //   7474: aload 22
    //   7476: astore 28
    //   7478: aload 23
    //   7480: astore 27
    //   7482: aload 17
    //   7484: astore 26
    //   7486: aload 20
    //   7488: astore 25
    //   7490: aload 21
    //   7492: astore 24
    //   7494: iload_1
    //   7495: istore_3
    //   7496: aload 22
    //   7498: astore 36
    //   7500: aload 23
    //   7502: astore 34
    //   7504: aload 17
    //   7506: astore 32
    //   7508: aload 20
    //   7510: astore 31
    //   7512: aload 21
    //   7514: astore 30
    //   7516: aload 18
    //   7518: monitorenter
    //   7519: aload 18
    //   7521: aload 18
    //   7523: getfield 544	com/taobao/munion/net/b$f:d	J
    //   7526: invokestatic 409	java/lang/System:nanoTime	()J
    //   7529: lload 12
    //   7531: lsub
    //   7532: ldc2_w 410
    //   7535: ldiv
    //   7536: ladd
    //   7537: putfield 544	com/taobao/munion/net/b$f:d	J
    //   7540: aload 18
    //   7542: monitorexit
    //   7543: iconst_0
    //   7544: istore 6
    //   7546: iload_1
    //   7547: istore 4
    //   7549: aload 22
    //   7551: astore 33
    //   7553: aload 23
    //   7555: astore 35
    //   7557: aload 17
    //   7559: astore 37
    //   7561: aload 20
    //   7563: astore 38
    //   7565: aload 21
    //   7567: astore 39
    //   7569: iload_1
    //   7570: istore_2
    //   7571: aload 16
    //   7573: astore 29
    //   7575: aload 22
    //   7577: astore 28
    //   7579: aload 23
    //   7581: astore 27
    //   7583: aload 17
    //   7585: astore 26
    //   7587: aload 20
    //   7589: astore 25
    //   7591: aload 21
    //   7593: astore 24
    //   7595: iload_1
    //   7596: istore_3
    //   7597: aload 22
    //   7599: astore 36
    //   7601: aload 23
    //   7603: astore 34
    //   7605: aload 17
    //   7607: astore 32
    //   7609: aload 20
    //   7611: astore 31
    //   7613: aload 21
    //   7615: astore 30
    //   7617: aload 40
    //   7619: aload 41
    //   7621: iconst_0
    //   7622: iload 8
    //   7624: invokevirtual 550	java/io/OutputStream:write	([BII)V
    //   7627: iload_1
    //   7628: istore 4
    //   7630: aload 22
    //   7632: astore 33
    //   7634: aload 23
    //   7636: astore 35
    //   7638: aload 17
    //   7640: astore 37
    //   7642: aload 20
    //   7644: astore 38
    //   7646: aload 21
    //   7648: astore 39
    //   7650: iload_1
    //   7651: istore_2
    //   7652: aload 16
    //   7654: astore 29
    //   7656: aload 22
    //   7658: astore 28
    //   7660: aload 23
    //   7662: astore 27
    //   7664: aload 17
    //   7666: astore 26
    //   7668: aload 20
    //   7670: astore 25
    //   7672: aload 21
    //   7674: astore 24
    //   7676: iload_1
    //   7677: istore_3
    //   7678: aload 22
    //   7680: astore 36
    //   7682: aload 23
    //   7684: astore 34
    //   7686: aload 17
    //   7688: astore 32
    //   7690: aload 20
    //   7692: astore 31
    //   7694: aload 21
    //   7696: astore 30
    //   7698: aload_0
    //   7699: getfield 87	com/taobao/munion/net/b:p	Lcom/taobao/munion/net/e;
    //   7702: getfield 526	com/taobao/munion/net/e:q	Ljava/io/OutputStream;
    //   7705: astore 42
    //   7707: aload 42
    //   7709: ifnull +57 -> 7766
    //   7712: iload_1
    //   7713: istore_2
    //   7714: aload 16
    //   7716: astore 29
    //   7718: aload 22
    //   7720: astore 28
    //   7722: aload 23
    //   7724: astore 27
    //   7726: aload 17
    //   7728: astore 26
    //   7730: aload 20
    //   7732: astore 25
    //   7734: aload 21
    //   7736: astore 24
    //   7738: iload_1
    //   7739: istore_3
    //   7740: aload 22
    //   7742: astore 36
    //   7744: aload 23
    //   7746: astore 34
    //   7748: aload 17
    //   7750: astore 32
    //   7752: aload 20
    //   7754: astore 31
    //   7756: aload 21
    //   7758: astore 30
    //   7760: ldc2_w 551
    //   7763: invokestatic 557	java/lang/Thread:sleep	(J)V
    //   7766: iload_1
    //   7767: istore 4
    //   7769: aload 22
    //   7771: astore 33
    //   7773: aload 23
    //   7775: astore 35
    //   7777: aload 17
    //   7779: astore 37
    //   7781: aload 20
    //   7783: astore 38
    //   7785: aload 21
    //   7787: astore 39
    //   7789: iload_1
    //   7790: istore_2
    //   7791: aload 16
    //   7793: astore 29
    //   7795: aload 22
    //   7797: astore 28
    //   7799: aload 23
    //   7801: astore 27
    //   7803: aload 17
    //   7805: astore 26
    //   7807: aload 20
    //   7809: astore 25
    //   7811: aload 21
    //   7813: astore 24
    //   7815: iload_1
    //   7816: istore_3
    //   7817: aload 22
    //   7819: astore 36
    //   7821: aload 23
    //   7823: astore 34
    //   7825: aload 17
    //   7827: astore 32
    //   7829: aload 20
    //   7831: astore 31
    //   7833: aload 21
    //   7835: astore 30
    //   7837: aload_0
    //   7838: getfield 87	com/taobao/munion/net/b:p	Lcom/taobao/munion/net/e;
    //   7841: astore 42
    //   7843: iload_1
    //   7844: istore 4
    //   7846: aload 22
    //   7848: astore 33
    //   7850: aload 23
    //   7852: astore 35
    //   7854: aload 17
    //   7856: astore 37
    //   7858: aload 20
    //   7860: astore 38
    //   7862: aload 21
    //   7864: astore 39
    //   7866: iload_1
    //   7867: istore_2
    //   7868: aload 16
    //   7870: astore 29
    //   7872: aload 22
    //   7874: astore 28
    //   7876: aload 23
    //   7878: astore 27
    //   7880: aload 17
    //   7882: astore 26
    //   7884: aload 20
    //   7886: astore 25
    //   7888: aload 21
    //   7890: astore 24
    //   7892: iload_1
    //   7893: istore_3
    //   7894: aload 22
    //   7896: astore 36
    //   7898: aload 23
    //   7900: astore 34
    //   7902: aload 17
    //   7904: astore 32
    //   7906: aload 20
    //   7908: astore 31
    //   7910: aload 21
    //   7912: astore 30
    //   7914: aload 42
    //   7916: aload 42
    //   7918: getfield 529	com/taobao/munion/net/e:p	J
    //   7921: iload 8
    //   7923: i2l
    //   7924: ladd
    //   7925: putfield 529	com/taobao/munion/net/e:p	J
    //   7928: iload_1
    //   7929: istore 4
    //   7931: aload 22
    //   7933: astore 33
    //   7935: aload 23
    //   7937: astore 35
    //   7939: aload 17
    //   7941: astore 37
    //   7943: aload 20
    //   7945: astore 38
    //   7947: aload 21
    //   7949: astore 39
    //   7951: iload_1
    //   7952: istore_2
    //   7953: aload 16
    //   7955: astore 29
    //   7957: aload 22
    //   7959: astore 28
    //   7961: aload 23
    //   7963: astore 27
    //   7965: aload 17
    //   7967: astore 26
    //   7969: aload 20
    //   7971: astore 25
    //   7973: aload 21
    //   7975: astore 24
    //   7977: iload 5
    //   7979: istore 8
    //   7981: iload_1
    //   7982: istore_3
    //   7983: aload 22
    //   7985: astore 36
    //   7987: aload 23
    //   7989: astore 34
    //   7991: aload 17
    //   7993: astore 32
    //   7995: aload 20
    //   7997: astore 31
    //   7999: aload 21
    //   8001: astore 30
    //   8003: aload_0
    //   8004: getfield 69	com/taobao/munion/net/b:v	Lcom/taobao/munion/net/i;
    //   8007: ifnull +194 -> 8201
    //   8010: iload_1
    //   8011: istore 4
    //   8013: aload 22
    //   8015: astore 33
    //   8017: aload 23
    //   8019: astore 35
    //   8021: aload 17
    //   8023: astore 37
    //   8025: aload 20
    //   8027: astore 38
    //   8029: aload 21
    //   8031: astore 39
    //   8033: iload_1
    //   8034: istore_2
    //   8035: aload 16
    //   8037: astore 29
    //   8039: aload 22
    //   8041: astore 28
    //   8043: aload 23
    //   8045: astore 27
    //   8047: aload 17
    //   8049: astore 26
    //   8051: aload 20
    //   8053: astore 25
    //   8055: aload 21
    //   8057: astore 24
    //   8059: iload 5
    //   8061: istore 8
    //   8063: iload_1
    //   8064: istore_3
    //   8065: aload 22
    //   8067: astore 36
    //   8069: aload 23
    //   8071: astore 34
    //   8073: aload 17
    //   8075: astore 32
    //   8077: aload 20
    //   8079: astore 31
    //   8081: aload 21
    //   8083: astore 30
    //   8085: aload_0
    //   8086: getfield 87	com/taobao/munion/net/b:p	Lcom/taobao/munion/net/e;
    //   8089: getfield 529	com/taobao/munion/net/e:p	J
    //   8092: iload 5
    //   8094: i2l
    //   8095: lcmp
    //   8096: ifle +105 -> 8201
    //   8099: iload_1
    //   8100: istore 4
    //   8102: aload 22
    //   8104: astore 33
    //   8106: aload 23
    //   8108: astore 35
    //   8110: aload 17
    //   8112: astore 37
    //   8114: aload 20
    //   8116: astore 38
    //   8118: aload 21
    //   8120: astore 39
    //   8122: iload_1
    //   8123: istore_2
    //   8124: aload 16
    //   8126: astore 29
    //   8128: aload 22
    //   8130: astore 28
    //   8132: aload 23
    //   8134: astore 27
    //   8136: aload 17
    //   8138: astore 26
    //   8140: aload 20
    //   8142: astore 25
    //   8144: aload 21
    //   8146: astore 24
    //   8148: iload_1
    //   8149: istore_3
    //   8150: aload 22
    //   8152: astore 36
    //   8154: aload 23
    //   8156: astore 34
    //   8158: aload 17
    //   8160: astore 32
    //   8162: aload 20
    //   8164: astore 31
    //   8166: aload 21
    //   8168: astore 30
    //   8170: aload_0
    //   8171: getfield 69	com/taobao/munion/net/b:v	Lcom/taobao/munion/net/i;
    //   8174: ldc_w 531
    //   8177: aload_0
    //   8178: getfield 87	com/taobao/munion/net/b:p	Lcom/taobao/munion/net/e;
    //   8181: getfield 529	com/taobao/munion/net/e:p	J
    //   8184: l2i
    //   8185: iload 11
    //   8187: iconst_0
    //   8188: iadd
    //   8189: invokeinterface 536 4 0
    //   8194: iload 5
    //   8196: iload 9
    //   8198: iadd
    //   8199: istore 8
    //   8201: iload_1
    //   8202: istore 4
    //   8204: aload 22
    //   8206: astore 33
    //   8208: aload 23
    //   8210: astore 35
    //   8212: aload 17
    //   8214: astore 37
    //   8216: aload 20
    //   8218: astore 38
    //   8220: aload 21
    //   8222: astore 39
    //   8224: iload_1
    //   8225: istore_2
    //   8226: aload 16
    //   8228: astore 29
    //   8230: aload 22
    //   8232: astore 28
    //   8234: aload 23
    //   8236: astore 27
    //   8238: aload 17
    //   8240: astore 26
    //   8242: aload 20
    //   8244: astore 25
    //   8246: aload 21
    //   8248: astore 24
    //   8250: iload 8
    //   8252: istore 5
    //   8254: iload 6
    //   8256: istore 7
    //   8258: iload_1
    //   8259: istore_3
    //   8260: aload 22
    //   8262: astore 36
    //   8264: aload 23
    //   8266: astore 34
    //   8268: aload 17
    //   8270: astore 32
    //   8272: aload 20
    //   8274: astore 31
    //   8276: aload 21
    //   8278: astore 30
    //   8280: aload_0
    //   8281: getfield 225	com/taobao/munion/net/b:r	Z
    //   8284: ifeq -1029 -> 7255
    //   8287: iload_1
    //   8288: istore 4
    //   8290: aload 22
    //   8292: astore 33
    //   8294: aload 23
    //   8296: astore 35
    //   8298: aload 17
    //   8300: astore 37
    //   8302: aload 20
    //   8304: astore 38
    //   8306: aload 21
    //   8308: astore 39
    //   8310: iload_1
    //   8311: istore_2
    //   8312: aload 16
    //   8314: astore 29
    //   8316: aload 22
    //   8318: astore 28
    //   8320: aload 23
    //   8322: astore 27
    //   8324: aload 17
    //   8326: astore 26
    //   8328: aload 20
    //   8330: astore 25
    //   8332: aload 21
    //   8334: astore 24
    //   8336: iload 8
    //   8338: istore 5
    //   8340: iload 6
    //   8342: istore 7
    //   8344: iload_1
    //   8345: istore_3
    //   8346: aload 22
    //   8348: astore 36
    //   8350: aload 23
    //   8352: astore 34
    //   8354: aload 17
    //   8356: astore 32
    //   8358: aload 20
    //   8360: astore 31
    //   8362: aload 21
    //   8364: astore 30
    //   8366: aload_0
    //   8367: getfield 87	com/taobao/munion/net/b:p	Lcom/taobao/munion/net/e;
    //   8370: getfield 526	com/taobao/munion/net/e:q	Ljava/io/OutputStream;
    //   8373: ifnull -1118 -> 7255
    //   8376: iload_1
    //   8377: istore 4
    //   8379: aload 22
    //   8381: astore 33
    //   8383: aload 23
    //   8385: astore 35
    //   8387: aload 17
    //   8389: astore 37
    //   8391: aload 20
    //   8393: astore 38
    //   8395: aload 21
    //   8397: astore 39
    //   8399: iload_1
    //   8400: istore_2
    //   8401: aload 16
    //   8403: astore 29
    //   8405: aload 22
    //   8407: astore 28
    //   8409: aload 23
    //   8411: astore 27
    //   8413: aload 17
    //   8415: astore 26
    //   8417: aload 20
    //   8419: astore 25
    //   8421: aload 21
    //   8423: astore 24
    //   8425: iload_1
    //   8426: istore_3
    //   8427: aload 22
    //   8429: astore 36
    //   8431: aload 23
    //   8433: astore 34
    //   8435: aload 17
    //   8437: astore 32
    //   8439: aload 20
    //   8441: astore 31
    //   8443: aload 21
    //   8445: astore 30
    //   8447: aload 18
    //   8449: monitorenter
    //   8450: aload 18
    //   8452: getfield 559	com/taobao/munion/net/b$f:f	J
    //   8455: lstore 14
    //   8457: aload 18
    //   8459: invokestatic 409	java/lang/System:nanoTime	()J
    //   8462: lload 12
    //   8464: lsub
    //   8465: ldc2_w 410
    //   8468: ldiv
    //   8469: lload 14
    //   8471: ladd
    //   8472: putfield 559	com/taobao/munion/net/b$f:f	J
    //   8475: aload 18
    //   8477: monitorexit
    //   8478: iload_1
    //   8479: istore 4
    //   8481: aload 22
    //   8483: astore 33
    //   8485: aload 23
    //   8487: astore 35
    //   8489: aload 17
    //   8491: astore 37
    //   8493: aload 20
    //   8495: astore 38
    //   8497: aload 21
    //   8499: astore 39
    //   8501: iload_1
    //   8502: istore_2
    //   8503: aload 16
    //   8505: astore 29
    //   8507: aload 22
    //   8509: astore 28
    //   8511: aload 23
    //   8513: astore 27
    //   8515: aload 17
    //   8517: astore 26
    //   8519: aload 20
    //   8521: astore 25
    //   8523: aload 21
    //   8525: astore 24
    //   8527: iload_1
    //   8528: istore_3
    //   8529: aload 22
    //   8531: astore 36
    //   8533: aload 23
    //   8535: astore 34
    //   8537: aload 17
    //   8539: astore 32
    //   8541: aload 20
    //   8543: astore 31
    //   8545: aload 21
    //   8547: astore 30
    //   8549: getstatic 230	com/taobao/munion/net/h:h	Lcom/taobao/munion/net/h;
    //   8552: astore 40
    //   8554: getstatic 104	com/taobao/munion/net/b:u	Lcom/taobao/munion/net/c;
    //   8557: ifnull +47 -> 8604
    //   8560: iconst_0
    //   8561: istore_2
    //   8562: aload 23
    //   8564: ifnull +9 -> 8573
    //   8567: aload 23
    //   8569: invokevirtual 302	java/io/ByteArrayOutputStream:size	()I
    //   8572: istore_2
    //   8573: aload 20
    //   8575: ifnull +9 -> 8584
    //   8578: aload 20
    //   8580: getfield 306	com/taobao/munion/net/n:a	I
    //   8583: istore_2
    //   8584: getstatic 104	com/taobao/munion/net/b:u	Lcom/taobao/munion/net/c;
    //   8587: iload_1
    //   8588: iload_2
    //   8589: invokestatic 183	java/lang/System:currentTimeMillis	()J
    //   8592: aload_0
    //   8593: getfield 67	com/taobao/munion/net/b:t	J
    //   8596: lsub
    //   8597: aload 16
    //   8599: invokeinterface 238 6 0
    //   8604: aload 22
    //   8606: ifnull +8 -> 8614
    //   8609: aload 22
    //   8611: invokevirtual 311	java/io/DataInputStream:close	()V
    //   8614: aload 17
    //   8616: ifnull +8 -> 8624
    //   8619: aload 17
    //   8621: invokevirtual 314	java/io/InputStream:close	()V
    //   8624: aload 20
    //   8626: ifnull +8 -> 8634
    //   8629: aload 20
    //   8631: invokevirtual 315	com/taobao/munion/net/n:close	()V
    //   8634: aload 21
    //   8636: ifnull +8 -> 8644
    //   8639: aload 21
    //   8641: invokevirtual 318	java/util/zip/GZIPInputStream:close	()V
    //   8644: aload 23
    //   8646: ifnull +8 -> 8654
    //   8649: aload 23
    //   8651: invokevirtual 319	java/io/ByteArrayOutputStream:close	()V
    //   8654: aload 40
    //   8656: areturn
    //   8657: iload_1
    //   8658: istore 4
    //   8660: aload 59
    //   8662: astore 33
    //   8664: aload 48
    //   8666: astore 35
    //   8668: aload 17
    //   8670: astore 37
    //   8672: aload 57
    //   8674: astore 38
    //   8676: aload 54
    //   8678: astore 39
    //   8680: iload_1
    //   8681: istore_2
    //   8682: aload 16
    //   8684: astore 29
    //   8686: aload 53
    //   8688: astore 28
    //   8690: aload 46
    //   8692: astore 27
    //   8694: aload 17
    //   8696: astore 26
    //   8698: aload 58
    //   8700: astore 25
    //   8702: aload 51
    //   8704: astore 24
    //   8706: iload_1
    //   8707: istore_3
    //   8708: aload 52
    //   8710: astore 36
    //   8712: aload 47
    //   8714: astore 34
    //   8716: aload 17
    //   8718: astore 32
    //   8720: aload 56
    //   8722: astore 31
    //   8724: aload 60
    //   8726: astore 30
    //   8728: new 308	java/io/DataInputStream
    //   8731: dup
    //   8732: aload 17
    //   8734: invokespecial 523	java/io/DataInputStream:<init>	(Ljava/io/InputStream;)V
    //   8737: astore 22
    //   8739: aload 55
    //   8741: astore 20
    //   8743: goto -2070 -> 6673
    //   8746: iload_1
    //   8747: istore 4
    //   8749: aload 22
    //   8751: astore 33
    //   8753: aload 48
    //   8755: astore 35
    //   8757: aload 17
    //   8759: astore 37
    //   8761: aload 20
    //   8763: astore 38
    //   8765: aload 21
    //   8767: astore 39
    //   8769: iload_1
    //   8770: istore_2
    //   8771: aload 16
    //   8773: astore 29
    //   8775: aload 22
    //   8777: astore 28
    //   8779: aload 46
    //   8781: astore 27
    //   8783: aload 17
    //   8785: astore 26
    //   8787: aload 20
    //   8789: astore 25
    //   8791: aload 21
    //   8793: astore 24
    //   8795: iload_1
    //   8796: istore_3
    //   8797: aload 22
    //   8799: astore 36
    //   8801: aload 47
    //   8803: astore 34
    //   8805: aload 17
    //   8807: astore 32
    //   8809: aload 20
    //   8811: astore 31
    //   8813: aload 21
    //   8815: astore 30
    //   8817: new 299	java/io/ByteArrayOutputStream
    //   8820: dup
    //   8821: invokespecial 560	java/io/ByteArrayOutputStream:<init>	()V
    //   8824: astore 23
    //   8826: aload 23
    //   8828: astore 40
    //   8830: goto -1914 -> 6916
    //   8833: astore 40
    //   8835: iload_1
    //   8836: istore 4
    //   8838: aload 22
    //   8840: astore 33
    //   8842: aload 23
    //   8844: astore 35
    //   8846: aload 17
    //   8848: astore 37
    //   8850: aload 20
    //   8852: astore 38
    //   8854: aload 21
    //   8856: astore 39
    //   8858: iload_1
    //   8859: istore_2
    //   8860: aload 16
    //   8862: astore 29
    //   8864: aload 22
    //   8866: astore 28
    //   8868: aload 23
    //   8870: astore 27
    //   8872: aload 17
    //   8874: astore 26
    //   8876: aload 20
    //   8878: astore 25
    //   8880: aload 21
    //   8882: astore 24
    //   8884: iload_1
    //   8885: istore_3
    //   8886: aload 22
    //   8888: astore 36
    //   8890: aload 23
    //   8892: astore 34
    //   8894: aload 17
    //   8896: astore 32
    //   8898: aload 20
    //   8900: astore 31
    //   8902: aload 21
    //   8904: astore 30
    //   8906: aload 18
    //   8908: monitorexit
    //   8909: iload_1
    //   8910: istore 4
    //   8912: aload 22
    //   8914: astore 33
    //   8916: aload 23
    //   8918: astore 35
    //   8920: aload 17
    //   8922: astore 37
    //   8924: aload 20
    //   8926: astore 38
    //   8928: aload 21
    //   8930: astore 39
    //   8932: iload_1
    //   8933: istore_2
    //   8934: aload 16
    //   8936: astore 29
    //   8938: aload 22
    //   8940: astore 28
    //   8942: aload 23
    //   8944: astore 27
    //   8946: aload 17
    //   8948: astore 26
    //   8950: aload 20
    //   8952: astore 25
    //   8954: aload 21
    //   8956: astore 24
    //   8958: iload_1
    //   8959: istore_3
    //   8960: aload 22
    //   8962: astore 36
    //   8964: aload 23
    //   8966: astore 34
    //   8968: aload 17
    //   8970: astore 32
    //   8972: aload 20
    //   8974: astore 31
    //   8976: aload 21
    //   8978: astore 30
    //   8980: aload 40
    //   8982: athrow
    //   8983: astore 40
    //   8985: iload_1
    //   8986: istore 4
    //   8988: aload 22
    //   8990: astore 33
    //   8992: aload 23
    //   8994: astore 35
    //   8996: aload 17
    //   8998: astore 37
    //   9000: aload 20
    //   9002: astore 38
    //   9004: aload 21
    //   9006: astore 39
    //   9008: iload_1
    //   9009: istore_2
    //   9010: aload 16
    //   9012: astore 29
    //   9014: aload 22
    //   9016: astore 28
    //   9018: aload 23
    //   9020: astore 27
    //   9022: aload 17
    //   9024: astore 26
    //   9026: aload 20
    //   9028: astore 25
    //   9030: aload 21
    //   9032: astore 24
    //   9034: iload_1
    //   9035: istore_3
    //   9036: aload 22
    //   9038: astore 36
    //   9040: aload 23
    //   9042: astore 34
    //   9044: aload 17
    //   9046: astore 32
    //   9048: aload 20
    //   9050: astore 31
    //   9052: aload 21
    //   9054: astore 30
    //   9056: aload 18
    //   9058: monitorexit
    //   9059: iload_1
    //   9060: istore 4
    //   9062: aload 22
    //   9064: astore 33
    //   9066: aload 23
    //   9068: astore 35
    //   9070: aload 17
    //   9072: astore 37
    //   9074: aload 20
    //   9076: astore 38
    //   9078: aload 21
    //   9080: astore 39
    //   9082: iload_1
    //   9083: istore_2
    //   9084: aload 16
    //   9086: astore 29
    //   9088: aload 22
    //   9090: astore 28
    //   9092: aload 23
    //   9094: astore 27
    //   9096: aload 17
    //   9098: astore 26
    //   9100: aload 20
    //   9102: astore 25
    //   9104: aload 21
    //   9106: astore 24
    //   9108: iload_1
    //   9109: istore_3
    //   9110: aload 22
    //   9112: astore 36
    //   9114: aload 23
    //   9116: astore 34
    //   9118: aload 17
    //   9120: astore 32
    //   9122: aload 20
    //   9124: astore 31
    //   9126: aload 21
    //   9128: astore 30
    //   9130: aload 40
    //   9132: athrow
    //   9133: astore 40
    //   9135: iload_1
    //   9136: istore 4
    //   9138: aload 22
    //   9140: astore 33
    //   9142: aload 23
    //   9144: astore 35
    //   9146: aload 17
    //   9148: astore 37
    //   9150: aload 20
    //   9152: astore 38
    //   9154: aload 21
    //   9156: astore 39
    //   9158: iload_1
    //   9159: istore_2
    //   9160: aload 16
    //   9162: astore 29
    //   9164: aload 22
    //   9166: astore 28
    //   9168: aload 23
    //   9170: astore 27
    //   9172: aload 17
    //   9174: astore 26
    //   9176: aload 20
    //   9178: astore 25
    //   9180: aload 21
    //   9182: astore 24
    //   9184: iload_1
    //   9185: istore_3
    //   9186: aload 22
    //   9188: astore 36
    //   9190: aload 23
    //   9192: astore 34
    //   9194: aload 17
    //   9196: astore 32
    //   9198: aload 20
    //   9200: astore 31
    //   9202: aload 21
    //   9204: astore 30
    //   9206: aload 40
    //   9208: invokevirtual 561	java/io/IOException:printStackTrace	()V
    //   9211: iload_1
    //   9212: istore 4
    //   9214: aload 22
    //   9216: astore 33
    //   9218: aload 23
    //   9220: astore 35
    //   9222: aload 17
    //   9224: astore 37
    //   9226: aload 20
    //   9228: astore 38
    //   9230: aload 21
    //   9232: astore 39
    //   9234: iload_1
    //   9235: istore_2
    //   9236: aload 16
    //   9238: astore 29
    //   9240: aload 22
    //   9242: astore 28
    //   9244: aload 23
    //   9246: astore 27
    //   9248: aload 17
    //   9250: astore 26
    //   9252: aload 20
    //   9254: astore 25
    //   9256: aload 21
    //   9258: astore 24
    //   9260: iload_1
    //   9261: istore_3
    //   9262: aload 22
    //   9264: astore 36
    //   9266: aload 23
    //   9268: astore 34
    //   9270: aload 17
    //   9272: astore 32
    //   9274: aload 20
    //   9276: astore 31
    //   9278: aload 21
    //   9280: astore 30
    //   9282: aload 18
    //   9284: monitorenter
    //   9285: aload 18
    //   9287: getfield 559	com/taobao/munion/net/b$f:f	J
    //   9290: lstore 14
    //   9292: aload 18
    //   9294: invokestatic 409	java/lang/System:nanoTime	()J
    //   9297: lload 12
    //   9299: lsub
    //   9300: ldc2_w 410
    //   9303: ldiv
    //   9304: lload 14
    //   9306: ladd
    //   9307: putfield 559	com/taobao/munion/net/b$f:f	J
    //   9310: aload 18
    //   9312: monitorexit
    //   9313: iload_1
    //   9314: istore 4
    //   9316: aload 22
    //   9318: astore 33
    //   9320: aload 23
    //   9322: astore 35
    //   9324: aload 17
    //   9326: astore 37
    //   9328: aload 20
    //   9330: astore 38
    //   9332: aload 21
    //   9334: astore 39
    //   9336: iload_1
    //   9337: istore_2
    //   9338: aload 16
    //   9340: astore 29
    //   9342: aload 22
    //   9344: astore 28
    //   9346: aload 23
    //   9348: astore 27
    //   9350: aload 17
    //   9352: astore 26
    //   9354: aload 20
    //   9356: astore 25
    //   9358: aload 21
    //   9360: astore 24
    //   9362: iload_1
    //   9363: istore_3
    //   9364: aload 22
    //   9366: astore 36
    //   9368: aload 23
    //   9370: astore 34
    //   9372: aload 17
    //   9374: astore 32
    //   9376: aload 20
    //   9378: astore 31
    //   9380: aload 21
    //   9382: astore 30
    //   9384: new 227	com/taobao/munion/net/h
    //   9387: dup
    //   9388: bipush -7
    //   9390: invokespecial 564	com/taobao/munion/net/h:<init>	(I)V
    //   9393: astore 40
    //   9395: getstatic 104	com/taobao/munion/net/b:u	Lcom/taobao/munion/net/c;
    //   9398: ifnull +47 -> 9445
    //   9401: iconst_0
    //   9402: istore_2
    //   9403: aload 23
    //   9405: ifnull +9 -> 9414
    //   9408: aload 23
    //   9410: invokevirtual 302	java/io/ByteArrayOutputStream:size	()I
    //   9413: istore_2
    //   9414: aload 20
    //   9416: ifnull +9 -> 9425
    //   9419: aload 20
    //   9421: getfield 306	com/taobao/munion/net/n:a	I
    //   9424: istore_2
    //   9425: getstatic 104	com/taobao/munion/net/b:u	Lcom/taobao/munion/net/c;
    //   9428: iload_1
    //   9429: iload_2
    //   9430: invokestatic 183	java/lang/System:currentTimeMillis	()J
    //   9433: aload_0
    //   9434: getfield 67	com/taobao/munion/net/b:t	J
    //   9437: lsub
    //   9438: aload 16
    //   9440: invokeinterface 238 6 0
    //   9445: aload 22
    //   9447: ifnull +8 -> 9455
    //   9450: aload 22
    //   9452: invokevirtual 311	java/io/DataInputStream:close	()V
    //   9455: aload 17
    //   9457: ifnull +8 -> 9465
    //   9460: aload 17
    //   9462: invokevirtual 314	java/io/InputStream:close	()V
    //   9465: aload 20
    //   9467: ifnull +8 -> 9475
    //   9470: aload 20
    //   9472: invokevirtual 315	com/taobao/munion/net/n:close	()V
    //   9475: aload 21
    //   9477: ifnull +8 -> 9485
    //   9480: aload 21
    //   9482: invokevirtual 318	java/util/zip/GZIPInputStream:close	()V
    //   9485: aload 23
    //   9487: ifnull +8 -> 9495
    //   9490: aload 23
    //   9492: invokevirtual 319	java/io/ByteArrayOutputStream:close	()V
    //   9495: aload 40
    //   9497: areturn
    //   9498: astore 40
    //   9500: iload_1
    //   9501: istore 4
    //   9503: aload 22
    //   9505: astore 33
    //   9507: aload 23
    //   9509: astore 35
    //   9511: aload 17
    //   9513: astore 37
    //   9515: aload 20
    //   9517: astore 38
    //   9519: aload 21
    //   9521: astore 39
    //   9523: iload_1
    //   9524: istore_2
    //   9525: aload 16
    //   9527: astore 29
    //   9529: aload 22
    //   9531: astore 28
    //   9533: aload 23
    //   9535: astore 27
    //   9537: aload 17
    //   9539: astore 26
    //   9541: aload 20
    //   9543: astore 25
    //   9545: aload 21
    //   9547: astore 24
    //   9549: iload_1
    //   9550: istore_3
    //   9551: aload 22
    //   9553: astore 36
    //   9555: aload 23
    //   9557: astore 34
    //   9559: aload 17
    //   9561: astore 32
    //   9563: aload 20
    //   9565: astore 31
    //   9567: aload 21
    //   9569: astore 30
    //   9571: aload 18
    //   9573: monitorexit
    //   9574: iload_1
    //   9575: istore 4
    //   9577: aload 22
    //   9579: astore 33
    //   9581: aload 23
    //   9583: astore 35
    //   9585: aload 17
    //   9587: astore 37
    //   9589: aload 20
    //   9591: astore 38
    //   9593: aload 21
    //   9595: astore 39
    //   9597: iload_1
    //   9598: istore_2
    //   9599: aload 16
    //   9601: astore 29
    //   9603: aload 22
    //   9605: astore 28
    //   9607: aload 23
    //   9609: astore 27
    //   9611: aload 17
    //   9613: astore 26
    //   9615: aload 20
    //   9617: astore 25
    //   9619: aload 21
    //   9621: astore 24
    //   9623: iload_1
    //   9624: istore_3
    //   9625: aload 22
    //   9627: astore 36
    //   9629: aload 23
    //   9631: astore 34
    //   9633: aload 17
    //   9635: astore 32
    //   9637: aload 20
    //   9639: astore 31
    //   9641: aload 21
    //   9643: astore 30
    //   9645: aload 40
    //   9647: athrow
    //   9648: astore 40
    //   9650: iload_1
    //   9651: istore 4
    //   9653: aload 22
    //   9655: astore 33
    //   9657: aload 23
    //   9659: astore 35
    //   9661: aload 17
    //   9663: astore 37
    //   9665: aload 20
    //   9667: astore 38
    //   9669: aload 21
    //   9671: astore 39
    //   9673: iload_1
    //   9674: istore_2
    //   9675: aload 16
    //   9677: astore 29
    //   9679: aload 22
    //   9681: astore 28
    //   9683: aload 23
    //   9685: astore 27
    //   9687: aload 17
    //   9689: astore 26
    //   9691: aload 20
    //   9693: astore 25
    //   9695: aload 21
    //   9697: astore 24
    //   9699: iload_1
    //   9700: istore_3
    //   9701: aload 22
    //   9703: astore 36
    //   9705: aload 23
    //   9707: astore 34
    //   9709: aload 17
    //   9711: astore 32
    //   9713: aload 20
    //   9715: astore 31
    //   9717: aload 21
    //   9719: astore 30
    //   9721: aload 18
    //   9723: monitorexit
    //   9724: iload_1
    //   9725: istore 4
    //   9727: aload 22
    //   9729: astore 33
    //   9731: aload 23
    //   9733: astore 35
    //   9735: aload 17
    //   9737: astore 37
    //   9739: aload 20
    //   9741: astore 38
    //   9743: aload 21
    //   9745: astore 39
    //   9747: iload_1
    //   9748: istore_2
    //   9749: aload 16
    //   9751: astore 29
    //   9753: aload 22
    //   9755: astore 28
    //   9757: aload 23
    //   9759: astore 27
    //   9761: aload 17
    //   9763: astore 26
    //   9765: aload 20
    //   9767: astore 25
    //   9769: aload 21
    //   9771: astore 24
    //   9773: iload_1
    //   9774: istore_3
    //   9775: aload 22
    //   9777: astore 36
    //   9779: aload 23
    //   9781: astore 34
    //   9783: aload 17
    //   9785: astore 32
    //   9787: aload 20
    //   9789: astore 31
    //   9791: aload 21
    //   9793: astore 30
    //   9795: aload 40
    //   9797: athrow
    //   9798: iload_1
    //   9799: istore 4
    //   9801: aload 22
    //   9803: astore 33
    //   9805: aload 23
    //   9807: astore 35
    //   9809: aload 17
    //   9811: astore 37
    //   9813: aload 20
    //   9815: astore 38
    //   9817: aload 21
    //   9819: astore 39
    //   9821: iload_1
    //   9822: istore_2
    //   9823: aload 16
    //   9825: astore 29
    //   9827: aload 22
    //   9829: astore 28
    //   9831: aload 23
    //   9833: astore 27
    //   9835: aload 17
    //   9837: astore 26
    //   9839: aload 20
    //   9841: astore 25
    //   9843: aload 21
    //   9845: astore 24
    //   9847: iload_1
    //   9848: istore_3
    //   9849: aload 22
    //   9851: astore 36
    //   9853: aload 23
    //   9855: astore 34
    //   9857: aload 17
    //   9859: astore 32
    //   9861: aload 20
    //   9863: astore 31
    //   9865: aload 21
    //   9867: astore 30
    //   9869: aload_0
    //   9870: getfield 87	com/taobao/munion/net/b:p	Lcom/taobao/munion/net/e;
    //   9873: getfield 526	com/taobao/munion/net/e:q	Ljava/io/OutputStream;
    //   9876: ifnonnull +374 -> 10250
    //   9879: iload_1
    //   9880: istore 4
    //   9882: aload 22
    //   9884: astore 33
    //   9886: aload 23
    //   9888: astore 35
    //   9890: aload 17
    //   9892: astore 37
    //   9894: aload 20
    //   9896: astore 38
    //   9898: aload 21
    //   9900: astore 39
    //   9902: iload_1
    //   9903: istore_2
    //   9904: aload 16
    //   9906: astore 29
    //   9908: aload 22
    //   9910: astore 28
    //   9912: aload 23
    //   9914: astore 27
    //   9916: aload 17
    //   9918: astore 26
    //   9920: aload 20
    //   9922: astore 25
    //   9924: aload 21
    //   9926: astore 24
    //   9928: iload_1
    //   9929: istore_3
    //   9930: aload 22
    //   9932: astore 36
    //   9934: aload 23
    //   9936: astore 34
    //   9938: aload 17
    //   9940: astore 32
    //   9942: aload 20
    //   9944: astore 31
    //   9946: aload 21
    //   9948: astore 30
    //   9950: aload 23
    //   9952: invokevirtual 567	java/io/ByteArrayOutputStream:toByteArray	()[B
    //   9955: astore 40
    //   9957: iload_1
    //   9958: istore 4
    //   9960: aload 22
    //   9962: astore 33
    //   9964: aload 23
    //   9966: astore 35
    //   9968: aload 17
    //   9970: astore 37
    //   9972: aload 20
    //   9974: astore 38
    //   9976: aload 21
    //   9978: astore 39
    //   9980: iload_1
    //   9981: istore_2
    //   9982: aload 16
    //   9984: astore 29
    //   9986: aload 22
    //   9988: astore 28
    //   9990: aload 23
    //   9992: astore 27
    //   9994: aload 17
    //   9996: astore 26
    //   9998: aload 20
    //   10000: astore 25
    //   10002: aload 21
    //   10004: astore 24
    //   10006: iload_1
    //   10007: istore_3
    //   10008: aload 22
    //   10010: astore 36
    //   10012: aload 23
    //   10014: astore 34
    //   10016: aload 17
    //   10018: astore 32
    //   10020: aload 20
    //   10022: astore 31
    //   10024: aload 21
    //   10026: astore 30
    //   10028: aload 18
    //   10030: monitorenter
    //   10031: aload 18
    //   10033: getfield 559	com/taobao/munion/net/b$f:f	J
    //   10036: lstore 14
    //   10038: aload 18
    //   10040: invokestatic 409	java/lang/System:nanoTime	()J
    //   10043: lload 12
    //   10045: lsub
    //   10046: ldc2_w 410
    //   10049: ldiv
    //   10050: lload 14
    //   10052: ladd
    //   10053: putfield 559	com/taobao/munion/net/b$f:f	J
    //   10056: aload 18
    //   10058: monitorexit
    //   10059: iload_1
    //   10060: istore 4
    //   10062: aload 22
    //   10064: astore 33
    //   10066: aload 23
    //   10068: astore 35
    //   10070: aload 17
    //   10072: astore 37
    //   10074: aload 20
    //   10076: astore 38
    //   10078: aload 21
    //   10080: astore 39
    //   10082: iload_1
    //   10083: istore_2
    //   10084: aload 16
    //   10086: astore 29
    //   10088: aload 22
    //   10090: astore 28
    //   10092: aload 23
    //   10094: astore 27
    //   10096: aload 17
    //   10098: astore 26
    //   10100: aload 20
    //   10102: astore 25
    //   10104: aload 21
    //   10106: astore 24
    //   10108: iload_1
    //   10109: istore_3
    //   10110: aload 22
    //   10112: astore 36
    //   10114: aload 23
    //   10116: astore 34
    //   10118: aload 17
    //   10120: astore 32
    //   10122: aload 20
    //   10124: astore 31
    //   10126: aload 21
    //   10128: astore 30
    //   10130: new 227	com/taobao/munion/net/h
    //   10133: dup
    //   10134: sipush 200
    //   10137: ldc_w 569
    //   10140: aload 40
    //   10142: invokespecial 336	com/taobao/munion/net/h:<init>	(ILjava/lang/String;[B)V
    //   10145: astore 40
    //   10147: getstatic 104	com/taobao/munion/net/b:u	Lcom/taobao/munion/net/c;
    //   10150: ifnull +47 -> 10197
    //   10153: iconst_0
    //   10154: istore_2
    //   10155: aload 23
    //   10157: ifnull +9 -> 10166
    //   10160: aload 23
    //   10162: invokevirtual 302	java/io/ByteArrayOutputStream:size	()I
    //   10165: istore_2
    //   10166: aload 20
    //   10168: ifnull +9 -> 10177
    //   10171: aload 20
    //   10173: getfield 306	com/taobao/munion/net/n:a	I
    //   10176: istore_2
    //   10177: getstatic 104	com/taobao/munion/net/b:u	Lcom/taobao/munion/net/c;
    //   10180: iload_1
    //   10181: iload_2
    //   10182: invokestatic 183	java/lang/System:currentTimeMillis	()J
    //   10185: aload_0
    //   10186: getfield 67	com/taobao/munion/net/b:t	J
    //   10189: lsub
    //   10190: aload 16
    //   10192: invokeinterface 238 6 0
    //   10197: aload 22
    //   10199: ifnull +8 -> 10207
    //   10202: aload 22
    //   10204: invokevirtual 311	java/io/DataInputStream:close	()V
    //   10207: aload 17
    //   10209: ifnull +8 -> 10217
    //   10212: aload 17
    //   10214: invokevirtual 314	java/io/InputStream:close	()V
    //   10217: aload 20
    //   10219: ifnull +8 -> 10227
    //   10222: aload 20
    //   10224: invokevirtual 315	com/taobao/munion/net/n:close	()V
    //   10227: aload 21
    //   10229: ifnull +8 -> 10237
    //   10232: aload 21
    //   10234: invokevirtual 318	java/util/zip/GZIPInputStream:close	()V
    //   10237: aload 23
    //   10239: ifnull +8 -> 10247
    //   10242: aload 23
    //   10244: invokevirtual 319	java/io/ByteArrayOutputStream:close	()V
    //   10247: aload 40
    //   10249: areturn
    //   10250: aconst_null
    //   10251: astore 40
    //   10253: goto -296 -> 9957
    //   10256: astore 40
    //   10258: iload_1
    //   10259: istore 4
    //   10261: aload 22
    //   10263: astore 33
    //   10265: aload 23
    //   10267: astore 35
    //   10269: aload 17
    //   10271: astore 37
    //   10273: aload 20
    //   10275: astore 38
    //   10277: aload 21
    //   10279: astore 39
    //   10281: iload_1
    //   10282: istore_2
    //   10283: aload 16
    //   10285: astore 29
    //   10287: aload 22
    //   10289: astore 28
    //   10291: aload 23
    //   10293: astore 27
    //   10295: aload 17
    //   10297: astore 26
    //   10299: aload 20
    //   10301: astore 25
    //   10303: aload 21
    //   10305: astore 24
    //   10307: iload_1
    //   10308: istore_3
    //   10309: aload 22
    //   10311: astore 36
    //   10313: aload 23
    //   10315: astore 34
    //   10317: aload 17
    //   10319: astore 32
    //   10321: aload 20
    //   10323: astore 31
    //   10325: aload 21
    //   10327: astore 30
    //   10329: aload 18
    //   10331: monitorexit
    //   10332: iload_1
    //   10333: istore 4
    //   10335: aload 22
    //   10337: astore 33
    //   10339: aload 23
    //   10341: astore 35
    //   10343: aload 17
    //   10345: astore 37
    //   10347: aload 20
    //   10349: astore 38
    //   10351: aload 21
    //   10353: astore 39
    //   10355: iload_1
    //   10356: istore_2
    //   10357: aload 16
    //   10359: astore 29
    //   10361: aload 22
    //   10363: astore 28
    //   10365: aload 23
    //   10367: astore 27
    //   10369: aload 17
    //   10371: astore 26
    //   10373: aload 20
    //   10375: astore 25
    //   10377: aload 21
    //   10379: astore 24
    //   10381: iload_1
    //   10382: istore_3
    //   10383: aload 22
    //   10385: astore 36
    //   10387: aload 23
    //   10389: astore 34
    //   10391: aload 17
    //   10393: astore 32
    //   10395: aload 20
    //   10397: astore 31
    //   10399: aload 21
    //   10401: astore 30
    //   10403: aload 40
    //   10405: athrow
    //   10406: astore 22
    //   10408: aload 23
    //   10410: monitorexit
    //   10411: aload 22
    //   10413: athrow
    //   10414: astore 19
    //   10416: iload_1
    //   10417: istore_2
    //   10418: aload 16
    //   10420: astore 29
    //   10422: aload 36
    //   10424: astore 28
    //   10426: aload 34
    //   10428: astore 27
    //   10430: aload 18
    //   10432: astore 26
    //   10434: aload 17
    //   10436: astore 25
    //   10438: aload 20
    //   10440: astore 24
    //   10442: aload 21
    //   10444: monitorexit
    //   10445: iload_1
    //   10446: istore_2
    //   10447: aload 16
    //   10449: astore 29
    //   10451: aload 36
    //   10453: astore 28
    //   10455: aload 34
    //   10457: astore 27
    //   10459: aload 18
    //   10461: astore 26
    //   10463: aload 17
    //   10465: astore 25
    //   10467: aload 20
    //   10469: astore 24
    //   10471: aload 19
    //   10473: athrow
    //   10474: astore 19
    //   10476: iload_1
    //   10477: istore_2
    //   10478: aload 16
    //   10480: astore 29
    //   10482: aload 33
    //   10484: astore 28
    //   10486: aload 35
    //   10488: astore 27
    //   10490: aload 21
    //   10492: astore 26
    //   10494: aload 17
    //   10496: astore 25
    //   10498: aload 22
    //   10500: astore 24
    //   10502: aload 18
    //   10504: monitorexit
    //   10505: iload_1
    //   10506: istore_2
    //   10507: aload 16
    //   10509: astore 29
    //   10511: aload 33
    //   10513: astore 28
    //   10515: aload 35
    //   10517: astore 27
    //   10519: aload 21
    //   10521: astore 26
    //   10523: aload 17
    //   10525: astore 25
    //   10527: aload 22
    //   10529: astore 24
    //   10531: aload 19
    //   10533: athrow
    //   10534: astore 24
    //   10536: goto -2770 -> 7766
    //   10539: astore 18
    //   10541: aload 18
    //   10543: invokevirtual 561	java/io/IOException:printStackTrace	()V
    //   10546: goto -9155 -> 1391
    //   10549: astore 17
    //   10551: aload 17
    //   10553: invokevirtual 561	java/io/IOException:printStackTrace	()V
    //   10556: goto -9155 -> 1401
    //   10559: astore 17
    //   10561: aload 17
    //   10563: invokevirtual 561	java/io/IOException:printStackTrace	()V
    //   10566: goto -9155 -> 1411
    //   10569: astore 17
    //   10571: aload 17
    //   10573: invokevirtual 561	java/io/IOException:printStackTrace	()V
    //   10576: goto -9155 -> 1421
    //   10579: astore 17
    //   10581: aload 17
    //   10583: invokevirtual 561	java/io/IOException:printStackTrace	()V
    //   10586: goto -9155 -> 1431
    //   10589: astore 16
    //   10591: aload 16
    //   10593: invokevirtual 561	java/io/IOException:printStackTrace	()V
    //   10596: goto -8899 -> 1697
    //   10599: astore 16
    //   10601: aload 16
    //   10603: invokevirtual 561	java/io/IOException:printStackTrace	()V
    //   10606: goto -8899 -> 1707
    //   10609: astore 16
    //   10611: aload 16
    //   10613: invokevirtual 561	java/io/IOException:printStackTrace	()V
    //   10616: goto -8899 -> 1717
    //   10619: astore 16
    //   10621: aload 16
    //   10623: invokevirtual 561	java/io/IOException:printStackTrace	()V
    //   10626: goto -8899 -> 1727
    //   10629: astore 16
    //   10631: aload 16
    //   10633: invokevirtual 561	java/io/IOException:printStackTrace	()V
    //   10636: goto -8899 -> 1737
    //   10639: astore 16
    //   10641: aload 16
    //   10643: invokevirtual 561	java/io/IOException:printStackTrace	()V
    //   10646: goto -9989 -> 657
    //   10649: astore 16
    //   10651: aload 16
    //   10653: invokevirtual 561	java/io/IOException:printStackTrace	()V
    //   10656: goto -9987 -> 669
    //   10659: astore 16
    //   10661: aload 16
    //   10663: invokevirtual 561	java/io/IOException:printStackTrace	()V
    //   10666: goto -9985 -> 681
    //   10669: astore 16
    //   10671: aload 16
    //   10673: invokevirtual 561	java/io/IOException:printStackTrace	()V
    //   10676: goto -9983 -> 693
    //   10679: astore 16
    //   10681: aload 16
    //   10683: invokevirtual 561	java/io/IOException:printStackTrace	()V
    //   10686: goto -9981 -> 705
    //   10689: astore 16
    //   10691: aload 16
    //   10693: invokevirtual 561	java/io/IOException:printStackTrace	()V
    //   10696: goto -7670 -> 3026
    //   10699: astore 16
    //   10701: aload 16
    //   10703: invokevirtual 561	java/io/IOException:printStackTrace	()V
    //   10706: goto -7668 -> 3038
    //   10709: astore 16
    //   10711: aload 16
    //   10713: invokevirtual 561	java/io/IOException:printStackTrace	()V
    //   10716: goto -7666 -> 3050
    //   10719: astore 16
    //   10721: aload 16
    //   10723: invokevirtual 561	java/io/IOException:printStackTrace	()V
    //   10726: goto -7664 -> 3062
    //   10729: astore 16
    //   10731: aload 16
    //   10733: invokevirtual 561	java/io/IOException:printStackTrace	()V
    //   10736: goto -7662 -> 3074
    //   10739: astore 16
    //   10741: aload 16
    //   10743: invokevirtual 561	java/io/IOException:printStackTrace	()V
    //   10746: goto -7178 -> 3568
    //   10749: astore 16
    //   10751: aload 16
    //   10753: invokevirtual 561	java/io/IOException:printStackTrace	()V
    //   10756: goto -7176 -> 3580
    //   10759: astore 16
    //   10761: aload 16
    //   10763: invokevirtual 561	java/io/IOException:printStackTrace	()V
    //   10766: goto -7174 -> 3592
    //   10769: astore 16
    //   10771: aload 16
    //   10773: invokevirtual 561	java/io/IOException:printStackTrace	()V
    //   10776: goto -7172 -> 3604
    //   10779: astore 16
    //   10781: aload 16
    //   10783: invokevirtual 561	java/io/IOException:printStackTrace	()V
    //   10786: goto -7170 -> 3616
    //   10789: astore 16
    //   10791: aload 16
    //   10793: invokevirtual 561	java/io/IOException:printStackTrace	()V
    //   10796: goto -7018 -> 3778
    //   10799: astore 16
    //   10801: aload 16
    //   10803: invokevirtual 561	java/io/IOException:printStackTrace	()V
    //   10806: goto -7016 -> 3790
    //   10809: astore 16
    //   10811: aload 16
    //   10813: invokevirtual 561	java/io/IOException:printStackTrace	()V
    //   10816: goto -7014 -> 3802
    //   10819: astore 16
    //   10821: aload 16
    //   10823: invokevirtual 561	java/io/IOException:printStackTrace	()V
    //   10826: goto -7012 -> 3814
    //   10829: astore 16
    //   10831: aload 16
    //   10833: invokevirtual 561	java/io/IOException:printStackTrace	()V
    //   10836: goto -7010 -> 3826
    //   10839: astore 16
    //   10841: aload 16
    //   10843: invokevirtual 561	java/io/IOException:printStackTrace	()V
    //   10846: goto -5566 -> 5280
    //   10849: astore 16
    //   10851: aload 16
    //   10853: invokevirtual 561	java/io/IOException:printStackTrace	()V
    //   10856: goto -5564 -> 5292
    //   10859: astore 16
    //   10861: aload 16
    //   10863: invokevirtual 561	java/io/IOException:printStackTrace	()V
    //   10866: goto -5562 -> 5304
    //   10869: astore 16
    //   10871: aload 16
    //   10873: invokevirtual 561	java/io/IOException:printStackTrace	()V
    //   10876: goto -5560 -> 5316
    //   10879: astore 16
    //   10881: aload 16
    //   10883: invokevirtual 561	java/io/IOException:printStackTrace	()V
    //   10886: goto -5558 -> 5328
    //   10889: astore 16
    //   10891: aload 16
    //   10893: invokevirtual 561	java/io/IOException:printStackTrace	()V
    //   10896: goto -1441 -> 9455
    //   10899: astore 16
    //   10901: aload 16
    //   10903: invokevirtual 561	java/io/IOException:printStackTrace	()V
    //   10906: goto -1441 -> 9465
    //   10909: astore 16
    //   10911: aload 16
    //   10913: invokevirtual 561	java/io/IOException:printStackTrace	()V
    //   10916: goto -1441 -> 9475
    //   10919: astore 16
    //   10921: aload 16
    //   10923: invokevirtual 561	java/io/IOException:printStackTrace	()V
    //   10926: goto -1441 -> 9485
    //   10929: astore 16
    //   10931: aload 16
    //   10933: invokevirtual 561	java/io/IOException:printStackTrace	()V
    //   10936: goto -1441 -> 9495
    //   10939: astore 16
    //   10941: aload 16
    //   10943: invokevirtual 561	java/io/IOException:printStackTrace	()V
    //   10946: goto -2332 -> 8614
    //   10949: astore 16
    //   10951: aload 16
    //   10953: invokevirtual 561	java/io/IOException:printStackTrace	()V
    //   10956: goto -2332 -> 8624
    //   10959: astore 16
    //   10961: aload 16
    //   10963: invokevirtual 561	java/io/IOException:printStackTrace	()V
    //   10966: goto -2332 -> 8634
    //   10969: astore 16
    //   10971: aload 16
    //   10973: invokevirtual 561	java/io/IOException:printStackTrace	()V
    //   10976: goto -2332 -> 8644
    //   10979: astore 16
    //   10981: aload 16
    //   10983: invokevirtual 561	java/io/IOException:printStackTrace	()V
    //   10986: goto -2332 -> 8654
    //   10989: astore 16
    //   10991: aload 16
    //   10993: invokevirtual 561	java/io/IOException:printStackTrace	()V
    //   10996: goto -789 -> 10207
    //   10999: astore 16
    //   11001: aload 16
    //   11003: invokevirtual 561	java/io/IOException:printStackTrace	()V
    //   11006: goto -789 -> 10217
    //   11009: astore 16
    //   11011: aload 16
    //   11013: invokevirtual 561	java/io/IOException:printStackTrace	()V
    //   11016: goto -789 -> 10227
    //   11019: astore 16
    //   11021: aload 16
    //   11023: invokevirtual 561	java/io/IOException:printStackTrace	()V
    //   11026: goto -789 -> 10237
    //   11029: astore 16
    //   11031: aload 16
    //   11033: invokevirtual 561	java/io/IOException:printStackTrace	()V
    //   11036: goto -789 -> 10247
    //   11039: astore 16
    //   11041: aload 16
    //   11043: invokevirtual 561	java/io/IOException:printStackTrace	()V
    //   11046: goto -10015 -> 1031
    //   11049: astore 16
    //   11051: aload 16
    //   11053: invokevirtual 561	java/io/IOException:printStackTrace	()V
    //   11056: goto -10013 -> 1043
    //   11059: astore 16
    //   11061: aload 16
    //   11063: invokevirtual 561	java/io/IOException:printStackTrace	()V
    //   11066: goto -10011 -> 1055
    //   11069: astore 16
    //   11071: aload 16
    //   11073: invokevirtual 561	java/io/IOException:printStackTrace	()V
    //   11076: goto -10009 -> 1067
    //   11079: astore 16
    //   11081: aload 16
    //   11083: invokevirtual 561	java/io/IOException:printStackTrace	()V
    //   11086: goto -10007 -> 1079
    //   11089: astore 16
    //   11091: aload 18
    //   11093: astore 29
    //   11095: aload 45
    //   11097: astore 28
    //   11099: aload 44
    //   11101: astore 27
    //   11103: aload 24
    //   11105: astore 17
    //   11107: aload 50
    //   11109: astore 24
    //   11111: goto -9780 -> 1331
    //   11114: astore 18
    //   11116: aload 16
    //   11118: astore 29
    //   11120: aload 18
    //   11122: astore 16
    //   11124: aload 45
    //   11126: astore 28
    //   11128: aload 44
    //   11130: astore 27
    //   11132: aload 20
    //   11134: astore 25
    //   11136: aload 50
    //   11138: astore 24
    //   11140: goto -9809 -> 1331
    //   11143: astore 18
    //   11145: aload 16
    //   11147: astore 29
    //   11149: aload 18
    //   11151: astore 16
    //   11153: aload 45
    //   11155: astore 28
    //   11157: aload 44
    //   11159: astore 27
    //   11161: aload 20
    //   11163: astore 25
    //   11165: aload 21
    //   11167: astore 24
    //   11169: goto -9838 -> 1331
    //   11172: astore 20
    //   11174: ldc_w 571
    //   11177: astore 17
    //   11179: aload 19
    //   11181: astore 16
    //   11183: aconst_null
    //   11184: astore 18
    //   11186: aload 17
    //   11188: astore 19
    //   11190: aload 41
    //   11192: astore 33
    //   11194: aload 40
    //   11196: astore 35
    //   11198: aload 31
    //   11200: astore 21
    //   11202: aload 30
    //   11204: astore 17
    //   11206: aload 23
    //   11208: astore 22
    //   11210: goto -6924 -> 4286
    //   11213: astore 20
    //   11215: aconst_null
    //   11216: astore 18
    //   11218: ldc_w 571
    //   11221: astore 19
    //   11223: aload 41
    //   11225: astore 33
    //   11227: aload 40
    //   11229: astore 35
    //   11231: aload 31
    //   11233: astore 21
    //   11235: aload 30
    //   11237: astore 17
    //   11239: aload 23
    //   11241: astore 22
    //   11243: goto -6957 -> 4286
    //   11246: astore 20
    //   11248: aconst_null
    //   11249: astore 18
    //   11251: aload 41
    //   11253: astore 33
    //   11255: aload 40
    //   11257: astore 35
    //   11259: aload 31
    //   11261: astore 21
    //   11263: aload 30
    //   11265: astore 17
    //   11267: aload 23
    //   11269: astore 22
    //   11271: goto -6985 -> 4286
    //   11274: astore 21
    //   11276: aload 20
    //   11278: astore 22
    //   11280: aload 21
    //   11282: astore 20
    //   11284: aload 41
    //   11286: astore 33
    //   11288: aload 40
    //   11290: astore 35
    //   11292: aload 17
    //   11294: astore 21
    //   11296: aload 22
    //   11298: astore 17
    //   11300: aload 23
    //   11302: astore 22
    //   11304: goto -7018 -> 4286
    //   11307: astore 24
    //   11309: aload 20
    //   11311: astore 23
    //   11313: aload 21
    //   11315: astore 22
    //   11317: aload 24
    //   11319: astore 20
    //   11321: aload 41
    //   11323: astore 33
    //   11325: aload 40
    //   11327: astore 35
    //   11329: aload 17
    //   11331: astore 21
    //   11333: aload 23
    //   11335: astore 17
    //   11337: goto -7051 -> 4286
    //   11340: astore 19
    //   11342: aload 20
    //   11344: astore 16
    //   11346: aconst_null
    //   11347: astore 21
    //   11349: aload 43
    //   11351: astore 36
    //   11353: aload 42
    //   11355: astore 34
    //   11357: aload 33
    //   11359: astore 18
    //   11361: aload 32
    //   11363: astore 17
    //   11365: aload 22
    //   11367: astore 20
    //   11369: goto -9856 -> 1513
    //   11372: astore 19
    //   11374: aload 18
    //   11376: astore 21
    //   11378: aload 43
    //   11380: astore 36
    //   11382: aload 42
    //   11384: astore 34
    //   11386: aload 17
    //   11388: astore 18
    //   11390: aload 20
    //   11392: astore 17
    //   11394: aload 22
    //   11396: astore 20
    //   11398: goto -9885 -> 1513
    //   11401: astore 19
    //   11403: aload 21
    //   11405: astore 22
    //   11407: aload 18
    //   11409: astore 21
    //   11411: aload 43
    //   11413: astore 36
    //   11415: aload 42
    //   11417: astore 34
    //   11419: aload 17
    //   11421: astore 18
    //   11423: aload 20
    //   11425: astore 17
    //   11427: aload 22
    //   11429: astore 20
    //   11431: goto -9918 -> 1513
    //   11434: astore 22
    //   11436: iconst_m1
    //   11437: istore_1
    //   11438: aconst_null
    //   11439: astore 25
    //   11441: aconst_null
    //   11442: astore 19
    //   11444: aconst_null
    //   11445: astore 23
    //   11447: aload 17
    //   11449: astore 21
    //   11451: ldc_w 571
    //   11454: astore 24
    //   11456: aconst_null
    //   11457: astore 16
    //   11459: aconst_null
    //   11460: astore 20
    //   11462: aconst_null
    //   11463: astore 18
    //   11465: aload 25
    //   11467: astore 17
    //   11469: goto -10273 -> 1196
    //   11472: astore 22
    //   11474: iconst_m1
    //   11475: istore_1
    //   11476: ldc_w 571
    //   11479: astore 24
    //   11481: aconst_null
    //   11482: astore 19
    //   11484: aconst_null
    //   11485: astore 18
    //   11487: aconst_null
    //   11488: astore 23
    //   11490: aconst_null
    //   11491: astore 17
    //   11493: aconst_null
    //   11494: astore 20
    //   11496: aload 16
    //   11498: astore 21
    //   11500: aconst_null
    //   11501: astore 25
    //   11503: aload 17
    //   11505: astore 16
    //   11507: aload 25
    //   11509: astore 17
    //   11511: goto -10315 -> 1196
    //   11514: astore 22
    //   11516: aconst_null
    //   11517: astore 27
    //   11519: aload 17
    //   11521: astore 20
    //   11523: aconst_null
    //   11524: astore 25
    //   11526: aconst_null
    //   11527: astore 26
    //   11529: aload 16
    //   11531: astore 21
    //   11533: aconst_null
    //   11534: astore 17
    //   11536: aload 18
    //   11538: astore 23
    //   11540: aload 19
    //   11542: astore 24
    //   11544: aload 27
    //   11546: astore 16
    //   11548: aload 20
    //   11550: astore 18
    //   11552: aload 26
    //   11554: astore 19
    //   11556: aload 25
    //   11558: astore 20
    //   11560: goto -10364 -> 1196
    //   11563: astore 22
    //   11565: aconst_null
    //   11566: astore 27
    //   11568: aload 17
    //   11570: astore 21
    //   11572: aconst_null
    //   11573: astore 26
    //   11575: aload 19
    //   11577: astore 24
    //   11579: aload 20
    //   11581: astore 19
    //   11583: aload 16
    //   11585: astore 25
    //   11587: aconst_null
    //   11588: astore 17
    //   11590: aload 18
    //   11592: astore 23
    //   11594: aload 27
    //   11596: astore 16
    //   11598: aload 21
    //   11600: astore 18
    //   11602: aload 26
    //   11604: astore 20
    //   11606: aload 25
    //   11608: astore 21
    //   11610: goto -10414 -> 1196
    //   11613: astore 22
    //   11615: aload 17
    //   11617: astore 25
    //   11619: aload 19
    //   11621: astore 24
    //   11623: aload 20
    //   11625: astore 19
    //   11627: aload 16
    //   11629: astore 26
    //   11631: aconst_null
    //   11632: astore 17
    //   11634: aconst_null
    //   11635: astore 16
    //   11637: aload 21
    //   11639: astore 20
    //   11641: aload 18
    //   11643: astore 23
    //   11645: aload 25
    //   11647: astore 18
    //   11649: aload 26
    //   11651: astore 21
    //   11653: goto -10457 -> 1196
    //   11656: astore 23
    //   11658: aload 22
    //   11660: astore 26
    //   11662: aload 17
    //   11664: astore 25
    //   11666: aload 19
    //   11668: astore 24
    //   11670: aload 20
    //   11672: astore 19
    //   11674: aload 16
    //   11676: astore 27
    //   11678: aconst_null
    //   11679: astore 17
    //   11681: aload 23
    //   11683: astore 22
    //   11685: aload 18
    //   11687: astore 23
    //   11689: aload 26
    //   11691: astore 16
    //   11693: aload 25
    //   11695: astore 18
    //   11697: aload 21
    //   11699: astore 20
    //   11701: aload 27
    //   11703: astore 21
    //   11705: goto -10509 -> 1196
    //   11708: aload 17
    //   11710: astore 16
    //   11712: aload 18
    //   11714: astore 17
    //   11716: goto -11493 -> 223
    //   11719: astore 22
    //   11721: iload 5
    //   11723: istore_1
    //   11724: aconst_null
    //   11725: astore 17
    //   11727: aconst_null
    //   11728: astore 25
    //   11730: aconst_null
    //   11731: astore 20
    //   11733: aconst_null
    //   11734: astore 26
    //   11736: aload 16
    //   11738: astore 21
    //   11740: aconst_null
    //   11741: astore 27
    //   11743: aload 18
    //   11745: astore 23
    //   11747: aload 19
    //   11749: astore 24
    //   11751: aload 17
    //   11753: astore 16
    //   11755: aload 27
    //   11757: astore 17
    //   11759: aload 25
    //   11761: astore 18
    //   11763: aload 26
    //   11765: astore 19
    //   11767: goto -10571 -> 1196
    //   11770: astore 19
    //   11772: iload_3
    //   11773: istore_1
    //   11774: aload 18
    //   11776: astore 21
    //   11778: aload 32
    //   11780: astore 18
    //   11782: aload 31
    //   11784: astore 17
    //   11786: aload 30
    //   11788: astore 20
    //   11790: goto -10277 -> 1513
    //   11793: iload 6
    //   11795: iconst_1
    //   11796: iadd
    //   11797: istore 6
    //   11799: goto -6026 -> 5773
    //   11802: iconst_1
    //   11803: istore 7
    //   11805: iload 9
    //   11807: istore 5
    //   11809: goto -4554 -> 7255
    //   11812: astore 28
    //   11814: aload 22
    //   11816: astore 26
    //   11818: aload 17
    //   11820: astore 25
    //   11822: aload 19
    //   11824: astore 24
    //   11826: aload 20
    //   11828: astore 19
    //   11830: aload 16
    //   11832: astore 27
    //   11834: aload 23
    //   11836: astore 17
    //   11838: aload 28
    //   11840: astore 22
    //   11842: aload 18
    //   11844: astore 23
    //   11846: aload 26
    //   11848: astore 16
    //   11850: aload 25
    //   11852: astore 18
    //   11854: aload 21
    //   11856: astore 20
    //   11858: aload 27
    //   11860: astore 21
    //   11862: goto -10666 -> 1196
    // Local variable table:
    //   start	length	slot	name	signature
    //   0	11865	0	this	b
    //   130	11644	1	i1	int
    //   224	10283	2	i2	int
    //   29	11744	3	i3	int
    //   436	9898	4	i4	int
    //   485	11323	5	i5	int
    //   4003	7795	6	i6	int
    //   7436	4368	7	i7	int
    //   7337	1000	8	i8	int
    //   6996	4810	9	i9	int
    //   140	4432	10	i10	int
    //   7077	1112	11	i11	int
    //   6301	3743	12	l1	long
    //   8455	1596	14	l2	long
    //   4	4507	16	localObject1	Object
    //   4577	5931	16	str	String
    //   10589	3	16	localIOException1	java.io.IOException
    //   10599	3	16	localIOException2	java.io.IOException
    //   10609	3	16	localIOException3	java.io.IOException
    //   10619	3	16	localIOException4	java.io.IOException
    //   10629	3	16	localIOException5	java.io.IOException
    //   10639	3	16	localIOException6	java.io.IOException
    //   10649	3	16	localIOException7	java.io.IOException
    //   10659	3	16	localIOException8	java.io.IOException
    //   10669	3	16	localIOException9	java.io.IOException
    //   10679	3	16	localIOException10	java.io.IOException
    //   10689	3	16	localIOException11	java.io.IOException
    //   10699	3	16	localIOException12	java.io.IOException
    //   10709	3	16	localIOException13	java.io.IOException
    //   10719	3	16	localIOException14	java.io.IOException
    //   10729	3	16	localIOException15	java.io.IOException
    //   10739	3	16	localIOException16	java.io.IOException
    //   10749	3	16	localIOException17	java.io.IOException
    //   10759	3	16	localIOException18	java.io.IOException
    //   10769	3	16	localIOException19	java.io.IOException
    //   10779	3	16	localIOException20	java.io.IOException
    //   10789	3	16	localIOException21	java.io.IOException
    //   10799	3	16	localIOException22	java.io.IOException
    //   10809	3	16	localIOException23	java.io.IOException
    //   10819	3	16	localIOException24	java.io.IOException
    //   10829	3	16	localIOException25	java.io.IOException
    //   10839	3	16	localIOException26	java.io.IOException
    //   10849	3	16	localIOException27	java.io.IOException
    //   10859	3	16	localIOException28	java.io.IOException
    //   10869	3	16	localIOException29	java.io.IOException
    //   10879	3	16	localIOException30	java.io.IOException
    //   10889	3	16	localIOException31	java.io.IOException
    //   10899	3	16	localIOException32	java.io.IOException
    //   10909	3	16	localIOException33	java.io.IOException
    //   10919	3	16	localIOException34	java.io.IOException
    //   10929	3	16	localIOException35	java.io.IOException
    //   10939	3	16	localIOException36	java.io.IOException
    //   10949	3	16	localIOException37	java.io.IOException
    //   10959	3	16	localIOException38	java.io.IOException
    //   10969	3	16	localIOException39	java.io.IOException
    //   10979	3	16	localIOException40	java.io.IOException
    //   10989	3	16	localIOException41	java.io.IOException
    //   10999	3	16	localIOException42	java.io.IOException
    //   11009	3	16	localIOException43	java.io.IOException
    //   11019	3	16	localIOException44	java.io.IOException
    //   11029	3	16	localIOException45	java.io.IOException
    //   11039	3	16	localIOException46	java.io.IOException
    //   11049	3	16	localIOException47	java.io.IOException
    //   11059	3	16	localIOException48	java.io.IOException
    //   11069	3	16	localIOException49	java.io.IOException
    //   11079	3	16	localIOException50	java.io.IOException
    //   11089	28	16	localObject2	Object
    //   11122	727	16	localObject3	Object
    //   156	2919	17	localObject4	Object
    //   3077	154	17	localObject5	Object
    //   3504	7020	17	localObject6	Object
    //   10549	3	17	localIOException51	java.io.IOException
    //   10559	3	17	localIOException52	java.io.IOException
    //   10569	3	17	localIOException53	java.io.IOException
    //   10579	3	17	localIOException54	java.io.IOException
    //   11105	732	17	localObject7	Object
    //   144	10359	18	localObject8	Object
    //   10539	553	18	localIOException55	java.io.IOException
    //   11114	7	18	localObject9	Object
    //   11143	7	18	localObject10	Object
    //   11184	669	18	localObject11	Object
    //   148	1164	19	localObject12	Object
    //   1488	139	19	localFileNotFoundException1	java.io.FileNotFoundException
    //   1635	3412	19	localh1	h
    //   10414	58	19	localObject13	Object
    //   10474	706	19	localObject14	Object
    //   11188	34	19	localObject15	Object
    //   11340	1	19	localFileNotFoundException2	java.io.FileNotFoundException
    //   11372	1	19	localFileNotFoundException3	java.io.FileNotFoundException
    //   11401	1	19	localFileNotFoundException4	java.io.FileNotFoundException
    //   11442	324	19	localObject16	Object
    //   11770	53	19	localFileNotFoundException5	java.io.FileNotFoundException
    //   11828	1	19	localObject17	Object
    //   152	2239	20	localObject18	Object
    //   4269	292	20	localException1	Exception
    //   4766	6396	20	localObject19	Object
    //   11172	1	20	localException2	Exception
    //   11213	1	20	localException3	Exception
    //   11246	31	20	localException4	Exception
    //   11282	575	20	localObject20	Object
    //   43	11219	21	localObject21	Object
    //   11274	7	21	localException5	Exception
    //   11294	567	21	localObject22	Object
    //   31	1	22	localObject23	Object
    //   1162	115	22	localSocketTimeoutException1	java.net.SocketTimeoutException
    //   1297	9087	22	localObject24	Object
    //   10406	122	22	localObject25	Object
    //   11208	220	22	localObject26	Object
    //   11434	1	22	localSocketTimeoutException2	java.net.SocketTimeoutException
    //   11472	1	22	localSocketTimeoutException3	java.net.SocketTimeoutException
    //   11514	1	22	localSocketTimeoutException4	java.net.SocketTimeoutException
    //   11563	1	22	localSocketTimeoutException5	java.net.SocketTimeoutException
    //   11613	46	22	localSocketTimeoutException6	java.net.SocketTimeoutException
    //   11683	1	22	localObject27	Object
    //   11719	96	22	localSocketTimeoutException7	java.net.SocketTimeoutException
    //   11840	1	22	localObject28	Object
    //   37	1180	23	localObject29	Object
    //   1293	7	23	localObject30	Object
    //   6914	4730	23	localObject31	Object
    //   11656	26	23	localSocketTimeoutException8	java.net.SocketTimeoutException
    //   11687	158	23	localObject32	Object
    //   88	10442	24	localObject33	Object
    //   10534	570	24	localException6	Exception
    //   11109	59	24	localObject34	Object
    //   11307	11	24	localException7	Exception
    //   11454	371	24	localObject35	Object
    //   70	11781	25	localObject36	Object
    //   132	11715	26	localObject37	Object
    //   235	11624	27	localObject38	Object
    //   231	10925	28	localObject39	Object
    //   11812	27	28	localSocketTimeoutException9	java.net.SocketTimeoutException
    //   227	10921	29	localObject40	Object
    //   58	11729	30	localObject41	Object
    //   79	11704	31	localObject42	Object
    //   52	11727	32	localObject43	Object
    //   73	11285	33	localObject44	Object
    //   495	10923	34	localObject45	Object
    //   444	10884	35	localObject46	Object
    //   491	10923	36	localObject47	Object
    //   448	9898	37	localObject48	Object
    //   452	9898	38	localObject49	Object
    //   456	9898	39	localObject50	Object
    //   97	8732	40	localObject51	Object
    //   8833	148	40	localObject52	Object
    //   8983	148	40	localObject53	Object
    //   9133	74	40	localIOException56	java.io.IOException
    //   9393	103	40	localh2	h
    //   9498	148	40	localObject54	Object
    //   9648	148	40	localObject55	Object
    //   9955	297	40	localObject56	Object
    //   10256	1070	40	localObject57	Object
    //   118	11204	41	arrayOfByte	byte[]
    //   91	11325	42	localObject58	Object
    //   112	11300	43	localObject59	Object
    //   109	11049	44	localObject60	Object
    //   127	11027	45	localObject61	Object
    //   100	8680	46	localObject62	Object
    //   106	8696	47	localObject63	Object
    //   94	8660	48	localObject64	Object
    //   103	6810	49	localObject65	Object
    //   49	11088	50	localObject66	Object
    //   40	8663	51	localObject67	Object
    //   124	8585	52	localObject68	Object
    //   121	8566	53	localObject69	Object
    //   34	8643	54	localObject70	Object
    //   64	8676	55	localObject71	Object
    //   67	8654	56	localObject72	Object
    //   55	8618	57	localObject73	Object
    //   61	8638	58	localObject74	Object
    //   115	8546	59	localObject75	Object
    //   46	8679	60	localObject76	Object
    //   82	6345	61	localObject77	Object
    //   76	6325	62	localObject78	Object
    //   85	6367	63	localObject79	Object
    //   359	6105	64	localObject80	Object
    //   2400	3814	65	localObject81	Object
    // Exception table:
    //   from	to	target	type
    //   319	325	1162	java/net/SocketTimeoutException
    //   355	361	1162	java/net/SocketTimeoutException
    //   387	398	1162	java/net/SocketTimeoutException
    //   430	435	1162	java/net/SocketTimeoutException
    //   895	905	1162	java/net/SocketTimeoutException
    //   931	938	1162	java/net/SocketTimeoutException
    //   964	969	1162	java/net/SocketTimeoutException
    //   1113	1122	1162	java/net/SocketTimeoutException
    //   1148	1162	1162	java/net/SocketTimeoutException
    //   1460	1485	1162	java/net/SocketTimeoutException
    //   1771	1776	1162	java/net/SocketTimeoutException
    //   1201	1204	1293	finally
    //   1219	1239	1293	finally
    //   1239	1293	1293	finally
    //   10408	10414	1293	finally
    //   249	260	1488	java/io/FileNotFoundException
    //   286	293	1488	java/io/FileNotFoundException
    //   319	325	1488	java/io/FileNotFoundException
    //   355	361	1488	java/io/FileNotFoundException
    //   387	398	1488	java/io/FileNotFoundException
    //   430	435	1488	java/io/FileNotFoundException
    //   895	905	1488	java/io/FileNotFoundException
    //   931	938	1488	java/io/FileNotFoundException
    //   964	969	1488	java/io/FileNotFoundException
    //   1113	1122	1488	java/io/FileNotFoundException
    //   1148	1162	1488	java/io/FileNotFoundException
    //   1460	1485	1488	java/io/FileNotFoundException
    //   1771	1776	1488	java/io/FileNotFoundException
    //   2834	2869	3077	finally
    //   509	516	4269	java/lang/Exception
    //   590	595	4269	java/lang/Exception
    //   1858	1871	4269	java/lang/Exception
    //   1945	1967	4269	java/lang/Exception
    //   2041	2051	4269	java/lang/Exception
    //   2129	2139	4269	java/lang/Exception
    //   2213	2232	4269	java/lang/Exception
    //   2306	2316	4269	java/lang/Exception
    //   2390	2402	4269	java/lang/Exception
    //   2476	2503	4269	java/lang/Exception
    //   2580	2591	4269	java/lang/Exception
    //   2668	2674	4269	java/lang/Exception
    //   2748	2757	4269	java/lang/Exception
    //   2831	2834	4269	java/lang/Exception
    //   2948	2964	4269	java/lang/Exception
    //   3153	3156	4269	java/lang/Exception
    //   3230	3233	4269	java/lang/Exception
    //   3307	3320	4269	java/lang/Exception
    //   3394	3409	4269	java/lang/Exception
    //   3490	3506	4269	java/lang/Exception
    //   3700	3716	4269	java/lang/Exception
    //   3903	3913	4269	java/lang/Exception
    //   3987	4002	4269	java/lang/Exception
    //   4086	4096	4269	java/lang/Exception
    //   4175	4183	4269	java/lang/Exception
    //   4257	4269	4269	java/lang/Exception
    //   4668	4678	4269	java/lang/Exception
    //   4752	4768	4269	java/lang/Exception
    //   4851	4868	4269	java/lang/Exception
    //   4951	4965	4269	java/lang/Exception
    //   5039	5058	4269	java/lang/Exception
    //   5132	5138	4269	java/lang/Exception
    //   5212	5218	4269	java/lang/Exception
    //   5412	5422	4269	java/lang/Exception
    //   5496	5510	4269	java/lang/Exception
    //   5584	5594	4269	java/lang/Exception
    //   5668	5687	4269	java/lang/Exception
    //   5761	5770	4269	java/lang/Exception
    //   5847	5855	4269	java/lang/Exception
    //   5941	5950	4269	java/lang/Exception
    //   6029	6038	4269	java/lang/Exception
    //   6112	6122	4269	java/lang/Exception
    //   6201	6221	4269	java/lang/Exception
    //   6298	6303	4269	java/lang/Exception
    //   6377	6389	4269	java/lang/Exception
    //   6463	6477	4269	java/lang/Exception
    //   6553	6569	4269	java/lang/Exception
    //   6640	6651	4269	java/lang/Exception
    //   6744	6751	4269	java/lang/Exception
    //   6822	6832	4269	java/lang/Exception
    //   6903	6912	4269	java/lang/Exception
    //   6987	6998	4269	java/lang/Exception
    //   7069	7079	4269	java/lang/Exception
    //   7150	7157	4269	java/lang/Exception
    //   7228	7252	4269	java/lang/Exception
    //   7326	7339	4269	java/lang/Exception
    //   7416	7419	4269	java/lang/Exception
    //   7516	7519	4269	java/lang/Exception
    //   7617	7627	4269	java/lang/Exception
    //   7698	7707	4269	java/lang/Exception
    //   7837	7843	4269	java/lang/Exception
    //   7914	7928	4269	java/lang/Exception
    //   8003	8010	4269	java/lang/Exception
    //   8085	8099	4269	java/lang/Exception
    //   8170	8194	4269	java/lang/Exception
    //   8280	8287	4269	java/lang/Exception
    //   8366	8376	4269	java/lang/Exception
    //   8447	8450	4269	java/lang/Exception
    //   8549	8554	4269	java/lang/Exception
    //   8728	8739	4269	java/lang/Exception
    //   8817	8826	4269	java/lang/Exception
    //   8906	8909	4269	java/lang/Exception
    //   8980	8983	4269	java/lang/Exception
    //   9056	9059	4269	java/lang/Exception
    //   9130	9133	4269	java/lang/Exception
    //   9206	9211	4269	java/lang/Exception
    //   9282	9285	4269	java/lang/Exception
    //   9384	9395	4269	java/lang/Exception
    //   9571	9574	4269	java/lang/Exception
    //   9645	9648	4269	java/lang/Exception
    //   9721	9724	4269	java/lang/Exception
    //   9795	9798	4269	java/lang/Exception
    //   9869	9879	4269	java/lang/Exception
    //   9950	9957	4269	java/lang/Exception
    //   10028	10031	4269	java/lang/Exception
    //   10130	10147	4269	java/lang/Exception
    //   10329	10332	4269	java/lang/Exception
    //   10403	10406	4269	java/lang/Exception
    //   249	260	4577	finally
    //   286	293	4577	finally
    //   319	325	4577	finally
    //   355	361	4577	finally
    //   387	398	4577	finally
    //   430	435	4577	finally
    //   509	516	4577	finally
    //   590	595	4577	finally
    //   895	905	4577	finally
    //   931	938	4577	finally
    //   964	969	4577	finally
    //   1113	1122	4577	finally
    //   1148	1162	4577	finally
    //   1460	1485	4577	finally
    //   1544	1547	4577	finally
    //   1588	1593	4577	finally
    //   1619	1637	4577	finally
    //   1771	1776	4577	finally
    //   1858	1871	4577	finally
    //   1945	1967	4577	finally
    //   2041	2051	4577	finally
    //   2129	2139	4577	finally
    //   2213	2232	4577	finally
    //   2306	2316	4577	finally
    //   2390	2402	4577	finally
    //   2476	2503	4577	finally
    //   2580	2591	4577	finally
    //   2668	2674	4577	finally
    //   2748	2757	4577	finally
    //   2831	2834	4577	finally
    //   2948	2964	4577	finally
    //   3153	3156	4577	finally
    //   3230	3233	4577	finally
    //   3307	3320	4577	finally
    //   3394	3409	4577	finally
    //   3490	3506	4577	finally
    //   3700	3716	4577	finally
    //   3903	3913	4577	finally
    //   3987	4002	4577	finally
    //   4086	4096	4577	finally
    //   4175	4183	4577	finally
    //   4257	4269	4577	finally
    //   4317	4320	4577	finally
    //   4361	4367	4577	finally
    //   4393	4398	4577	finally
    //   4429	4434	4577	finally
    //   4460	4470	4577	finally
    //   4496	4508	4577	finally
    //   4534	4577	4577	finally
    //   4668	4678	4577	finally
    //   4752	4768	4577	finally
    //   4851	4868	4577	finally
    //   4951	4965	4577	finally
    //   5039	5058	4577	finally
    //   5132	5138	4577	finally
    //   5212	5218	4577	finally
    //   5412	5422	4577	finally
    //   5496	5510	4577	finally
    //   5584	5594	4577	finally
    //   5668	5687	4577	finally
    //   5761	5770	4577	finally
    //   5847	5855	4577	finally
    //   5941	5950	4577	finally
    //   6029	6038	4577	finally
    //   6112	6122	4577	finally
    //   6201	6221	4577	finally
    //   6298	6303	4577	finally
    //   6377	6389	4577	finally
    //   6463	6477	4577	finally
    //   6553	6569	4577	finally
    //   6640	6651	4577	finally
    //   6744	6751	4577	finally
    //   6822	6832	4577	finally
    //   6903	6912	4577	finally
    //   6987	6998	4577	finally
    //   7069	7079	4577	finally
    //   7150	7157	4577	finally
    //   7228	7252	4577	finally
    //   7326	7339	4577	finally
    //   7416	7419	4577	finally
    //   7516	7519	4577	finally
    //   7617	7627	4577	finally
    //   7698	7707	4577	finally
    //   7760	7766	4577	finally
    //   7837	7843	4577	finally
    //   7914	7928	4577	finally
    //   8003	8010	4577	finally
    //   8085	8099	4577	finally
    //   8170	8194	4577	finally
    //   8280	8287	4577	finally
    //   8366	8376	4577	finally
    //   8447	8450	4577	finally
    //   8549	8554	4577	finally
    //   8728	8739	4577	finally
    //   8817	8826	4577	finally
    //   8906	8909	4577	finally
    //   8980	8983	4577	finally
    //   9056	9059	4577	finally
    //   9130	9133	4577	finally
    //   9206	9211	4577	finally
    //   9282	9285	4577	finally
    //   9384	9395	4577	finally
    //   9571	9574	4577	finally
    //   9645	9648	4577	finally
    //   9721	9724	4577	finally
    //   9795	9798	4577	finally
    //   9869	9879	4577	finally
    //   9950	9957	4577	finally
    //   10028	10031	4577	finally
    //   10130	10147	4577	finally
    //   10329	10332	4577	finally
    //   10403	10406	4577	finally
    //   10442	10445	4577	finally
    //   10471	10474	4577	finally
    //   10502	10505	4577	finally
    //   10531	10534	4577	finally
    //   7419	7436	8833	finally
    //   7519	7543	8983	finally
    //   7617	7627	9133	java/io/IOException
    //   7698	7707	9133	java/io/IOException
    //   7760	7766	9133	java/io/IOException
    //   9285	9313	9498	finally
    //   8450	8478	9648	finally
    //   10031	10059	10256	finally
    //   1204	1219	10406	finally
    //   1547	1562	10414	finally
    //   4320	4335	10474	finally
    //   7760	7766	10534	java/lang/Exception
    //   1386	1391	10539	java/io/IOException
    //   1396	1401	10549	java/io/IOException
    //   1406	1411	10559	java/io/IOException
    //   1416	1421	10569	java/io/IOException
    //   1426	1431	10579	java/io/IOException
    //   1692	1697	10589	java/io/IOException
    //   1702	1707	10599	java/io/IOException
    //   1712	1717	10609	java/io/IOException
    //   1722	1727	10619	java/io/IOException
    //   1732	1737	10629	java/io/IOException
    //   649	657	10639	java/io/IOException
    //   661	669	10649	java/io/IOException
    //   673	681	10659	java/io/IOException
    //   685	693	10669	java/io/IOException
    //   697	705	10679	java/io/IOException
    //   3018	3026	10689	java/io/IOException
    //   3030	3038	10699	java/io/IOException
    //   3042	3050	10709	java/io/IOException
    //   3054	3062	10719	java/io/IOException
    //   3066	3074	10729	java/io/IOException
    //   3560	3568	10739	java/io/IOException
    //   3572	3580	10749	java/io/IOException
    //   3584	3592	10759	java/io/IOException
    //   3596	3604	10769	java/io/IOException
    //   3608	3616	10779	java/io/IOException
    //   3770	3778	10789	java/io/IOException
    //   3782	3790	10799	java/io/IOException
    //   3794	3802	10809	java/io/IOException
    //   3806	3814	10819	java/io/IOException
    //   3818	3826	10829	java/io/IOException
    //   5272	5280	10839	java/io/IOException
    //   5284	5292	10849	java/io/IOException
    //   5296	5304	10859	java/io/IOException
    //   5308	5316	10869	java/io/IOException
    //   5320	5328	10879	java/io/IOException
    //   9450	9455	10889	java/io/IOException
    //   9460	9465	10899	java/io/IOException
    //   9470	9475	10909	java/io/IOException
    //   9480	9485	10919	java/io/IOException
    //   9490	9495	10929	java/io/IOException
    //   8609	8614	10939	java/io/IOException
    //   8619	8624	10949	java/io/IOException
    //   8629	8634	10959	java/io/IOException
    //   8639	8644	10969	java/io/IOException
    //   8649	8654	10979	java/io/IOException
    //   10202	10207	10989	java/io/IOException
    //   10212	10217	10999	java/io/IOException
    //   10222	10227	11009	java/io/IOException
    //   10232	10237	11019	java/io/IOException
    //   10242	10247	11029	java/io/IOException
    //   1023	1031	11039	java/io/IOException
    //   1035	1043	11049	java/io/IOException
    //   1047	1055	11059	java/io/IOException
    //   1059	1067	11069	java/io/IOException
    //   1071	1079	11079	java/io/IOException
    //   158	168	11089	finally
    //   184	194	11089	finally
    //   210	219	11089	finally
    //   729	737	11089	finally
    //   765	778	11089	finally
    //   794	809	11089	finally
    //   836	863	11089	finally
    //   6651	6662	11114	finally
    //   6662	6673	11143	finally
    //   158	168	11172	java/lang/Exception
    //   184	194	11172	java/lang/Exception
    //   210	219	11172	java/lang/Exception
    //   729	737	11172	java/lang/Exception
    //   765	778	11172	java/lang/Exception
    //   794	809	11172	java/lang/Exception
    //   836	863	11172	java/lang/Exception
    //   249	260	11213	java/lang/Exception
    //   286	293	11213	java/lang/Exception
    //   319	325	11246	java/lang/Exception
    //   355	361	11246	java/lang/Exception
    //   387	398	11246	java/lang/Exception
    //   430	435	11246	java/lang/Exception
    //   895	905	11246	java/lang/Exception
    //   931	938	11246	java/lang/Exception
    //   964	969	11246	java/lang/Exception
    //   1113	1122	11246	java/lang/Exception
    //   1148	1162	11246	java/lang/Exception
    //   1460	1485	11246	java/lang/Exception
    //   1771	1776	11246	java/lang/Exception
    //   6651	6662	11274	java/lang/Exception
    //   6662	6673	11307	java/lang/Exception
    //   158	168	11340	java/io/FileNotFoundException
    //   184	194	11340	java/io/FileNotFoundException
    //   210	219	11340	java/io/FileNotFoundException
    //   729	737	11340	java/io/FileNotFoundException
    //   765	778	11340	java/io/FileNotFoundException
    //   794	809	11340	java/io/FileNotFoundException
    //   836	863	11340	java/io/FileNotFoundException
    //   6651	6662	11372	java/io/FileNotFoundException
    //   6662	6673	11401	java/io/FileNotFoundException
    //   158	168	11434	java/net/SocketTimeoutException
    //   184	194	11434	java/net/SocketTimeoutException
    //   210	219	11434	java/net/SocketTimeoutException
    //   729	737	11434	java/net/SocketTimeoutException
    //   765	778	11434	java/net/SocketTimeoutException
    //   794	809	11434	java/net/SocketTimeoutException
    //   836	863	11434	java/net/SocketTimeoutException
    //   249	260	11472	java/net/SocketTimeoutException
    //   286	293	11472	java/net/SocketTimeoutException
    //   6553	6569	11514	java/net/SocketTimeoutException
    //   6640	6651	11514	java/net/SocketTimeoutException
    //   8728	8739	11514	java/net/SocketTimeoutException
    //   6651	6662	11563	java/net/SocketTimeoutException
    //   6662	6673	11613	java/net/SocketTimeoutException
    //   6744	6751	11656	java/net/SocketTimeoutException
    //   6822	6832	11656	java/net/SocketTimeoutException
    //   6903	6912	11656	java/net/SocketTimeoutException
    //   8817	8826	11656	java/net/SocketTimeoutException
    //   509	516	11719	java/net/SocketTimeoutException
    //   590	595	11719	java/net/SocketTimeoutException
    //   1858	1871	11719	java/net/SocketTimeoutException
    //   1945	1967	11719	java/net/SocketTimeoutException
    //   2041	2051	11719	java/net/SocketTimeoutException
    //   2129	2139	11719	java/net/SocketTimeoutException
    //   2213	2232	11719	java/net/SocketTimeoutException
    //   2306	2316	11719	java/net/SocketTimeoutException
    //   2390	2402	11719	java/net/SocketTimeoutException
    //   2476	2503	11719	java/net/SocketTimeoutException
    //   2580	2591	11719	java/net/SocketTimeoutException
    //   2668	2674	11719	java/net/SocketTimeoutException
    //   2748	2757	11719	java/net/SocketTimeoutException
    //   2831	2834	11719	java/net/SocketTimeoutException
    //   2948	2964	11719	java/net/SocketTimeoutException
    //   3153	3156	11719	java/net/SocketTimeoutException
    //   3230	3233	11719	java/net/SocketTimeoutException
    //   3307	3320	11719	java/net/SocketTimeoutException
    //   3394	3409	11719	java/net/SocketTimeoutException
    //   3490	3506	11719	java/net/SocketTimeoutException
    //   3700	3716	11719	java/net/SocketTimeoutException
    //   3903	3913	11719	java/net/SocketTimeoutException
    //   3987	4002	11719	java/net/SocketTimeoutException
    //   4086	4096	11719	java/net/SocketTimeoutException
    //   4175	4183	11719	java/net/SocketTimeoutException
    //   4257	4269	11719	java/net/SocketTimeoutException
    //   4668	4678	11719	java/net/SocketTimeoutException
    //   4752	4768	11719	java/net/SocketTimeoutException
    //   4851	4868	11719	java/net/SocketTimeoutException
    //   4951	4965	11719	java/net/SocketTimeoutException
    //   5039	5058	11719	java/net/SocketTimeoutException
    //   5132	5138	11719	java/net/SocketTimeoutException
    //   5212	5218	11719	java/net/SocketTimeoutException
    //   5412	5422	11719	java/net/SocketTimeoutException
    //   5496	5510	11719	java/net/SocketTimeoutException
    //   5584	5594	11719	java/net/SocketTimeoutException
    //   5668	5687	11719	java/net/SocketTimeoutException
    //   5761	5770	11719	java/net/SocketTimeoutException
    //   5847	5855	11719	java/net/SocketTimeoutException
    //   5941	5950	11719	java/net/SocketTimeoutException
    //   6029	6038	11719	java/net/SocketTimeoutException
    //   6112	6122	11719	java/net/SocketTimeoutException
    //   6201	6221	11719	java/net/SocketTimeoutException
    //   6298	6303	11719	java/net/SocketTimeoutException
    //   6377	6389	11719	java/net/SocketTimeoutException
    //   6463	6477	11719	java/net/SocketTimeoutException
    //   509	516	11770	java/io/FileNotFoundException
    //   590	595	11770	java/io/FileNotFoundException
    //   1858	1871	11770	java/io/FileNotFoundException
    //   1945	1967	11770	java/io/FileNotFoundException
    //   2041	2051	11770	java/io/FileNotFoundException
    //   2129	2139	11770	java/io/FileNotFoundException
    //   2213	2232	11770	java/io/FileNotFoundException
    //   2306	2316	11770	java/io/FileNotFoundException
    //   2390	2402	11770	java/io/FileNotFoundException
    //   2476	2503	11770	java/io/FileNotFoundException
    //   2580	2591	11770	java/io/FileNotFoundException
    //   2668	2674	11770	java/io/FileNotFoundException
    //   2748	2757	11770	java/io/FileNotFoundException
    //   2831	2834	11770	java/io/FileNotFoundException
    //   2948	2964	11770	java/io/FileNotFoundException
    //   3153	3156	11770	java/io/FileNotFoundException
    //   3230	3233	11770	java/io/FileNotFoundException
    //   3307	3320	11770	java/io/FileNotFoundException
    //   3394	3409	11770	java/io/FileNotFoundException
    //   3490	3506	11770	java/io/FileNotFoundException
    //   3700	3716	11770	java/io/FileNotFoundException
    //   3903	3913	11770	java/io/FileNotFoundException
    //   3987	4002	11770	java/io/FileNotFoundException
    //   4086	4096	11770	java/io/FileNotFoundException
    //   4175	4183	11770	java/io/FileNotFoundException
    //   4257	4269	11770	java/io/FileNotFoundException
    //   4668	4678	11770	java/io/FileNotFoundException
    //   4752	4768	11770	java/io/FileNotFoundException
    //   4851	4868	11770	java/io/FileNotFoundException
    //   4951	4965	11770	java/io/FileNotFoundException
    //   5039	5058	11770	java/io/FileNotFoundException
    //   5132	5138	11770	java/io/FileNotFoundException
    //   5212	5218	11770	java/io/FileNotFoundException
    //   5412	5422	11770	java/io/FileNotFoundException
    //   5496	5510	11770	java/io/FileNotFoundException
    //   5584	5594	11770	java/io/FileNotFoundException
    //   5668	5687	11770	java/io/FileNotFoundException
    //   5761	5770	11770	java/io/FileNotFoundException
    //   5847	5855	11770	java/io/FileNotFoundException
    //   5941	5950	11770	java/io/FileNotFoundException
    //   6029	6038	11770	java/io/FileNotFoundException
    //   6112	6122	11770	java/io/FileNotFoundException
    //   6201	6221	11770	java/io/FileNotFoundException
    //   6298	6303	11770	java/io/FileNotFoundException
    //   6377	6389	11770	java/io/FileNotFoundException
    //   6463	6477	11770	java/io/FileNotFoundException
    //   6553	6569	11770	java/io/FileNotFoundException
    //   6640	6651	11770	java/io/FileNotFoundException
    //   6744	6751	11770	java/io/FileNotFoundException
    //   6822	6832	11770	java/io/FileNotFoundException
    //   6903	6912	11770	java/io/FileNotFoundException
    //   6987	6998	11770	java/io/FileNotFoundException
    //   7069	7079	11770	java/io/FileNotFoundException
    //   7150	7157	11770	java/io/FileNotFoundException
    //   7228	7252	11770	java/io/FileNotFoundException
    //   7326	7339	11770	java/io/FileNotFoundException
    //   7416	7419	11770	java/io/FileNotFoundException
    //   7516	7519	11770	java/io/FileNotFoundException
    //   7617	7627	11770	java/io/FileNotFoundException
    //   7698	7707	11770	java/io/FileNotFoundException
    //   7760	7766	11770	java/io/FileNotFoundException
    //   7837	7843	11770	java/io/FileNotFoundException
    //   7914	7928	11770	java/io/FileNotFoundException
    //   8003	8010	11770	java/io/FileNotFoundException
    //   8085	8099	11770	java/io/FileNotFoundException
    //   8170	8194	11770	java/io/FileNotFoundException
    //   8280	8287	11770	java/io/FileNotFoundException
    //   8366	8376	11770	java/io/FileNotFoundException
    //   8447	8450	11770	java/io/FileNotFoundException
    //   8549	8554	11770	java/io/FileNotFoundException
    //   8728	8739	11770	java/io/FileNotFoundException
    //   8817	8826	11770	java/io/FileNotFoundException
    //   8906	8909	11770	java/io/FileNotFoundException
    //   8980	8983	11770	java/io/FileNotFoundException
    //   9056	9059	11770	java/io/FileNotFoundException
    //   9130	9133	11770	java/io/FileNotFoundException
    //   9206	9211	11770	java/io/FileNotFoundException
    //   9282	9285	11770	java/io/FileNotFoundException
    //   9384	9395	11770	java/io/FileNotFoundException
    //   9571	9574	11770	java/io/FileNotFoundException
    //   9645	9648	11770	java/io/FileNotFoundException
    //   9721	9724	11770	java/io/FileNotFoundException
    //   9795	9798	11770	java/io/FileNotFoundException
    //   9869	9879	11770	java/io/FileNotFoundException
    //   9950	9957	11770	java/io/FileNotFoundException
    //   10028	10031	11770	java/io/FileNotFoundException
    //   10130	10147	11770	java/io/FileNotFoundException
    //   10329	10332	11770	java/io/FileNotFoundException
    //   10403	10406	11770	java/io/FileNotFoundException
    //   6987	6998	11812	java/net/SocketTimeoutException
    //   7069	7079	11812	java/net/SocketTimeoutException
    //   7150	7157	11812	java/net/SocketTimeoutException
    //   7228	7252	11812	java/net/SocketTimeoutException
    //   7326	7339	11812	java/net/SocketTimeoutException
    //   7416	7419	11812	java/net/SocketTimeoutException
    //   7516	7519	11812	java/net/SocketTimeoutException
    //   7617	7627	11812	java/net/SocketTimeoutException
    //   7698	7707	11812	java/net/SocketTimeoutException
    //   7760	7766	11812	java/net/SocketTimeoutException
    //   7837	7843	11812	java/net/SocketTimeoutException
    //   7914	7928	11812	java/net/SocketTimeoutException
    //   8003	8010	11812	java/net/SocketTimeoutException
    //   8085	8099	11812	java/net/SocketTimeoutException
    //   8170	8194	11812	java/net/SocketTimeoutException
    //   8280	8287	11812	java/net/SocketTimeoutException
    //   8366	8376	11812	java/net/SocketTimeoutException
    //   8447	8450	11812	java/net/SocketTimeoutException
    //   8549	8554	11812	java/net/SocketTimeoutException
    //   8906	8909	11812	java/net/SocketTimeoutException
    //   8980	8983	11812	java/net/SocketTimeoutException
    //   9056	9059	11812	java/net/SocketTimeoutException
    //   9130	9133	11812	java/net/SocketTimeoutException
    //   9206	9211	11812	java/net/SocketTimeoutException
    //   9282	9285	11812	java/net/SocketTimeoutException
    //   9384	9395	11812	java/net/SocketTimeoutException
    //   9571	9574	11812	java/net/SocketTimeoutException
    //   9645	9648	11812	java/net/SocketTimeoutException
    //   9721	9724	11812	java/net/SocketTimeoutException
    //   9795	9798	11812	java/net/SocketTimeoutException
    //   9869	9879	11812	java/net/SocketTimeoutException
    //   9950	9957	11812	java/net/SocketTimeoutException
    //   10028	10031	11812	java/net/SocketTimeoutException
    //   10130	10147	11812	java/net/SocketTimeoutException
    //   10329	10332	11812	java/net/SocketTimeoutException
    //   10403	10406	11812	java/net/SocketTimeoutException
  }
  
  public void a()
  {
    this.r = true;
  }
  
  public void a(h paramh)
  {
    if (this.v != null) {
      this.v.a(paramh);
    }
  }
  
  public void a(i parami)
  {
    this.v = parami;
  }
  
  protected void a(HttpClient paramHttpClient)
  {
    if ((paramHttpClient instanceof DefaultHttpClient)) {
      ((DefaultHttpClient)paramHttpClient).setCookieStore(new PersistentCookieStore(MunionConfigManager.getInstance().getContext()));
    }
  }
  
  /* Error */
  public h b()
  {
    // Byte code:
    //   0: iconst_0
    //   1: istore_1
    //   2: invokestatic 200	com/taobao/munion/net/f:a	()Lcom/taobao/munion/net/f;
    //   5: getfield 601	com/taobao/munion/net/f:d	Landroid/content/Context;
    //   8: ifnull +29 -> 37
    //   11: invokestatic 200	com/taobao/munion/net/f:a	()Lcom/taobao/munion/net/f;
    //   14: getfield 601	com/taobao/munion/net/f:d	Landroid/content/Context;
    //   17: invokestatic 604	com/taobao/munion/utils/m:a	(Landroid/content/Context;)Z
    //   20: ifne +17 -> 37
    //   23: new 227	com/taobao/munion/net/h
    //   26: dup
    //   27: bipush -4
    //   29: invokespecial 564	com/taobao/munion/net/h:<init>	(I)V
    //   32: astore 5
    //   34: aload 5
    //   36: areturn
    //   37: aload_0
    //   38: iconst_0
    //   39: putfield 225	com/taobao/munion/net/b:r	Z
    //   42: aload_0
    //   43: iconst_0
    //   44: putfield 65	com/taobao/munion/net/b:s	I
    //   47: ldc_w 571
    //   50: astore 5
    //   52: aconst_null
    //   53: astore 4
    //   55: aload 5
    //   57: astore 6
    //   59: iload_1
    //   60: aload_0
    //   61: getfield 87	com/taobao/munion/net/b:p	Lcom/taobao/munion/net/e;
    //   64: getfield 606	com/taobao/munion/net/e:f	I
    //   67: if_icmpge +141 -> 208
    //   70: aload_0
    //   71: getfield 225	com/taobao/munion/net/b:r	Z
    //   74: ifeq +7 -> 81
    //   77: getstatic 230	com/taobao/munion/net/h:h	Lcom/taobao/munion/net/h;
    //   80: areturn
    //   81: aload_0
    //   82: getfield 85	com/taobao/munion/net/b:q	Ljava/lang/String;
    //   85: astore 4
    //   87: aload 4
    //   89: ifnull +12 -> 101
    //   92: aload 4
    //   94: invokevirtual 271	java/lang/String:length	()I
    //   97: iconst_5
    //   98: if_icmpgt +7 -> 105
    //   101: getstatic 608	com/taobao/munion/net/h:i	Lcom/taobao/munion/net/h;
    //   104: areturn
    //   105: aload_0
    //   106: invokespecial 483	com/taobao/munion/net/b:e	()Lcom/taobao/munion/net/h;
    //   109: astore 4
    //   111: aload 4
    //   113: areturn
    //   114: astore 6
    //   116: aload 6
    //   118: invokevirtual 609	com/taobao/munion/net/b$d:getMessage	()Ljava/lang/String;
    //   121: astore 5
    //   123: aload 6
    //   125: invokevirtual 610	com/taobao/munion/net/b$d:printStackTrace	()V
    //   128: new 227	com/taobao/munion/net/h
    //   131: dup
    //   132: bipush -4
    //   134: aload 6
    //   136: invokevirtual 609	com/taobao/munion/net/b$d:getMessage	()Ljava/lang/String;
    //   139: aconst_null
    //   140: invokespecial 336	com/taobao/munion/net/h:<init>	(ILjava/lang/String;[B)V
    //   143: astore 4
    //   145: aload 4
    //   147: aload 6
    //   149: getfield 611	com/taobao/munion/net/b$d:a	I
    //   152: putfield 613	com/taobao/munion/net/h:g	I
    //   155: iload_1
    //   156: iconst_1
    //   157: iadd
    //   158: iconst_2
    //   159: imul
    //   160: sipush 1000
    //   163: imul
    //   164: i2l
    //   165: lstore_2
    //   166: lload_2
    //   167: invokestatic 557	java/lang/Thread:sleep	(J)V
    //   170: iload_1
    //   171: iconst_1
    //   172: iadd
    //   173: istore_1
    //   174: goto -119 -> 55
    //   177: astore 4
    //   179: aload 4
    //   181: invokevirtual 614	com/taobao/munion/net/b$c:getMessage	()Ljava/lang/String;
    //   184: astore 6
    //   186: aload 4
    //   188: invokevirtual 615	com/taobao/munion/net/b$c:printStackTrace	()V
    //   191: new 227	com/taobao/munion/net/h
    //   194: dup
    //   195: bipush -4
    //   197: aload 4
    //   199: invokevirtual 614	com/taobao/munion/net/b$c:getMessage	()Ljava/lang/String;
    //   202: aconst_null
    //   203: invokespecial 336	com/taobao/munion/net/h:<init>	(ILjava/lang/String;[B)V
    //   206: astore 4
    //   208: iload_1
    //   209: aload_0
    //   210: getfield 87	com/taobao/munion/net/b:p	Lcom/taobao/munion/net/e;
    //   213: getfield 606	com/taobao/munion/net/e:f	I
    //   216: if_icmplt +21 -> 237
    //   219: new 617	com/taobao/munion/net/b$g
    //   222: dup
    //   223: aload_0
    //   224: aload 6
    //   226: invokespecial 618	com/taobao/munion/net/b$g:<init>	(Lcom/taobao/munion/net/b;Ljava/lang/String;)V
    //   229: athrow
    //   230: astore 5
    //   232: aload 5
    //   234: invokevirtual 619	java/lang/Exception:printStackTrace	()V
    //   237: aload 4
    //   239: astore 5
    //   241: aload 4
    //   243: ifnonnull -209 -> 34
    //   246: new 227	com/taobao/munion/net/h
    //   249: dup
    //   250: sipush 64536
    //   253: ldc_w 571
    //   256: aconst_null
    //   257: invokespecial 336	com/taobao/munion/net/h:<init>	(ILjava/lang/String;[B)V
    //   260: areturn
    //   261: astore 4
    //   263: aload 4
    //   265: invokevirtual 620	com/taobao/munion/net/b$e:printStackTrace	()V
    //   268: new 227	com/taobao/munion/net/h
    //   271: dup
    //   272: bipush -6
    //   274: aload 4
    //   276: invokevirtual 621	com/taobao/munion/net/b$e:getMessage	()Ljava/lang/String;
    //   279: aconst_null
    //   280: invokespecial 336	com/taobao/munion/net/h:<init>	(ILjava/lang/String;[B)V
    //   283: astore 4
    //   285: aload 5
    //   287: astore 6
    //   289: goto -81 -> 208
    //   292: astore 4
    //   294: aload 4
    //   296: invokevirtual 622	com/taobao/munion/net/b$h:printStackTrace	()V
    //   299: new 227	com/taobao/munion/net/h
    //   302: dup
    //   303: bipush -5
    //   305: aload 4
    //   307: invokevirtual 623	com/taobao/munion/net/b$h:getMessage	()Ljava/lang/String;
    //   310: aconst_null
    //   311: invokespecial 336	com/taobao/munion/net/h:<init>	(ILjava/lang/String;[B)V
    //   314: astore 4
    //   316: aload 5
    //   318: astore 6
    //   320: goto -112 -> 208
    //   323: astore 6
    //   325: goto -155 -> 170
    // Local variable table:
    //   start	length	slot	name	signature
    //   0	328	0	this	b
    //   1	216	1	i1	int
    //   165	2	2	l1	long
    //   53	93	4	localObject1	Object
    //   177	21	4	localc	b.c
    //   206	36	4	localh1	h
    //   261	14	4	locale	b.e
    //   283	1	4	localh2	h
    //   292	14	4	localh	b.h
    //   314	1	4	localh3	h
    //   32	90	5	localObject2	Object
    //   230	3	5	localException	Exception
    //   239	78	5	localObject3	Object
    //   57	1	6	localObject4	Object
    //   114	34	6	locald	b.d
    //   184	135	6	localObject5	Object
    //   323	1	6	localInterruptedException	InterruptedException
    // Exception table:
    //   from	to	target	type
    //   105	111	114	com/taobao/munion/net/b$d
    //   105	111	177	com/taobao/munion/net/b$c
    //   219	230	230	java/lang/Exception
    //   105	111	261	com/taobao/munion/net/b$e
    //   105	111	292	com/taobao/munion/net/b$h
    //   166	170	323	java/lang/InterruptedException
  }
  
  e c()
  {
    return this.p;
  }
}


/* Location:              E:\project\angent\dex2jar-2.0\classes-dex2jar.jar!\com\taobao\munion\net\b.class
 * Java compiler version: 6 (50.0)
 * JD-Core Version:       0.7.1
 */