package com.taobao.munion.requests;

import com.taobao.munion.net.p;

public class e
  extends p
{
  /* Error */
  public e(com.taobao.munion.model.b paramb, com.taobao.munion.model.c paramc)
  {
    // Byte code:
    //   0: aload_0
    //   1: invokespecial 11	com/taobao/munion/net/p:<init>	()V
    //   4: aload_0
    //   5: ldc 13
    //   7: getstatic 18	com/umeng/newxp/common/ExchangeConstants:sdk_version	Ljava/lang/String;
    //   10: invokevirtual 22	com/taobao/munion/requests/e:a	(Ljava/lang/String;Ljava/lang/String;)V
    //   13: aload_0
    //   14: ldc 24
    //   16: getstatic 26	com/umeng/newxp/common/ExchangeConstants:protocol_version	Ljava/lang/String;
    //   19: invokevirtual 22	com/taobao/munion/requests/e:a	(Ljava/lang/String;Ljava/lang/String;)V
    //   22: aload_1
    //   23: invokevirtual 31	com/taobao/munion/model/b:a	()Ljava/lang/String;
    //   26: invokestatic 37	com/umeng/common/ufp/util/g:d	(Ljava/lang/String;)Z
    //   29: ifne +170 -> 199
    //   32: aload_0
    //   33: ldc 39
    //   35: aload_1
    //   36: invokevirtual 31	com/taobao/munion/model/b:a	()Ljava/lang/String;
    //   39: invokevirtual 22	com/taobao/munion/requests/e:a	(Ljava/lang/String;Ljava/lang/String;)V
    //   42: invokestatic 45	com/taobao/munion/common/MunionConfigManager:getInstance	()Lcom/taobao/munion/common/MunionConfigManager;
    //   45: invokevirtual 49	com/taobao/munion/common/MunionConfigManager:getContext	()Landroid/content/Context;
    //   48: invokestatic 55	com/umeng/newxp/common/c:K	(Landroid/content/Context;)Ljava/lang/String;
    //   51: invokestatic 61	android/text/TextUtils:isEmpty	(Ljava/lang/CharSequence;)Z
    //   54: ifne +18 -> 72
    //   57: aload_0
    //   58: ldc 63
    //   60: invokestatic 45	com/taobao/munion/common/MunionConfigManager:getInstance	()Lcom/taobao/munion/common/MunionConfigManager;
    //   63: invokevirtual 49	com/taobao/munion/common/MunionConfigManager:getContext	()Landroid/content/Context;
    //   66: invokestatic 55	com/umeng/newxp/common/c:K	(Landroid/content/Context;)Ljava/lang/String;
    //   69: invokevirtual 22	com/taobao/munion/requests/e:a	(Ljava/lang/String;Ljava/lang/String;)V
    //   72: aload_0
    //   73: ldc 65
    //   75: aload_1
    //   76: invokevirtual 69	com/taobao/munion/model/b:f	()I
    //   79: i2l
    //   80: invokevirtual 72	com/taobao/munion/requests/e:a	(Ljava/lang/String;J)V
    //   83: aload_2
    //   84: invokevirtual 77	com/taobao/munion/model/c:e	()Ljava/lang/String;
    //   87: ifnull +28 -> 115
    //   90: ldc 79
    //   92: aload_2
    //   93: invokevirtual 77	com/taobao/munion/model/c:e	()Ljava/lang/String;
    //   96: invokevirtual 85	java/lang/String:equals	(Ljava/lang/Object;)Z
    //   99: ifne +16 -> 115
    //   102: aload_0
    //   103: ldc 87
    //   105: aload_2
    //   106: invokevirtual 77	com/taobao/munion/model/c:e	()Ljava/lang/String;
    //   109: invokestatic 90	com/umeng/newxp/common/c:d	(Ljava/lang/String;)Ljava/lang/String;
    //   112: invokevirtual 22	com/taobao/munion/requests/e:a	(Ljava/lang/String;Ljava/lang/String;)V
    //   115: aload_1
    //   116: getfield 93	com/taobao/munion/model/b:n	Ljava/lang/String;
    //   119: invokestatic 61	android/text/TextUtils:isEmpty	(Ljava/lang/CharSequence;)Z
    //   122: ifne +206 -> 328
    //   125: aload_1
    //   126: getfield 93	com/taobao/munion/model/b:n	Ljava/lang/String;
    //   129: ldc 95
    //   131: invokevirtual 99	java/lang/String:split	(Ljava/lang/String;)[Ljava/lang/String;
    //   134: astore 8
    //   136: new 101	java/util/HashMap
    //   139: dup
    //   140: invokespecial 102	java/util/HashMap:<init>	()V
    //   143: astore 7
    //   145: aload 8
    //   147: arraylength
    //   148: istore 4
    //   150: iconst_0
    //   151: istore_3
    //   152: iload_3
    //   153: iload 4
    //   155: if_icmpge +114 -> 269
    //   158: aload 8
    //   160: iload_3
    //   161: aaload
    //   162: ldc 104
    //   164: invokevirtual 99	java/lang/String:split	(Ljava/lang/String;)[Ljava/lang/String;
    //   167: astore 9
    //   169: aload 9
    //   171: arraylength
    //   172: iconst_2
    //   173: if_icmpne +19 -> 192
    //   176: aload 7
    //   178: aload 9
    //   180: iconst_0
    //   181: aaload
    //   182: aload 9
    //   184: iconst_1
    //   185: aaload
    //   186: invokeinterface 110 3 0
    //   191: pop
    //   192: iload_3
    //   193: iconst_1
    //   194: iadd
    //   195: istore_3
    //   196: goto -44 -> 152
    //   199: invokestatic 45	com/taobao/munion/common/MunionConfigManager:getInstance	()Lcom/taobao/munion/common/MunionConfigManager;
    //   202: invokevirtual 49	com/taobao/munion/common/MunionConfigManager:getContext	()Landroid/content/Context;
    //   205: aconst_null
    //   206: invokestatic 113	com/umeng/newxp/common/c:a	(Landroid/content/Context;Lcom/umeng/newxp/controller/ExchangeDataService;)Ljava/lang/String;
    //   209: astore 7
    //   211: aload 7
    //   213: invokestatic 37	com/umeng/common/ufp/util/g:d	(Ljava/lang/String;)Z
    //   216: ifne +42 -> 258
    //   219: aload_0
    //   220: ldc 115
    //   222: aload 7
    //   224: invokevirtual 22	com/taobao/munion/requests/e:a	(Ljava/lang/String;Ljava/lang/String;)V
    //   227: goto -185 -> 42
    //   230: astore_1
    //   231: aload_1
    //   232: invokevirtual 118	java/lang/Exception:printStackTrace	()V
    //   235: new 120	java/lang/StringBuilder
    //   238: dup
    //   239: ldc 122
    //   241: invokespecial 125	java/lang/StringBuilder:<init>	(Ljava/lang/String;)V
    //   244: aload_1
    //   245: invokevirtual 128	java/lang/Exception:toString	()Ljava/lang/String;
    //   248: invokevirtual 132	java/lang/StringBuilder:append	(Ljava/lang/String;)Ljava/lang/StringBuilder;
    //   251: invokevirtual 133	java/lang/StringBuilder:toString	()Ljava/lang/String;
    //   254: invokestatic 138	com/taobao/munion/utils/k:b	(Ljava/lang/String;)V
    //   257: return
    //   258: getstatic 141	com/umeng/newxp/common/ExchangeConstants:LOG_TAG	Ljava/lang/String;
    //   261: ldc -113
    //   263: invokestatic 147	com/umeng/common/ufp/Log:b	(Ljava/lang/String;Ljava/lang/String;)V
    //   266: goto -224 -> 42
    //   269: aload 7
    //   271: invokeinterface 151 1 0
    //   276: invokeinterface 157 1 0
    //   281: astore 8
    //   283: aload 8
    //   285: invokeinterface 163 1 0
    //   290: ifeq +38 -> 328
    //   293: aload 8
    //   295: invokeinterface 167 1 0
    //   300: checkcast 81	java/lang/String
    //   303: astore 9
    //   305: aload_0
    //   306: aload 9
    //   308: aload 7
    //   310: aload 9
    //   312: invokeinterface 171 2 0
    //   317: checkcast 81	java/lang/String
    //   320: invokevirtual 22	com/taobao/munion/requests/e:a	(Ljava/lang/String;Ljava/lang/String;)V
    //   323: goto -40 -> 283
    //   326: astore 7
    //   328: aload_2
    //   329: invokevirtual 173	com/taobao/munion/model/c:d	()Ljava/lang/String;
    //   332: astore 7
    //   334: aload 7
    //   336: invokestatic 61	android/text/TextUtils:isEmpty	(Ljava/lang/CharSequence;)Z
    //   339: ifne +11 -> 350
    //   342: aload_0
    //   343: ldc -81
    //   345: aload 7
    //   347: invokevirtual 22	com/taobao/munion/requests/e:a	(Ljava/lang/String;Ljava/lang/String;)V
    //   350: aload_2
    //   351: invokevirtual 178	com/taobao/munion/model/c:h	()Ljava/lang/String;
    //   354: invokestatic 37	com/umeng/common/ufp/util/g:d	(Ljava/lang/String;)Z
    //   357: ifne +13 -> 370
    //   360: aload_0
    //   361: ldc -76
    //   363: aload_2
    //   364: invokevirtual 178	com/taobao/munion/model/c:h	()Ljava/lang/String;
    //   367: invokevirtual 22	com/taobao/munion/requests/e:a	(Ljava/lang/String;Ljava/lang/String;)V
    //   370: aload_1
    //   371: getfield 182	com/taobao/munion/model/b:e	Ljava/lang/String;
    //   374: invokestatic 61	android/text/TextUtils:isEmpty	(Ljava/lang/CharSequence;)Z
    //   377: ifne +13 -> 390
    //   380: aload_0
    //   381: ldc -72
    //   383: aload_1
    //   384: getfield 182	com/taobao/munion/model/b:e	Ljava/lang/String;
    //   387: invokevirtual 22	com/taobao/munion/requests/e:a	(Ljava/lang/String;Ljava/lang/String;)V
    //   390: getstatic 188	com/umeng/newxp/common/ExchangeConstants:DETAIL_PAGE	Z
    //   393: ifeq +560 -> 953
    //   396: iconst_1
    //   397: istore_3
    //   398: aload_0
    //   399: ldc -66
    //   401: iload_3
    //   402: i2l
    //   403: invokevirtual 72	com/taobao/munion/requests/e:a	(Ljava/lang/String;J)V
    //   406: aload_0
    //   407: ldc -64
    //   409: lconst_1
    //   410: invokevirtual 72	com/taobao/munion/requests/e:a	(Ljava/lang/String;J)V
    //   413: aload_0
    //   414: ldc -62
    //   416: ldc -60
    //   418: invokevirtual 22	com/taobao/munion/requests/e:a	(Ljava/lang/String;Ljava/lang/String;)V
    //   421: aload_0
    //   422: ldc -58
    //   424: ldc -56
    //   426: invokevirtual 22	com/taobao/munion/requests/e:a	(Ljava/lang/String;Ljava/lang/String;)V
    //   429: aload_0
    //   430: ldc -54
    //   432: invokestatic 45	com/taobao/munion/common/MunionConfigManager:getInstance	()Lcom/taobao/munion/common/MunionConfigManager;
    //   435: invokevirtual 49	com/taobao/munion/common/MunionConfigManager:getContext	()Landroid/content/Context;
    //   438: invokestatic 207	com/umeng/newxp/common/b/a:a	(Landroid/content/Context;)Lcom/umeng/newxp/common/b/a;
    //   441: invokevirtual 208	com/umeng/newxp/common/b/a:a	()Ljava/lang/String;
    //   444: invokevirtual 22	com/taobao/munion/requests/e:a	(Ljava/lang/String;Ljava/lang/String;)V
    //   447: invokestatic 45	com/taobao/munion/common/MunionConfigManager:getInstance	()Lcom/taobao/munion/common/MunionConfigManager;
    //   450: invokevirtual 49	com/taobao/munion/common/MunionConfigManager:getContext	()Landroid/content/Context;
    //   453: invokestatic 213	com/umeng/common/ufp/b:q	(Landroid/content/Context;)Ljava/lang/String;
    //   456: astore_1
    //   457: aload_0
    //   458: ldc -41
    //   460: aload_1
    //   461: invokevirtual 22	com/taobao/munion/requests/e:a	(Ljava/lang/String;Ljava/lang/String;)V
    //   464: aload_0
    //   465: ldc -39
    //   467: aload_1
    //   468: invokestatic 219	com/umeng/common/ufp/util/g:a	(Ljava/lang/String;)Ljava/lang/String;
    //   471: invokevirtual 22	com/taobao/munion/requests/e:a	(Ljava/lang/String;Ljava/lang/String;)V
    //   474: aload_0
    //   475: ldc -35
    //   477: getstatic 226	android/os/Build:MODEL	Ljava/lang/String;
    //   480: invokevirtual 22	com/taobao/munion/requests/e:a	(Ljava/lang/String;Ljava/lang/String;)V
    //   483: aload_0
    //   484: ldc -28
    //   486: ldc -26
    //   488: invokevirtual 22	com/taobao/munion/requests/e:a	(Ljava/lang/String;Ljava/lang/String;)V
    //   491: invokestatic 45	com/taobao/munion/common/MunionConfigManager:getInstance	()Lcom/taobao/munion/common/MunionConfigManager;
    //   494: invokevirtual 49	com/taobao/munion/common/MunionConfigManager:getContext	()Landroid/content/Context;
    //   497: invokestatic 233	com/umeng/common/ufp/b:D	(Landroid/content/Context;)Ljava/lang/String;
    //   500: astore_1
    //   501: aload_1
    //   502: invokestatic 61	android/text/TextUtils:isEmpty	(Ljava/lang/CharSequence;)Z
    //   505: ifne +10 -> 515
    //   508: aload_0
    //   509: ldc -21
    //   511: aload_1
    //   512: invokevirtual 22	com/taobao/munion/requests/e:a	(Ljava/lang/String;Ljava/lang/String;)V
    //   515: aload_0
    //   516: ldc -19
    //   518: getstatic 242	android/os/Build$VERSION:RELEASE	Ljava/lang/String;
    //   521: invokevirtual 22	com/taobao/munion/requests/e:a	(Ljava/lang/String;Ljava/lang/String;)V
    //   524: invokestatic 45	com/taobao/munion/common/MunionConfigManager:getInstance	()Lcom/taobao/munion/common/MunionConfigManager;
    //   527: invokevirtual 49	com/taobao/munion/common/MunionConfigManager:getContext	()Landroid/content/Context;
    //   530: invokevirtual 248	android/content/Context:getResources	()Landroid/content/res/Resources;
    //   533: invokevirtual 254	android/content/res/Resources:getConfiguration	()Landroid/content/res/Configuration;
    //   536: astore_1
    //   537: aload_1
    //   538: ifnull +378 -> 916
    //   541: aload_1
    //   542: getfield 260	android/content/res/Configuration:locale	Ljava/util/Locale;
    //   545: ifnull +371 -> 916
    //   548: aload_0
    //   549: ldc_w 261
    //   552: aload_1
    //   553: getfield 260	android/content/res/Configuration:locale	Ljava/util/Locale;
    //   556: invokevirtual 266	java/util/Locale:getDisplayName	()Ljava/lang/String;
    //   559: invokevirtual 22	com/taobao/munion/requests/e:a	(Ljava/lang/String;Ljava/lang/String;)V
    //   562: aload_0
    //   563: ldc_w 268
    //   566: aload_1
    //   567: getfield 260	android/content/res/Configuration:locale	Ljava/util/Locale;
    //   570: invokevirtual 269	java/util/Locale:toString	()Ljava/lang/String;
    //   573: invokevirtual 22	com/taobao/munion/requests/e:a	(Ljava/lang/String;Ljava/lang/String;)V
    //   576: aload_0
    //   577: ldc_w 271
    //   580: invokestatic 45	com/taobao/munion/common/MunionConfigManager:getInstance	()Lcom/taobao/munion/common/MunionConfigManager;
    //   583: invokevirtual 49	com/taobao/munion/common/MunionConfigManager:getContext	()Landroid/content/Context;
    //   586: invokestatic 275	com/umeng/common/ufp/b:A	(Landroid/content/Context;)I
    //   589: i2l
    //   590: invokevirtual 72	com/taobao/munion/requests/e:a	(Ljava/lang/String;J)V
    //   593: aload_0
    //   594: ldc_w 277
    //   597: invokestatic 45	com/taobao/munion/common/MunionConfigManager:getInstance	()Lcom/taobao/munion/common/MunionConfigManager;
    //   600: invokevirtual 49	com/taobao/munion/common/MunionConfigManager:getContext	()Landroid/content/Context;
    //   603: invokestatic 280	com/umeng/common/ufp/b:v	(Landroid/content/Context;)Ljava/lang/String;
    //   606: invokevirtual 22	com/taobao/munion/requests/e:a	(Ljava/lang/String;Ljava/lang/String;)V
    //   609: invokestatic 45	com/taobao/munion/common/MunionConfigManager:getInstance	()Lcom/taobao/munion/common/MunionConfigManager;
    //   612: invokevirtual 49	com/taobao/munion/common/MunionConfigManager:getContext	()Landroid/content/Context;
    //   615: invokestatic 284	com/umeng/common/ufp/b:w	(Landroid/content/Context;)[Ljava/lang/String;
    //   618: astore_1
    //   619: aload_0
    //   620: ldc_w 286
    //   623: aload_1
    //   624: iconst_0
    //   625: aaload
    //   626: invokevirtual 22	com/taobao/munion/requests/e:a	(Ljava/lang/String;Ljava/lang/String;)V
    //   629: ldc_w 288
    //   632: aload_1
    //   633: iconst_0
    //   634: aaload
    //   635: invokevirtual 85	java/lang/String:equals	(Ljava/lang/Object;)Z
    //   638: ifeq +13 -> 651
    //   641: aload_0
    //   642: ldc_w 290
    //   645: aload_1
    //   646: iconst_1
    //   647: aaload
    //   648: invokevirtual 22	com/taobao/munion/requests/e:a	(Ljava/lang/String;Ljava/lang/String;)V
    //   651: aload_0
    //   652: ldc_w 292
    //   655: invokestatic 45	com/taobao/munion/common/MunionConfigManager:getInstance	()Lcom/taobao/munion/common/MunionConfigManager;
    //   658: invokevirtual 49	com/taobao/munion/common/MunionConfigManager:getContext	()Landroid/content/Context;
    //   661: invokestatic 295	com/umeng/common/ufp/b:s	(Landroid/content/Context;)Ljava/lang/String;
    //   664: invokevirtual 22	com/taobao/munion/requests/e:a	(Ljava/lang/String;Ljava/lang/String;)V
    //   667: invokestatic 45	com/taobao/munion/common/MunionConfigManager:getInstance	()Lcom/taobao/munion/common/MunionConfigManager;
    //   670: invokevirtual 49	com/taobao/munion/common/MunionConfigManager:getContext	()Landroid/content/Context;
    //   673: invokestatic 299	com/umeng/common/ufp/b:y	(Landroid/content/Context;)Landroid/location/Location;
    //   676: astore_1
    //   677: aload_1
    //   678: ifnull +60 -> 738
    //   681: aload_0
    //   682: ldc_w 301
    //   685: aload_1
    //   686: invokevirtual 307	android/location/Location:getLatitude	()D
    //   689: invokestatic 311	java/lang/String:valueOf	(D)Ljava/lang/String;
    //   692: invokevirtual 22	com/taobao/munion/requests/e:a	(Ljava/lang/String;Ljava/lang/String;)V
    //   695: aload_0
    //   696: ldc_w 313
    //   699: aload_1
    //   700: invokevirtual 316	android/location/Location:getLongitude	()D
    //   703: invokestatic 311	java/lang/String:valueOf	(D)Ljava/lang/String;
    //   706: invokevirtual 22	com/taobao/munion/requests/e:a	(Ljava/lang/String;Ljava/lang/String;)V
    //   709: aload_1
    //   710: invokevirtual 320	android/location/Location:getTime	()J
    //   713: lstore 5
    //   715: aload_0
    //   716: ldc_w 322
    //   719: aload_1
    //   720: invokevirtual 325	android/location/Location:getProvider	()Ljava/lang/String;
    //   723: invokevirtual 22	com/taobao/munion/requests/e:a	(Ljava/lang/String;Ljava/lang/String;)V
    //   726: aload_0
    //   727: ldc_w 327
    //   730: lload 5
    //   732: invokestatic 330	java/lang/String:valueOf	(J)Ljava/lang/String;
    //   735: invokevirtual 22	com/taobao/munion/requests/e:a	(Ljava/lang/String;Ljava/lang/String;)V
    //   738: aload_0
    //   739: ldc_w 332
    //   742: invokestatic 334	com/umeng/common/ufp/b:f	()Ljava/lang/String;
    //   745: invokevirtual 22	com/taobao/munion/requests/e:a	(Ljava/lang/String;Ljava/lang/String;)V
    //   748: invokestatic 335	com/umeng/common/ufp/util/g:a	()Ljava/lang/String;
    //   751: astore_2
    //   752: aload_2
    //   753: ldc_w 337
    //   756: invokevirtual 99	java/lang/String:split	(Ljava/lang/String;)[Ljava/lang/String;
    //   759: iconst_0
    //   760: aaload
    //   761: astore_1
    //   762: aload_2
    //   763: ldc_w 337
    //   766: invokevirtual 99	java/lang/String:split	(Ljava/lang/String;)[Ljava/lang/String;
    //   769: iconst_1
    //   770: aaload
    //   771: astore_2
    //   772: aload_0
    //   773: ldc_w 339
    //   776: aload_1
    //   777: invokevirtual 22	com/taobao/munion/requests/e:a	(Ljava/lang/String;Ljava/lang/String;)V
    //   780: aload_0
    //   781: ldc_w 341
    //   784: aload_2
    //   785: invokevirtual 22	com/taobao/munion/requests/e:a	(Ljava/lang/String;Ljava/lang/String;)V
    //   788: aload_0
    //   789: ldc_w 343
    //   792: getstatic 346	android/os/Build:MANUFACTURER	Ljava/lang/String;
    //   795: invokevirtual 22	com/taobao/munion/requests/e:a	(Ljava/lang/String;Ljava/lang/String;)V
    //   798: aload_0
    //   799: ldc_w 271
    //   802: invokestatic 45	com/taobao/munion/common/MunionConfigManager:getInstance	()Lcom/taobao/munion/common/MunionConfigManager;
    //   805: invokevirtual 49	com/taobao/munion/common/MunionConfigManager:getContext	()Landroid/content/Context;
    //   808: invokestatic 275	com/umeng/common/ufp/b:A	(Landroid/content/Context;)I
    //   811: i2l
    //   812: invokevirtual 72	com/taobao/munion/requests/e:a	(Ljava/lang/String;J)V
    //   815: invokestatic 45	com/taobao/munion/common/MunionConfigManager:getInstance	()Lcom/taobao/munion/common/MunionConfigManager;
    //   818: invokevirtual 49	com/taobao/munion/common/MunionConfigManager:getContext	()Landroid/content/Context;
    //   821: invokestatic 349	com/umeng/common/ufp/b:H	(Landroid/content/Context;)Ljava/lang/String;
    //   824: astore_1
    //   825: aload_1
    //   826: invokestatic 61	android/text/TextUtils:isEmpty	(Ljava/lang/CharSequence;)Z
    //   829: ifne +11 -> 840
    //   832: aload_0
    //   833: ldc_w 351
    //   836: aload_1
    //   837: invokevirtual 22	com/taobao/munion/requests/e:a	(Ljava/lang/String;Ljava/lang/String;)V
    //   840: invokestatic 45	com/taobao/munion/common/MunionConfigManager:getInstance	()Lcom/taobao/munion/common/MunionConfigManager;
    //   843: invokevirtual 49	com/taobao/munion/common/MunionConfigManager:getContext	()Landroid/content/Context;
    //   846: invokestatic 354	com/umeng/common/ufp/b:o	(Landroid/content/Context;)Ljava/lang/String;
    //   849: astore_1
    //   850: aload_1
    //   851: invokestatic 61	android/text/TextUtils:isEmpty	(Ljava/lang/CharSequence;)Z
    //   854: ifne +11 -> 865
    //   857: aload_0
    //   858: ldc_w 356
    //   861: aload_1
    //   862: invokevirtual 22	com/taobao/munion/requests/e:a	(Ljava/lang/String;Ljava/lang/String;)V
    //   865: invokestatic 45	com/taobao/munion/common/MunionConfigManager:getInstance	()Lcom/taobao/munion/common/MunionConfigManager;
    //   868: invokevirtual 49	com/taobao/munion/common/MunionConfigManager:getContext	()Landroid/content/Context;
    //   871: invokestatic 358	com/umeng/common/ufp/b:n	(Landroid/content/Context;)Ljava/lang/String;
    //   874: astore_1
    //   875: aload_1
    //   876: invokestatic 61	android/text/TextUtils:isEmpty	(Ljava/lang/CharSequence;)Z
    //   879: ifne +11 -> 890
    //   882: aload_0
    //   883: ldc_w 360
    //   886: aload_1
    //   887: invokevirtual 22	com/taobao/munion/requests/e:a	(Ljava/lang/String;Ljava/lang/String;)V
    //   890: invokestatic 45	com/taobao/munion/common/MunionConfigManager:getInstance	()Lcom/taobao/munion/common/MunionConfigManager;
    //   893: invokevirtual 49	com/taobao/munion/common/MunionConfigManager:getContext	()Landroid/content/Context;
    //   896: invokestatic 363	com/umeng/common/ufp/b:p	(Landroid/content/Context;)Ljava/lang/String;
    //   899: astore_2
    //   900: aload_1
    //   901: invokestatic 61	android/text/TextUtils:isEmpty	(Ljava/lang/CharSequence;)Z
    //   904: ifne -647 -> 257
    //   907: aload_0
    //   908: ldc_w 365
    //   911: aload_2
    //   912: invokevirtual 22	com/taobao/munion/requests/e:a	(Ljava/lang/String;Ljava/lang/String;)V
    //   915: return
    //   916: aload_0
    //   917: ldc_w 261
    //   920: ldc_w 367
    //   923: invokevirtual 22	com/taobao/munion/requests/e:a	(Ljava/lang/String;Ljava/lang/String;)V
    //   926: aload_0
    //   927: ldc_w 268
    //   930: ldc_w 367
    //   933: invokevirtual 22	com/taobao/munion/requests/e:a	(Ljava/lang/String;Ljava/lang/String;)V
    //   936: goto -360 -> 576
    //   939: astore_1
    //   940: aload_0
    //   941: ldc_w 286
    //   944: ldc_w 369
    //   947: invokevirtual 22	com/taobao/munion/requests/e:a	(Ljava/lang/String;Ljava/lang/String;)V
    //   950: goto -299 -> 651
    //   953: iconst_0
    //   954: istore_3
    //   955: goto -557 -> 398
    // Local variable table:
    //   start	length	slot	name	signature
    //   0	958	0	this	e
    //   0	958	1	paramb	com.taobao.munion.model.b
    //   0	958	2	paramc	com.taobao.munion.model.c
    //   151	804	3	i	int
    //   148	8	4	j	int
    //   713	18	5	l	long
    //   143	166	7	localObject1	Object
    //   326	1	7	localException	Exception
    //   332	14	7	str	String
    //   134	160	8	localObject2	Object
    //   167	144	9	localObject3	Object
    // Exception table:
    //   from	to	target	type
    //   4	42	230	java/lang/Exception
    //   42	72	230	java/lang/Exception
    //   72	115	230	java/lang/Exception
    //   115	136	230	java/lang/Exception
    //   199	227	230	java/lang/Exception
    //   258	266	230	java/lang/Exception
    //   328	350	230	java/lang/Exception
    //   350	370	230	java/lang/Exception
    //   370	390	230	java/lang/Exception
    //   390	396	230	java/lang/Exception
    //   398	515	230	java/lang/Exception
    //   515	537	230	java/lang/Exception
    //   541	576	230	java/lang/Exception
    //   576	609	230	java/lang/Exception
    //   651	677	230	java/lang/Exception
    //   681	738	230	java/lang/Exception
    //   738	840	230	java/lang/Exception
    //   840	865	230	java/lang/Exception
    //   865	890	230	java/lang/Exception
    //   890	915	230	java/lang/Exception
    //   916	936	230	java/lang/Exception
    //   940	950	230	java/lang/Exception
    //   136	150	326	java/lang/Exception
    //   158	192	326	java/lang/Exception
    //   269	283	326	java/lang/Exception
    //   283	323	326	java/lang/Exception
    //   609	651	939	java/lang/Exception
  }
  
  protected void b() {}
}


/* Location:              E:\project\angent\dex2jar-2.0\classes-dex2jar.jar!\com\taobao\munion\requests\e.class
 * Java compiler version: 6 (50.0)
 * JD-Core Version:       0.7.1
 */